Workbook

Sheet Conceitos

Sheet Legenda
B2: Classificação | C2: D | D2: Desconhece
C3: B | D3: Bronze
C4: P | D4: Prata
C5: O | D5: Ouro
B6: Preceito | C6: 0 | D6: Desejável
C7: 1 | D7: Obrigatório
B8: Utilização | C8: A | D8: Aplicar
C9: I | D9: Ignorar
C10: N | D10: Não se Aplica

Sheet Matriz_Comportamentos
B2: CATEGORIA | C2: COMPETÊNCIAS | D2: Dev Trainee Backend | F2: Dev Júnior Backend | H2: Dev Pleno Backend | J2: Dev Sênior Backend | M2: Dev Trainee Frontend | O2: Dev Júnior Frontend | Q2: Dev Pleno Frontend | S2: Dev Sênior Frontend | V2: Q.A. Trainee | X2: Q.A. Júnior | Z2: Q.A. Pleno | AB2: Q.A. Sênior | AE2: Devops Trainee | AG2: Devops Júnior | AI2: Devops Pleno | AK2: Devops Sênior
D3: Conceito | E3: Preceito | F3: Conceito | G3: Preceito | H3: Conceito | I3: Preceito | J3: Conceito | K3: Preceito | M3: Conceito | N3: Preceito | O3: Conceito | P3: Preceito | Q3: Conceito | R3: Preceito | S3: Conceito | T3: Preceito | V3: Conceito | W3: Preceito | X3: Conceito | Y3: Preceito | Z3: Conceito | AA3: Preceito | AB3: Conceito | AC3: Preceito | AE3: Conceito | AF3: Preceito | AG3: Conceito | AH3: Preceito | AI3: Conceito | AJ3: Preceito | AK3: Conceito | AL3: Preceito
B5: Comportamentais | C5: Comunicação | D5: B | E5: 0 | F5: B | G5: 0 | H5: P | I5: 0 | J5: O | K5: 0 | M5: B | N5: 0 | O5: B | P5: 0 | Q5: P | R5: 0 | S5: O | T5: 0 | V5: B | W5: 0 | X5: B | Y5: 0 | Z5: P | AA5: 0 | AB5: O | AC5: 0 | AE5: B | AF5: 0 | AG5: B | AH5: 0 | AI5: P | AJ5: 0 | AK5: O | AL5: 0
B6: Comportamentais | C6: Confiança | D6: B | E6: 0 | F6: B | G6: 0 | H6: P | I6: 0 | J6: O | K6: 0 | M6: B | N6: 0 | O6: B | P6: 0 | Q6: P | R6: 0 | S6: O | T6: 0 | V6: B | W6: 0 | X6: B | Y6: 0 | Z6: P | AA6: 0 | AB6: O | AC6: 0 | AE6: B | AF6: 0 | AG6: B | AH6: 0 | AI6: P | AJ6: 0 | AK6: O | AL6: 0
B7: Comportamentais | C7: Desenvolvimento de Pessoas | D7: B | E7: 0 | F7: B | G7: 0 | H7: P | I7: 0 | J7: O | K7: 0 | M7: B | N7: 0 | O7: B | P7: 0 | Q7: P | R7: 0 | S7: O | T7: 0 | V7: B | W7: 0 | X7: B | Y7: 0 | Z7: P | AA7: 0 | AB7: O | AC7: 0 | AE7: B | AF7: 0 | AG7: B | AH7: 0 | AI7: P | AJ7: 0 | AK7: O | AL7: 0
B8: Comportamentais | C8: Comprometimento | D8: B | E8: 0 | F8: B | G8: 0 | H8: P | I8: 0 | J8: O | K8: 0 | M8: B | N8: 0 | O8: B | P8: 0 | Q8: P | R8: 0 | S8: O | T8: 0 | V8: B | W8: 0 | X8: B | Y8: 0 | Z8: P | AA8: 0 | AB8: O | AC8: 0 | AE8: B | AF8: 0 | AG8: B | AH8: 0 | AI8: P | AJ8: 0 | AK8: O | AL8: 0
B9: Comportamentais | C9: Protagonismo | D9: B | E9: 0 | F9: B | G9: 0 | H9: P | I9: 0 | J9: O | K9: 0 | M9: B | N9: 0 | O9: B | P9: 0 | Q9: P | R9: 0 | S9: O | T9: 0 | V9: B | W9: 0 | X9: B | Y9: 0 | Z9: P | AA9: 0 | AB9: O | AC9: 0 | AE9: B | AF9: 0 | AG9: B | AH9: 0 | AI9: P | AJ9: 0 | AK9: O | AL9: 0
B10: Comportamentais | C10: Compromisso com o Cliente | D10: B | E10: 0 | F10: B | G10: 0 | H10: P | I10: 0 | J10: O | K10: 0 | M10: B | N10: 0 | O10: B | P10: 0 | Q10: P | R10: 0 | S10: O | T10: 0 | V10: B | W10: 0 | X10: B | Y10: 0 | Z10: P | AA10: 0 | AB10: O | AC10: 0 | AE10: B | AF10: 0 | AG10: B | AH10: 0 | AI10: P | AJ10: 0 | AK10: O | AL10: 0
B12: Legenda:
B13: Símbolo | C13: Conceito | D13: Conceito Avaliação Desempenho
B14: D | C14: Desconhece | D14: Requer Melhoria
B15: B | C15: Bronze | D15: Está no Caminho
B16: P | C16: Prata | D16: Mandou Bem
B17: O | C17: Ouro | D17: Mandou Muito Bem

Sheet Matriz_Plataforma
B2: Meta 2026 | C2: CATEGORIA | D2: COMPETÊNCIAS | E2: Dev Trainee Backend | G2: Dev Júnior Backend | I2: Dev Pleno Backend | K2: Dev Sênior Backend | N2: Dev Trainee Frontend | P2: Dev Júnior Frontend | R2: Dev Pleno Frontend | T2: Dev Sênior Frontend | W2: Q.A. Trainee | Y2: Q.A. Júnior | AA2: Q.A. Pleno | AC2: Q.A. Sênior | AF2: Devops Trainee | AH2: Devops Júnior | AJ2: Devops Pleno | AL2: Devops Sênior | AO2: Dev Backend | AP2: Dev Frontend | AQ2: Q.A. | AR2: Devops | AT2: PAULO CORREIA CAMARGO JUNIOR | AV2: MARCOS ADRIANO RIBEIRO LIMA | AX2: BRUNA BRANCO | AZ2: EDIMILSON DA SILVA PEREIRA | BB2: GUILHERME ZANELLA HUGEN | BD2: RAFAEL ALDO SEROISKA | BF2: WELLENGTON JOSE MACHADO | BH2: CEDRICK QUADROS COSTA | BJ2: DAVI DOS SANTOS SILVA GONCALVES | BL2: IGOR ALESSANDRO FORGHIERI | BN2: MAURICIO DE SOUZA PERES | BP2: DIEGO DE LIZ | BR2: ADRIEL GOULART DE ABRANJO | BT2: MATHEUS BECKHAUSER NUNES | BV2: GILBERTO MOTA DE OLIVEIRA JUNIOR | BX2: FELIPE HEIDEN MAINES | BZ2: JOÃO VITOR RODRIGUES DE MORAES
E3: Conceito | F3: Preceito | G3: Conceito | H3: Preceito | I3: Conceito | J3: Preceito | K3: Conceito | L3: Preceito | N3: Conceito | O3: Preceito | P3: Conceito | Q3: Preceito | R3: Conceito | S3: Preceito | T3: Conceito | U3: Preceito | W3: Conceito | X3: Preceito | Y3: Conceito | Z3: Preceito | AA3: Conceito | AB3: Preceito | AC3: Conceito | AD3: Preceito | AF3: Conceito | AG3: Preceito | AH3: Conceito | AI3: Preceito | AJ3: Conceito | AK3: Preceito | AL3: Conceito | AM3: Preceito | AT3: =P2 -> Dev Júnior Frontend | AV3: =I2 -> Dev Pleno Backend | AX3: =R2 -> Dev Pleno Frontend | AZ3: =I2 -> Dev Pleno Backend | BB3: =AJ2 -> Devops Pleno | BD3: =AC2 -> Q.A. Sênior | BF3: =Y2 -> Q.A. Júnior | BH3: =K2 -> Dev Sênior Backend | BJ3: =Y2 -> Q.A. Júnior | BL3: =Y2 -> Q.A. Júnior | BN3: =AJ2 -> Devops Pleno | BP3: =T2 -> Dev Sênior Frontend | BR3: =I2 -> Dev Pleno Backend | BT3: =G2 -> Dev Júnior Backend | BV3: =G2 -> Dev Júnior Backend | BX3: =P2 -> Dev Júnior Frontend | BZ3: =G2 -> Dev Júnior Backend
AT4: Nível | AU4: Atinge Meta 2026 | AV4: Nível | AW4: Atinge Meta 2026 | AX4: Nível | AY4: Atinge Meta 2026 | AZ4: Nível | BA4: Atinge Meta 2026 | BB4: Nível | BC4: Atinge Meta 2026 | BD4: Nível | BE4: Atinge Meta 2026 | BF4: Nível | BG4: Atinge Meta 2026 | BH4: Nível | BI4: Atinge Meta 2026 | BJ4: Nível | BK4: Atinge Meta 2026 | BL4: Nível | BM4: Atinge Meta 2026 | BN4: Nível | BO4: Atinge Meta 2026 | BP4: Nível | BQ4: Atinge Meta 2026 | BR4: Nível | BS4: Atinge Meta 2026 | BT4: Nível | BU4: Atinge Meta 2026 | BV4: Nível | BW4: Atinge Meta 2026 | BX4: Nível | BY4: Atinge Meta 2026 | BZ4: Nível | CA4: Atinge Meta 2026
B5: Não | C5: Dev | D5: MultiThread | E5: B | F5: 0 | G5: P | H5: 1 | I5: O | J5: 1 | K5: O | L5: 1 | N5: N | O5: N | P5: N | Q5: N | R5: B | S5: 1 | T5: P | U5: 1 | W5: N | X5: N | Y5: N | Z5: N | AA5: N | AB5: N | AC5: N | AD5: N | AF5: N | AG5: N | AH5: N | AI5: N | AJ5: N | AK5: N | AL5: N | AM5: N | AO5: A | AP5: A | AQ5: I | AR5: I | AT5: P | AU5: =IF($P5="N", "N", IF($B5="Não", "Sim", IF(OR( AT5=$P5, AND($P5="B", OR(AT5="B", AT5="P", AT5="O")), AND($P5="P", OR(AT5="P", AT5="O")), AND($P5="O", AT5="O")), "Sim", "Não") ) ) -> N | AV5: O | AW5: =IF($I5="N", "N", IF($B5="Não", "Sim", IF(OR( AV5=$I5, AND($I5="B", OR(AV5="B", AV5="P", AV5="O")), AND($I5="P", OR(AV5="P", AV5="O")), AND($I5="O", AV5="O")), "Sim", "Não") ) ) -> Sim | AX5: B | AY5: =IF($R5="N", "N", IF($B5="Não", "Sim", IF(OR( AX5=$R5, AND($R5="B", OR(AX5="B", AX5="P", AX5="O")), AND($R5="P", OR(AX5="P", AX5="O")), AND($R5="O", AX5="O")), "Sim", "Não") ) ) -> Sim | AZ5: B | BA5: =IF($I5="N", "N", IF($B5="Não", "Sim", IF(OR( AZ5=$I5, AND($I5="B", OR(AZ5="B", AZ5="P", AZ5="O")), AND($I5="P", OR(AZ5="P", AZ5="O")), AND($I5="O", AZ5="O")), "Sim", "Não") ) ) -> Sim | BB5: N | BC5: =IF($AJ5="N", "N", IF($B5="Não", "Sim", IF(OR( BB5=$AJ5, AND($AJ5="B", OR(BB5="B", BB5="P", BB5="O")), AND($AJ5="P", OR(BB5="P", BB5="O")), AND($AJ5="O", BB5="O")), "Sim", "Não") ) ) -> N | BD5: N | BE5: =IF($AC5="N", "N", IF($B5="Não", "Sim", IF(OR( BD5=$AC5, AND($AC5="B", OR(BD5="B", BD5="P", BD5="O")), AND($AC5="P", OR(BD5="P", BD5="O")), AND($AC5="O", BD5="O")), "Sim", "Não") ) ) -> N | BF5: N | BG5: =IF($Y5="N", "N", IF($B5="Não", "Sim", IF(OR( BF5=$Y5, AND($Y5="B", OR(BF5="B", BF5="P", BF5="O")), AND($Y5="P", OR(BF5="P", BF5="O")), AND($Y5="O", BF5="O")), "Sim", "Não") ) ) -> N | BH5: O | BI5: =IF($K5="N", "N", IF($B5="Não", "Sim", IF(OR( BH5=$K5, AND($K5="B", OR(BH5="B", BH5="P", BH5="O")), AND($K5="P", OR(BH5="P", BH5="O")), AND($K5="O", BH5="O")), "Sim", "Não") ) ) -> Sim | BJ5: N | BK5: =IF($Y5="N", "N", IF($B5="Não", "Sim", IF(OR( BJ5=$Y5, AND($Y5="B", OR(BJ5="B", BJ5="P", BJ5="O")), AND($Y5="P", OR(BJ5="P", BJ5="O")), AND($Y5="O", BJ5="O")), "Sim", "Não") ) ) -> N | BL5: N | BM5: =IF($Y5="N", "N", IF($B5="Não", "Sim", IF(OR( BL5=$Y5, AND($Y5="B", OR(BL5="B", BL5="P", BL5="O")), AND($Y5="P", OR(BL5="P", BL5="O")), AND($Y5="O", BL5="O")), "Sim", "Não") ) ) -> N | BN5: N | BO5: =IF($AJ5="N", "N", IF($B5="Não", "Sim", IF(OR( BN5=$AJ5, AND($AJ5="B", OR(BN5="B", BN5="P", BN5="O")), AND($AJ5="P", OR(BN5="P", BN5="O")), AND($AJ5="O", BN5="O")), "Sim", "Não") ) ) -> N | BP5: P | BQ5: =IF($T5="N", "N", IF($B5="Não", "Sim", IF(OR( BP5=$T5, AND($T5="B", OR(BP5="B", BP5="P", BP5="O")), AND($T5="P", OR(BP5="P", BP5="O")), AND($T5="O", BP5="O")), "Sim", "Não") ) ) -> Sim | BR5: O | BS5: =IF($I5="N", "N", IF($B5="Não", "Sim", IF(OR( BR5=$I5, AND($I5="B", OR(BR5="B", BR5="P", BR5="O")), AND($I5="P", OR(BR5="P", BR5="O")), AND($I5="O", BR5="O")), "Sim", "Não") ) ) -> Sim | BT5: P | BU5: =IF($G5="N", "N", IF($B5="Não", "Sim", IF(OR( BT5=$G5, AND($G5="B", OR(BT5="B", BT5="P", BT5="O")), AND($G5="P", OR(BT5="P", BT5="O")), AND($G5="O", BT5="O")), "Sim", "Não") ) ) -> Sim | BV5: B | BW5: =IF($G5="N", "N", IF($B5="Não", "Sim", IF(OR( BV5=$G5, AND($G5="B", OR(BV5="B", BV5="P", BV5="O")), AND($G5="P", OR(BV5="P", BV5="O")), AND($G5="O", BV5="O")), "Sim", "Não") ) ) -> Sim | BX5: P | BY5: =IF($P5="N", "N", IF($B5="Não", "Sim", IF(OR( BX5=$P5, AND($P5="B", OR(BX5="B", BX5="P", BX5="O")), AND($P5="P", OR(BX5="P", BX5="O")), AND($P5="O", BX5="O")), "Sim", "Não") ) ) -> N | BZ5: B | CA5: =IF($G5="N", "N", IF($B5="Não", "Sim", IF(OR( BZ5=$G5, AND($G5="B", OR(BZ5="B", BZ5="P", BZ5="O")), AND($G5="P", OR(BZ5="P", BZ5="O")), AND($G5="O", BZ5="O")), "Sim", "Não") ) ) -> Sim
B6: Não | C6: Dev | D6: DDD (Domain Driven Design) | E6: B | F6: 0 | G6: B | H6: 0 | I6: B | J6: 0 | K6: P | L6: 1 | N6: N | O6: N | P6: N | Q6: N | R6: B | S6: 0 | T6: P | U6: 1 | W6: N | X6: N | Y6: N | Z6: N | AA6: N | AB6: N | AC6: N | AD6: N | AF6: N | AG6: N | AH6: N | AI6: N | AJ6: N | AK6: N | AL6: N | AM6: N | AO6: A | AP6: A | AQ6: I | AR6: I | AT6: P | AU6: =IF($P6="N", "N", IF($B6="Não", "Sim", IF(OR( AT6=$P6, AND($P6="B", OR(AT6="B", AT6="P", AT6="O")), AND($P6="P", OR(AT6="P", AT6="O")), AND($P6="O", AT6="O")), "Sim", "Não") ) ) -> N | AV6: O | AW6: =IF($I6="N", "N", IF($B6="Não", "Sim", IF(OR( AV6=$I6, AND($I6="B", OR(AV6="B", AV6="P", AV6="O")), AND($I6="P", OR(AV6="P", AV6="O")), AND($I6="O", AV6="O")), "Sim", "Não") ) ) -> Sim | AX6: B | AY6: =IF($R6="N", "N", IF($B6="Não", "Sim", IF(OR( AX6=$R6, AND($R6="B", OR(AX6="B", AX6="P", AX6="O")), AND($R6="P", OR(AX6="P", AX6="O")), AND($R6="O", AX6="O")), "Sim", "Não") ) ) -> Sim | AZ6: B | BA6: =IF($I6="N", "N", IF($B6="Não", "Sim", IF(OR( AZ6=$I6, AND($I6="B", OR(AZ6="B", AZ6="P", AZ6="O")), AND($I6="P", OR(AZ6="P", AZ6="O")), AND($I6="O", AZ6="O")), "Sim", "Não") ) ) -> Sim | BB6: N | BC6: =IF($AJ6="N", "N", IF($B6="Não", "Sim", IF(OR( BB6=$AJ6, AND($AJ6="B", OR(BB6="B", BB6="P", BB6="O")), AND($AJ6="P", OR(BB6="P", BB6="O")), AND($AJ6="O", BB6="O")), "Sim", "Não") ) ) -> N | BD6: N | BE6: =IF($AC6="N", "N", IF($B6="Não", "Sim", IF(OR( BD6=$AC6, AND($AC6="B", OR(BD6="B", BD6="P", BD6="O")), AND($AC6="P", OR(BD6="P", BD6="O")), AND($AC6="O", BD6="O")), "Sim", "Não") ) ) -> N | BF6: N | BG6: =IF($Y6="N", "N", IF($B6="Não", "Sim", IF(OR( BF6=$Y6, AND($Y6="B", OR(BF6="B", BF6="P", BF6="O")), AND($Y6="P", OR(BF6="P", BF6="O")), AND($Y6="O", BF6="O")), "Sim", "Não") ) ) -> N | BH6: P | BI6: =IF($K6="N", "N", IF($B6="Não", "Sim", IF(OR( BH6=$K6, AND($K6="B", OR(BH6="B", BH6="P", BH6="O")), AND($K6="P", OR(BH6="P", BH6="O")), AND($K6="O", BH6="O")), "Sim", "Não") ) ) -> Sim | BJ6: N | BK6: =IF($Y6="N", "N", IF($B6="Não", "Sim", IF(OR( BJ6=$Y6, AND($Y6="B", OR(BJ6="B", BJ6="P", BJ6="O")), AND($Y6="P", OR(BJ6="P", BJ6="O")), AND($Y6="O", BJ6="O")), "Sim", "Não") ) ) -> N | BL6: N | BM6: =IF($Y6="N", "N", IF($B6="Não", "Sim", IF(OR( BL6=$Y6, AND($Y6="B", OR(BL6="B", BL6="P", BL6="O")), AND($Y6="P", OR(BL6="P", BL6="O")), AND($Y6="O", BL6="O")), "Sim", "Não") ) ) -> N | BN6: N | BO6: =IF($AJ6="N", "N", IF($B6="Não", "Sim", IF(OR( BN6=$AJ6, AND($AJ6="B", OR(BN6="B", BN6="P", BN6="O")), AND($AJ6="P", OR(BN6="P", BN6="O")), AND($AJ6="O", BN6="O")), "Sim", "Não") ) ) -> N | BP6: P | BQ6: =IF($T6="N", "N", IF($B6="Não", "Sim", IF(OR( BP6=$T6, AND($T6="B", OR(BP6="B", BP6="P", BP6="O")), AND($T6="P", OR(BP6="P", BP6="O")), AND($T6="O", BP6="O")), "Sim", "Não") ) ) -> Sim | BR6: P | BS6: =IF($I6="N", "N", IF($B6="Não", "Sim", IF(OR( BR6=$I6, AND($I6="B", OR(BR6="B", BR6="P", BR6="O")), AND($I6="P", OR(BR6="P", BR6="O")), AND($I6="O", BR6="O")), "Sim", "Não") ) ) -> Sim | BT6: P | BU6: =IF($G6="N", "N", IF($B6="Não", "Sim", IF(OR( BT6=$G6, AND($G6="B", OR(BT6="B", BT6="P", BT6="O")), AND($G6="P", OR(BT6="P", BT6="O")), AND($G6="O", BT6="O")), "Sim", "Não") ) ) -> Sim | BV6: P | BW6: =IF($G6="N", "N", IF($B6="Não", "Sim", IF(OR( BV6=$G6, AND($G6="B", OR(BV6="B", BV6="P", BV6="O")), AND($G6="P", OR(BV6="P", BV6="O")), AND($G6="O", BV6="O")), "Sim", "Não") ) ) -> Sim | BX6: P | BY6: =IF($P6="N", "N", IF($B6="Não", "Sim", IF(OR( BX6=$P6, AND($P6="B", OR(BX6="B", BX6="P", BX6="O")), AND($P6="P", OR(BX6="P", BX6="O")), AND($P6="O", BX6="O")), "Sim", "Não") ) ) -> N | BZ6: P | CA6: =IF($G6="N", "N", IF($B6="Não", "Sim", IF(OR( BZ6=$G6, AND($G6="B", OR(BZ6="B", BZ6="P", BZ6="O")), AND($G6="P", OR(BZ6="P", BZ6="O")), AND($G6="O", BZ6="O")), "Sim", "Não") ) ) -> Sim
B7: Não | C7: Dev | D7: Microsserviços | E7: B | F7: 0 | G7: B | H7: 0 | I7: P | J7: 1 | K7: O | L7: 1 | N7: N | O7: N | P7: N | Q7: N | R7: B | S7: 1 | T7: P | U7: 1 | W7: N | X7: N | Y7: N | Z7: N | AA7: N | AB7: N | AC7: N | AD7: N | AF7: N | AG7: N | AH7: N | AI7: N | AJ7: N | AK7: N | AL7: N | AM7: N | AO7: A | AP7: A | AQ7: I | AR7: I | AT7: P | AU7: =IF($P7="N", "N", IF($B7="Não", "Sim", IF(OR( AT7=$P7, AND($P7="B", OR(AT7="B", AT7="P", AT7="O")), AND($P7="P", OR(AT7="P", AT7="O")), AND($P7="O", AT7="O")), "Sim", "Não") ) ) -> N | AV7: P | AW7: =IF($I7="N", "N", IF($B7="Não", "Sim", IF(OR( AV7=$I7, AND($I7="B", OR(AV7="B", AV7="P", AV7="O")), AND($I7="P", OR(AV7="P", AV7="O")), AND($I7="O", AV7="O")), "Sim", "Não") ) ) -> Sim | AX7: P | AY7: =IF($R7="N", "N", IF($B7="Não", "Sim", IF(OR( AX7=$R7, AND($R7="B", OR(AX7="B", AX7="P", AX7="O")), AND($R7="P", OR(AX7="P", AX7="O")), AND($R7="O", AX7="O")), "Sim", "Não") ) ) -> Sim | AZ7: P | BA7: =IF($I7="N", "N", IF($B7="Não", "Sim", IF(OR( AZ7=$I7, AND($I7="B", OR(AZ7="B", AZ7="P", AZ7="O")), AND($I7="P", OR(AZ7="P", AZ7="O")), AND($I7="O", AZ7="O")), "Sim", "Não") ) ) -> Sim | BB7: N | BC7: =IF($AJ7="N", "N", IF($B7="Não", "Sim", IF(OR( BB7=$AJ7, AND($AJ7="B", OR(BB7="B", BB7="P", BB7="O")), AND($AJ7="P", OR(BB7="P", BB7="O")), AND($AJ7="O", BB7="O")), "Sim", "Não") ) ) -> N | BD7: N | BE7: =IF($AC7="N", "N", IF($B7="Não", "Sim", IF(OR( BD7=$AC7, AND($AC7="B", OR(BD7="B", BD7="P", BD7="O")), AND($AC7="P", OR(BD7="P", BD7="O")), AND($AC7="O", BD7="O")), "Sim", "Não") ) ) -> N | BF7: N | BG7: =IF($Y7="N", "N", IF($B7="Não", "Sim", IF(OR( BF7=$Y7, AND($Y7="B", OR(BF7="B", BF7="P", BF7="O")), AND($Y7="P", OR(BF7="P", BF7="O")), AND($Y7="O", BF7="O")), "Sim", "Não") ) ) -> N | BH7: O | BI7: =IF($K7="N", "N", IF($B7="Não", "Sim", IF(OR( BH7=$K7, AND($K7="B", OR(BH7="B", BH7="P", BH7="O")), AND($K7="P", OR(BH7="P", BH7="O")), AND($K7="O", BH7="O")), "Sim", "Não") ) ) -> Sim | BJ7: N | BK7: =IF($Y7="N", "N", IF($B7="Não", "Sim", IF(OR( BJ7=$Y7, AND($Y7="B", OR(BJ7="B", BJ7="P", BJ7="O")), AND($Y7="P", OR(BJ7="P", BJ7="O")), AND($Y7="O", BJ7="O")), "Sim", "Não") ) ) -> N | BL7: N | BM7: =IF($Y7="N", "N", IF($B7="Não", "Sim", IF(OR( BL7=$Y7, AND($Y7="B", OR(BL7="B", BL7="P", BL7="O")), AND($Y7="P", OR(BL7="P", BL7="O")), AND($Y7="O", BL7="O")), "Sim", "Não") ) ) -> N | BN7: N | BO7: =IF($AJ7="N", "N", IF($B7="Não", "Sim", IF(OR( BN7=$AJ7, AND($AJ7="B", OR(BN7="B", BN7="P", BN7="O")), AND($AJ7="P", OR(BN7="P", BN7="O")), AND($AJ7="O", BN7="O")), "Sim", "Não") ) ) -> N | BP7: P | BQ7: =IF($T7="N", "N", IF($B7="Não", "Sim", IF(OR( BP7=$T7, AND($T7="B", OR(BP7="B", BP7="P", BP7="O")), AND($T7="P", OR(BP7="P", BP7="O")), AND($T7="O", BP7="O")), "Sim", "Não") ) ) -> Sim | BR7: O | BS7: =IF($I7="N", "N", IF($B7="Não", "Sim", IF(OR( BR7=$I7, AND($I7="B", OR(BR7="B", BR7="P", BR7="O")), AND($I7="P", OR(BR7="P", BR7="O")), AND($I7="O", BR7="O")), "Sim", "Não") ) ) -> Sim | BT7: B | BU7: =IF($G7="N", "N", IF($B7="Não", "Sim", IF(OR( BT7=$G7, AND($G7="B", OR(BT7="B", BT7="P", BT7="O")), AND($G7="P", OR(BT7="P", BT7="O")), AND($G7="O", BT7="O")), "Sim", "Não") ) ) -> Sim | BV7: B | BW7: =IF($G7="N", "N", IF($B7="Não", "Sim", IF(OR( BV7=$G7, AND($G7="B", OR(BV7="B", BV7="P", BV7="O")), AND($G7="P", OR(BV7="P", BV7="O")), AND($G7="O", BV7="O")), "Sim", "Não") ) ) -> Sim | BX7: P | BY7: =IF($P7="N", "N", IF($B7="Não", "Sim", IF(OR( BX7=$P7, AND($P7="B", OR(BX7="B", BX7="P", BX7="O")), AND($P7="P", OR(BX7="P", BX7="O")), AND($P7="O", BX7="O")), "Sim", "Não") ) ) -> N | BZ7: P | CA7: =IF($G7="N", "N", IF($B7="Não", "Sim", IF(OR( BZ7=$G7, AND($G7="B", OR(BZ7="B", BZ7="P", BZ7="O")), AND($G7="P", OR(BZ7="P", BZ7="O")), AND($G7="O", BZ7="O")), "Sim", "Não") ) ) -> Sim
B8: Não | C8: Dev | D8: Sistema de gerenciamento de Mensageria | E8: B | F8: 0 | G8: B | H8: 0 | I8: P | J8: 1 | K8: O | L8: 1 | N8: B | O8: 0 | P8: B | Q8: 0 | R8: P | S8: 1 | T8: O | U8: 1 | W8: N | X8: N | Y8: N | Z8: N | AA8: N | AB8: N | AC8: N | AD8: N | AF8: N | AG8: N | AH8: N | AI8: N | AJ8: N | AK8: N | AL8: N | AM8: N | AO8: A | AP8: A | AQ8: I | AR8: I | AT8: P | AU8: =IF($P8="N", "N", IF($B8="Não", "Sim", IF(OR( AT8=$P8, AND($P8="B", OR(AT8="B", AT8="P", AT8="O")), AND($P8="P", OR(AT8="P", AT8="O")), AND($P8="O", AT8="O")), "Sim", "Não") ) ) -> Sim | AV8: P | AW8: =IF($I8="N", "N", IF($B8="Não", "Sim", IF(OR( AV8=$I8, AND($I8="B", OR(AV8="B", AV8="P", AV8="O")), AND($I8="P", OR(AV8="P", AV8="O")), AND($I8="O", AV8="O")), "Sim", "Não") ) ) -> Sim | AX8: P | AY8: =IF($R8="N", "N", IF($B8="Não", "Sim", IF(OR( AX8=$R8, AND($R8="B", OR(AX8="B", AX8="P", AX8="O")), AND($R8="P", OR(AX8="P", AX8="O")), AND($R8="O", AX8="O")), "Sim", "Não") ) ) -> Sim | AZ8: B | BA8: =IF($I8="N", "N", IF($B8="Não", "Sim", IF(OR( AZ8=$I8, AND($I8="B", OR(AZ8="B", AZ8="P", AZ8="O")), AND($I8="P", OR(AZ8="P", AZ8="O")), AND($I8="O", AZ8="O")), "Sim", "Não") ) ) -> Sim | BB8: N | BC8: =IF($AJ8="N", "N", IF($B8="Não", "Sim", IF(OR( BB8=$AJ8, AND($AJ8="B", OR(BB8="B", BB8="P", BB8="O")), AND($AJ8="P", OR(BB8="P", BB8="O")), AND($AJ8="O", BB8="O")), "Sim", "Não") ) ) -> N | BD8: N | BE8: =IF($AC8="N", "N", IF($B8="Não", "Sim", IF(OR( BD8=$AC8, AND($AC8="B", OR(BD8="B", BD8="P", BD8="O")), AND($AC8="P", OR(BD8="P", BD8="O")), AND($AC8="O", BD8="O")), "Sim", "Não") ) ) -> N | BF8: N | BG8: =IF($Y8="N", "N", IF($B8="Não", "Sim", IF(OR( BF8=$Y8, AND($Y8="B", OR(BF8="B", BF8="P", BF8="O")), AND($Y8="P", OR(BF8="P", BF8="O")), AND($Y8="O", BF8="O")), "Sim", "Não") ) ) -> N | BH8: P | BI8: =IF($K8="N", "N", IF($B8="Não", "Sim", IF(OR( BH8=$K8, AND($K8="B", OR(BH8="B", BH8="P", BH8="O")), AND($K8="P", OR(BH8="P", BH8="O")), AND($K8="O", BH8="O")), "Sim", "Não") ) ) -> Sim | BJ8: N | BK8: =IF($Y8="N", "N", IF($B8="Não", "Sim", IF(OR( BJ8=$Y8, AND($Y8="B", OR(BJ8="B", BJ8="P", BJ8="O")), AND($Y8="P", OR(BJ8="P", BJ8="O")), AND($Y8="O", BJ8="O")), "Sim", "Não") ) ) -> N | BL8: N | BM8: =IF($Y8="N", "N", IF($B8="Não", "Sim", IF(OR( BL8=$Y8, AND($Y8="B", OR(BL8="B", BL8="P", BL8="O")), AND($Y8="P", OR(BL8="P", BL8="O")), AND($Y8="O", BL8="O")), "Sim", "Não") ) ) -> N | BN8: N | BO8: =IF($AJ8="N", "N", IF($B8="Não", "Sim", IF(OR( BN8=$AJ8, AND($AJ8="B", OR(BN8="B", BN8="P", BN8="O")), AND($AJ8="P", OR(BN8="P", BN8="O")), AND($AJ8="O", BN8="O")), "Sim", "Não") ) ) -> N | BP8: P | BQ8: =IF($T8="N", "N", IF($B8="Não", "Sim", IF(OR( BP8=$T8, AND($T8="B", OR(BP8="B", BP8="P", BP8="O")), AND($T8="P", OR(BP8="P", BP8="O")), AND($T8="O", BP8="O")), "Sim", "Não") ) ) -> Sim | BR8: P | BS8: =IF($I8="N", "N", IF($B8="Não", "Sim", IF(OR( BR8=$I8, AND($I8="B", OR(BR8="B", BR8="P", BR8="O")), AND($I8="P", OR(BR8="P", BR8="O")), AND($I8="O", BR8="O")), "Sim", "Não") ) ) -> Sim | BT8: B | BU8: =IF($G8="N", "N", IF($B8="Não", "Sim", IF(OR( BT8=$G8, AND($G8="B", OR(BT8="B", BT8="P", BT8="O")), AND($G8="P", OR(BT8="P", BT8="O")), AND($G8="O", BT8="O")), "Sim", "Não") ) ) -> Sim | BV8: B | BW8: =IF($G8="N", "N", IF($B8="Não", "Sim", IF(OR( BV8=$G8, AND($G8="B", OR(BV8="B", BV8="P", BV8="O")), AND($G8="P", OR(BV8="P", BV8="O")), AND($G8="O", BV8="O")), "Sim", "Não") ) ) -> Sim | BX8: B | BY8: =IF($P8="N", "N", IF($B8="Não", "Sim", IF(OR( BX8=$P8, AND($P8="B", OR(BX8="B", BX8="P", BX8="O")), AND($P8="P", OR(BX8="P", BX8="O")), AND($P8="O", BX8="O")), "Sim", "Não") ) ) -> Sim | BZ8: P | CA8: =IF($G8="N", "N", IF($B8="Não", "Sim", IF(OR( BZ8=$G8, AND($G8="B", OR(BZ8="B", BZ8="P", BZ8="O")), AND($G8="P", OR(BZ8="P", BZ8="O")), AND($G8="O", BZ8="O")), "Sim", "Não") ) ) -> Sim
B9: Não | C9: Dev | D9: Desenvolvimento de Web API e RESTful API's (Swagger) | E9: B | F9: 0 | G9: B | H9: 0 | I9: P | J9: 1 | K9: O | L9: 1 | N9: B | O9: 0 | P9: B | Q9: 0 | R9: P | S9: 1 | T9: O | U9: 1 | W9: N | X9: N | Y9: N | Z9: N | AA9: N | AB9: N | AC9: N | AD9: N | AF9: N | AG9: N | AH9: N | AI9: N | AJ9: N | AK9: N | AL9: N | AM9: N | AO9: A | AP9: A | AQ9: I | AR9: I | AT9: P | AU9: =IF($P9="N", "N", IF($B9="Não", "Sim", IF(OR( AT9=$P9, AND($P9="B", OR(AT9="B", AT9="P", AT9="O")), AND($P9="P", OR(AT9="P", AT9="O")), AND($P9="O", AT9="O")), "Sim", "Não") ) ) -> Sim | AV9: P | AW9: =IF($I9="N", "N", IF($B9="Não", "Sim", IF(OR( AV9=$I9, AND($I9="B", OR(AV9="B", AV9="P", AV9="O")), AND($I9="P", OR(AV9="P", AV9="O")), AND($I9="O", AV9="O")), "Sim", "Não") ) ) -> Sim | AX9: P | AY9: =IF($R9="N", "N", IF($B9="Não", "Sim", IF(OR( AX9=$R9, AND($R9="B", OR(AX9="B", AX9="P", AX9="O")), AND($R9="P", OR(AX9="P", AX9="O")), AND($R9="O", AX9="O")), "Sim", "Não") ) ) -> Sim | AZ9: O | BA9: =IF($I9="N", "N", IF($B9="Não", "Sim", IF(OR( AZ9=$I9, AND($I9="B", OR(AZ9="B", AZ9="P", AZ9="O")), AND($I9="P", OR(AZ9="P", AZ9="O")), AND($I9="O", AZ9="O")), "Sim", "Não") ) ) -> Sim | BB9: N | BC9: =IF($AJ9="N", "N", IF($B9="Não", "Sim", IF(OR( BB9=$AJ9, AND($AJ9="B", OR(BB9="B", BB9="P", BB9="O")), AND($AJ9="P", OR(BB9="P", BB9="O")), AND($AJ9="O", BB9="O")), "Sim", "Não") ) ) -> N | BD9: N | BE9: =IF($AC9="N", "N", IF($B9="Não", "Sim", IF(OR( BD9=$AC9, AND($AC9="B", OR(BD9="B", BD9="P", BD9="O")), AND($AC9="P", OR(BD9="P", BD9="O")), AND($AC9="O", BD9="O")), "Sim", "Não") ) ) -> N | BF9: N | BG9: =IF($Y9="N", "N", IF($B9="Não", "Sim", IF(OR( BF9=$Y9, AND($Y9="B", OR(BF9="B", BF9="P", BF9="O")), AND($Y9="P", OR(BF9="P", BF9="O")), AND($Y9="O", BF9="O")), "Sim", "Não") ) ) -> N | BH9: O | BI9: =IF($K9="N", "N", IF($B9="Não", "Sim", IF(OR( BH9=$K9, AND($K9="B", OR(BH9="B", BH9="P", BH9="O")), AND($K9="P", OR(BH9="P", BH9="O")), AND($K9="O", BH9="O")), "Sim", "Não") ) ) -> Sim | BJ9: N | BK9: =IF($Y9="N", "N", IF($B9="Não", "Sim", IF(OR( BJ9=$Y9, AND($Y9="B", OR(BJ9="B", BJ9="P", BJ9="O")), AND($Y9="P", OR(BJ9="P", BJ9="O")), AND($Y9="O", BJ9="O")), "Sim", "Não") ) ) -> N | BL9: N | BM9: =IF($Y9="N", "N", IF($B9="Não", "Sim", IF(OR( BL9=$Y9, AND($Y9="B", OR(BL9="B", BL9="P", BL9="O")), AND($Y9="P", OR(BL9="P", BL9="O")), AND($Y9="O", BL9="O")), "Sim", "Não") ) ) -> N | BN9: N | BO9: =IF($AJ9="N", "N", IF($B9="Não", "Sim", IF(OR( BN9=$AJ9, AND($AJ9="B", OR(BN9="B", BN9="P", BN9="O")), AND($AJ9="P", OR(BN9="P", BN9="O")), AND($AJ9="O", BN9="O")), "Sim", "Não") ) ) -> N | BP9: O | BQ9: =IF($T9="N", "N", IF($B9="Não", "Sim", IF(OR( BP9=$T9, AND($T9="B", OR(BP9="B", BP9="P", BP9="O")), AND($T9="P", OR(BP9="P", BP9="O")), AND($T9="O", BP9="O")), "Sim", "Não") ) ) -> Sim | BR9: O | BS9: =IF($I9="N", "N", IF($B9="Não", "Sim", IF(OR( BR9=$I9, AND($I9="B", OR(BR9="B", BR9="P", BR9="O")), AND($I9="P", OR(BR9="P", BR9="O")), AND($I9="O", BR9="O")), "Sim", "Não") ) ) -> Sim | BT9: B | BU9: =IF($G9="N", "N", IF($B9="Não", "Sim", IF(OR( BT9=$G9, AND($G9="B", OR(BT9="B", BT9="P", BT9="O")), AND($G9="P", OR(BT9="P", BT9="O")), AND($G9="O", BT9="O")), "Sim", "Não") ) ) -> Sim | BV9: P | BW9: =IF($G9="N", "N", IF($B9="Não", "Sim", IF(OR( BV9=$G9, AND($G9="B", OR(BV9="B", BV9="P", BV9="O")), AND($G9="P", OR(BV9="P", BV9="O")), AND($G9="O", BV9="O")), "Sim", "Não") ) ) -> Sim | BX9: P | BY9: =IF($P9="N", "N", IF($B9="Não", "Sim", IF(OR( BX9=$P9, AND($P9="B", OR(BX9="B", BX9="P", BX9="O")), AND($P9="P", OR(BX9="P", BX9="O")), AND($P9="O", BX9="O")), "Sim", "Não") ) ) -> Sim | BZ9: P | CA9: =IF($G9="N", "N", IF($B9="Não", "Sim", IF(OR( BZ9=$G9, AND($G9="B", OR(BZ9="B", BZ9="P", BZ9="O")), AND($G9="P", OR(BZ9="P", BZ9="O")), AND($G9="O", BZ9="O")), "Sim", "Não") ) ) -> Sim
B10: Não | C10: Dev | D10: Dapper | E10: B | F10: 0 | G10: B | H10: 0 | I10: P | J10: 1 | K10: O | L10: 1 | N10: B | O10: 0 | P10: B | Q10: 0 | R10: P | S10: 1 | T10: O | U10: 1 | W10: N | X10: N | Y10: N | Z10: N | AA10: N | AB10: N | AC10: N | AD10: N | AF10: N | AG10: N | AH10: N | AI10: N | AJ10: N | AK10: N | AL10: N | AM10: N | AO10: A | AP10: A | AQ10: I | AR10: I | AT10: P | AU10: =IF($P10="N", "N", IF($B10="Não", "Sim", IF(OR( AT10=$P10, AND($P10="B", OR(AT10="B", AT10="P", AT10="O")), AND($P10="P", OR(AT10="P", AT10="O")), AND($P10="O", AT10="O")), "Sim", "Não") ) ) -> Sim | AV10: P | AW10: =IF($I10="N", "N", IF($B10="Não", "Sim", IF(OR( AV10=$I10, AND($I10="B", OR(AV10="B", AV10="P", AV10="O")), AND($I10="P", OR(AV10="P", AV10="O")), AND($I10="O", AV10="O")), "Sim", "Não") ) ) -> Sim | AX10: P | AY10: =IF($R10="N", "N", IF($B10="Não", "Sim", IF(OR( AX10=$R10, AND($R10="B", OR(AX10="B", AX10="P", AX10="O")), AND($R10="P", OR(AX10="P", AX10="O")), AND($R10="O", AX10="O")), "Sim", "Não") ) ) -> Sim | AZ10: B | BA10: =IF($I10="N", "N", IF($B10="Não", "Sim", IF(OR( AZ10=$I10, AND($I10="B", OR(AZ10="B", AZ10="P", AZ10="O")), AND($I10="P", OR(AZ10="P", AZ10="O")), AND($I10="O", AZ10="O")), "Sim", "Não") ) ) -> Sim | BB10: N | BC10: =IF($AJ10="N", "N", IF($B10="Não", "Sim", IF(OR( BB10=$AJ10, AND($AJ10="B", OR(BB10="B", BB10="P", BB10="O")), AND($AJ10="P", OR(BB10="P", BB10="O")), AND($AJ10="O", BB10="O")), "Sim", "Não") ) ) -> N | BD10: N | BE10: =IF($AC10="N", "N", IF($B10="Não", "Sim", IF(OR( BD10=$AC10, AND($AC10="B", OR(BD10="B", BD10="P", BD10="O")), AND($AC10="P", OR(BD10="P", BD10="O")), AND($AC10="O", BD10="O")), "Sim", "Não") ) ) -> N | BF10: N | BG10: =IF($Y10="N", "N", IF($B10="Não", "Sim", IF(OR( BF10=$Y10, AND($Y10="B", OR(BF10="B", BF10="P", BF10="O")), AND($Y10="P", OR(BF10="P", BF10="O")), AND($Y10="O", BF10="O")), "Sim", "Não") ) ) -> N | BH10: O | BI10: =IF($K10="N", "N", IF($B10="Não", "Sim", IF(OR( BH10=$K10, AND($K10="B", OR(BH10="B", BH10="P", BH10="O")), AND($K10="P", OR(BH10="P", BH10="O")), AND($K10="O", BH10="O")), "Sim", "Não") ) ) -> Sim | BJ10: N | BK10: =IF($Y10="N", "N", IF($B10="Não", "Sim", IF(OR( BJ10=$Y10, AND($Y10="B", OR(BJ10="B", BJ10="P", BJ10="O")), AND($Y10="P", OR(BJ10="P", BJ10="O")), AND($Y10="O", BJ10="O")), "Sim", "Não") ) ) -> N | BL10: N | BM10: =IF($Y10="N", "N", IF($B10="Não", "Sim", IF(OR( BL10=$Y10, AND($Y10="B", OR(BL10="B", BL10="P", BL10="O")), AND($Y10="P", OR(BL10="P", BL10="O")), AND($Y10="O", BL10="O")), "Sim", "Não") ) ) -> N | BN10: N | BO10: =IF($AJ10="N", "N", IF($B10="Não", "Sim", IF(OR( BN10=$AJ10, AND($AJ10="B", OR(BN10="B", BN10="P", BN10="O")), AND($AJ10="P", OR(BN10="P", BN10="O")), AND($AJ10="O", BN10="O")), "Sim", "Não") ) ) -> N | BP10: O | BQ10: =IF($T10="N", "N", IF($B10="Não", "Sim", IF(OR( BP10=$T10, AND($T10="B", OR(BP10="B", BP10="P", BP10="O")), AND($T10="P", OR(BP10="P", BP10="O")), AND($T10="O", BP10="O")), "Sim", "Não") ) ) -> Sim | BR10: O | BS10: =IF($I10="N", "N", IF($B10="Não", "Sim", IF(OR( BR10=$I10, AND($I10="B", OR(BR10="B", BR10="P", BR10="O")), AND($I10="P", OR(BR10="P", BR10="O")), AND($I10="O", BR10="O")), "Sim", "Não") ) ) -> Sim | BT10: B | BU10: =IF($G10="N", "N", IF($B10="Não", "Sim", IF(OR( BT10=$G10, AND($G10="B", OR(BT10="B", BT10="P", BT10="O")), AND($G10="P", OR(BT10="P", BT10="O")), AND($G10="O", BT10="O")), "Sim", "Não") ) ) -> Sim | BV10: B | BW10: =IF($G10="N", "N", IF($B10="Não", "Sim", IF(OR( BV10=$G10, AND($G10="B", OR(BV10="B", BV10="P", BV10="O")), AND($G10="P", OR(BV10="P", BV10="O")), AND($G10="O", BV10="O")), "Sim", "Não") ) ) -> Sim | BX10: B | BY10: =IF($P10="N", "N", IF($B10="Não", "Sim", IF(OR( BX10=$P10, AND($P10="B", OR(BX10="B", BX10="P", BX10="O")), AND($P10="P", OR(BX10="P", BX10="O")), AND($P10="O", BX10="O")), "Sim", "Não") ) ) -> Sim | BZ10: O | CA10: =IF($G10="N", "N", IF($B10="Não", "Sim", IF(OR( BZ10=$G10, AND($G10="B", OR(BZ10="B", BZ10="P", BZ10="O")), AND($G10="P", OR(BZ10="P", BZ10="O")), AND($G10="O", BZ10="O")), "Sim", "Não") ) ) -> Sim
B11: Não | C11: Dev | D11: Testes Integrados automatizados | E11: B | F11: 0 | G11: B | H11: 0 | I11: P | J11: 1 | K11: P | L11: 1 | N11: N | O11: N | P11: N | Q11: N | R11: P | S11: 1 | T11: P | U11: 1 | W11: N | X11: N | Y11: N | Z11: N | AA11: N | AB11: N | AC11: N | AD11: N | AF11: N | AG11: N | AH11: N | AI11: N | AJ11: N | AK11: N | AL11: N | AM11: N | AO11: A | AP11: A | AQ11: I | AR11: I | AT11: P | AU11: =IF($P11="N", "N", IF($B11="Não", "Sim", IF(OR( AT11=$P11, AND($P11="B", OR(AT11="B", AT11="P", AT11="O")), AND($P11="P", OR(AT11="P", AT11="O")), AND($P11="O", AT11="O")), "Sim", "Não") ) ) -> N | AV11: P | AW11: =IF($I11="N", "N", IF($B11="Não", "Sim", IF(OR( AV11=$I11, AND($I11="B", OR(AV11="B", AV11="P", AV11="O")), AND($I11="P", OR(AV11="P", AV11="O")), AND($I11="O", AV11="O")), "Sim", "Não") ) ) -> Sim | AX11: P | AY11: =IF($R11="N", "N", IF($B11="Não", "Sim", IF(OR( AX11=$R11, AND($R11="B", OR(AX11="B", AX11="P", AX11="O")), AND($R11="P", OR(AX11="P", AX11="O")), AND($R11="O", AX11="O")), "Sim", "Não") ) ) -> Sim | AZ11: B | BA11: =IF($I11="N", "N", IF($B11="Não", "Sim", IF(OR( AZ11=$I11, AND($I11="B", OR(AZ11="B", AZ11="P", AZ11="O")), AND($I11="P", OR(AZ11="P", AZ11="O")), AND($I11="O", AZ11="O")), "Sim", "Não") ) ) -> Sim | BB11: N | BC11: =IF($AJ11="N", "N", IF($B11="Não", "Sim", IF(OR( BB11=$AJ11, AND($AJ11="B", OR(BB11="B", BB11="P", BB11="O")), AND($AJ11="P", OR(BB11="P", BB11="O")), AND($AJ11="O", BB11="O")), "Sim", "Não") ) ) -> N | BD11: N | BE11: =IF($AC11="N", "N", IF($B11="Não", "Sim", IF(OR( BD11=$AC11, AND($AC11="B", OR(BD11="B", BD11="P", BD11="O")), AND($AC11="P", OR(BD11="P", BD11="O")), AND($AC11="O", BD11="O")), "Sim", "Não") ) ) -> N | BF11: N | BG11: =IF($Y11="N", "N", IF($B11="Não", "Sim", IF(OR( BF11=$Y11, AND($Y11="B", OR(BF11="B", BF11="P", BF11="O")), AND($Y11="P", OR(BF11="P", BF11="O")), AND($Y11="O", BF11="O")), "Sim", "Não") ) ) -> N | BH11: P | BI11: =IF($K11="N", "N", IF($B11="Não", "Sim", IF(OR( BH11=$K11, AND($K11="B", OR(BH11="B", BH11="P", BH11="O")), AND($K11="P", OR(BH11="P", BH11="O")), AND($K11="O", BH11="O")), "Sim", "Não") ) ) -> Sim | BJ11: N | BK11: =IF($Y11="N", "N", IF($B11="Não", "Sim", IF(OR( BJ11=$Y11, AND($Y11="B", OR(BJ11="B", BJ11="P", BJ11="O")), AND($Y11="P", OR(BJ11="P", BJ11="O")), AND($Y11="O", BJ11="O")), "Sim", "Não") ) ) -> N | BL11: N | BM11: =IF($Y11="N", "N", IF($B11="Não", "Sim", IF(OR( BL11=$Y11, AND($Y11="B", OR(BL11="B", BL11="P", BL11="O")), AND($Y11="P", OR(BL11="P", BL11="O")), AND($Y11="O", BL11="O")), "Sim", "Não") ) ) -> N | BN11: N | BO11: =IF($AJ11="N", "N", IF($B11="Não", "Sim", IF(OR( BN11=$AJ11, AND($AJ11="B", OR(BN11="B", BN11="P", BN11="O")), AND($AJ11="P", OR(BN11="P", BN11="O")), AND($AJ11="O", BN11="O")), "Sim", "Não") ) ) -> N | BP11: P | BQ11: =IF($T11="N", "N", IF($B11="Não", "Sim", IF(OR( BP11=$T11, AND($T11="B", OR(BP11="B", BP11="P", BP11="O")), AND($T11="P", OR(BP11="P", BP11="O")), AND($T11="O", BP11="O")), "Sim", "Não") ) ) -> Sim | BR11: P | BS11: =IF($I11="N", "N", IF($B11="Não", "Sim", IF(OR( BR11=$I11, AND($I11="B", OR(BR11="B", BR11="P", BR11="O")), AND($I11="P", OR(BR11="P", BR11="O")), AND($I11="O", BR11="O")), "Sim", "Não") ) ) -> Sim | BT11: P | BU11: =IF($G11="N", "N", IF($B11="Não", "Sim", IF(OR( BT11=$G11, AND($G11="B", OR(BT11="B", BT11="P", BT11="O")), AND($G11="P", OR(BT11="P", BT11="O")), AND($G11="O", BT11="O")), "Sim", "Não") ) ) -> Sim | BV11: P | BW11: =IF($G11="N", "N", IF($B11="Não", "Sim", IF(OR( BV11=$G11, AND($G11="B", OR(BV11="B", BV11="P", BV11="O")), AND($G11="P", OR(BV11="P", BV11="O")), AND($G11="O", BV11="O")), "Sim", "Não") ) ) -> Sim | BX11: P | BY11: =IF($P11="N", "N", IF($B11="Não", "Sim", IF(OR( BX11=$P11, AND($P11="B", OR(BX11="B", BX11="P", BX11="O")), AND($P11="P", OR(BX11="P", BX11="O")), AND($P11="O", BX11="O")), "Sim", "Não") ) ) -> N | BZ11: O | CA11: =IF($G11="N", "N", IF($B11="Não", "Sim", IF(OR( BZ11=$G11, AND($G11="B", OR(BZ11="B", BZ11="P", BZ11="O")), AND($G11="P", OR(BZ11="P", BZ11="O")), AND($G11="O", BZ11="O")), "Sim", "Não") ) ) -> Sim
B12: Não | C12: Dev | D12: Code Review | E12: N | F12: N | G12: N | H12: N | I12: P | J12: 1 | K12: O | L12: 1 | N12: N | O12: N | P12: N | Q12: N | R12: P | S12: 1 | T12: O | U12: 1 | W12: N | X12: N | Y12: N | Z12: N | AA12: N | AB12: N | AC12: N | AD12: N | AF12: N | AG12: N | AH12: N | AI12: N | AJ12: N | AK12: N | AL12: N | AM12: N | AO12: A | AP12: A | AQ12: I | AR12: I | AT12: P | AU12: =IF($P12="N", "N", IF($B12="Não", "Sim", IF(OR( AT12=$P12, AND($P12="B", OR(AT12="B", AT12="P", AT12="O")), AND($P12="P", OR(AT12="P", AT12="O")), AND($P12="O", AT12="O")), "Sim", "Não") ) ) -> N | AV12: P | AW12: =IF($I12="N", "N", IF($B12="Não", "Sim", IF(OR( AV12=$I12, AND($I12="B", OR(AV12="B", AV12="P", AV12="O")), AND($I12="P", OR(AV12="P", AV12="O")), AND($I12="O", AV12="O")), "Sim", "Não") ) ) -> Sim | AX12: P | AY12: =IF($R12="N", "N", IF($B12="Não", "Sim", IF(OR( AX12=$R12, AND($R12="B", OR(AX12="B", AX12="P", AX12="O")), AND($R12="P", OR(AX12="P", AX12="O")), AND($R12="O", AX12="O")), "Sim", "Não") ) ) -> Sim | AZ12: O | BA12: =IF($I12="N", "N", IF($B12="Não", "Sim", IF(OR( AZ12=$I12, AND($I12="B", OR(AZ12="B", AZ12="P", AZ12="O")), AND($I12="P", OR(AZ12="P", AZ12="O")), AND($I12="O", AZ12="O")), "Sim", "Não") ) ) -> Sim | BB12: N | BC12: =IF($AJ12="N", "N", IF($B12="Não", "Sim", IF(OR( BB12=$AJ12, AND($AJ12="B", OR(BB12="B", BB12="P", BB12="O")), AND($AJ12="P", OR(BB12="P", BB12="O")), AND($AJ12="O", BB12="O")), "Sim", "Não") ) ) -> N | BD12: N | BE12: =IF($AC12="N", "N", IF($B12="Não", "Sim", IF(OR( BD12=$AC12, AND($AC12="B", OR(BD12="B", BD12="P", BD12="O")), AND($AC12="P", OR(BD12="P", BD12="O")), AND($AC12="O", BD12="O")), "Sim", "Não") ) ) -> N | BF12: N | BG12: =IF($Y12="N", "N", IF($B12="Não", "Sim", IF(OR( BF12=$Y12, AND($Y12="B", OR(BF12="B", BF12="P", BF12="O")), AND($Y12="P", OR(BF12="P", BF12="O")), AND($Y12="O", BF12="O")), "Sim", "Não") ) ) -> N | BH12: O | BI12: =IF($K12="N", "N", IF($B12="Não", "Sim", IF(OR( BH12=$K12, AND($K12="B", OR(BH12="B", BH12="P", BH12="O")), AND($K12="P", OR(BH12="P", BH12="O")), AND($K12="O", BH12="O")), "Sim", "Não") ) ) -> Sim | BJ12: N | BK12: =IF($Y12="N", "N", IF($B12="Não", "Sim", IF(OR( BJ12=$Y12, AND($Y12="B", OR(BJ12="B", BJ12="P", BJ12="O")), AND($Y12="P", OR(BJ12="P", BJ12="O")), AND($Y12="O", BJ12="O")), "Sim", "Não") ) ) -> N | BL12: N | BM12: =IF($Y12="N", "N", IF($B12="Não", "Sim", IF(OR( BL12=$Y12, AND($Y12="B", OR(BL12="B", BL12="P", BL12="O")), AND($Y12="P", OR(BL12="P", BL12="O")), AND($Y12="O", BL12="O")), "Sim", "Não") ) ) -> N | BN12: N | BO12: =IF($AJ12="N", "N", IF($B12="Não", "Sim", IF(OR( BN12=$AJ12, AND($AJ12="B", OR(BN12="B", BN12="P", BN12="O")), AND($AJ12="P", OR(BN12="P", BN12="O")), AND($AJ12="O", BN12="O")), "Sim", "Não") ) ) -> N | BP12: P | BQ12: =IF($T12="N", "N", IF($B12="Não", "Sim", IF(OR( BP12=$T12, AND($T12="B", OR(BP12="B", BP12="P", BP12="O")), AND($T12="P", OR(BP12="P", BP12="O")), AND($T12="O", BP12="O")), "Sim", "Não") ) ) -> Sim | BR12: P | BS12: =IF($I12="N", "N", IF($B12="Não", "Sim", IF(OR( BR12=$I12, AND($I12="B", OR(BR12="B", BR12="P", BR12="O")), AND($I12="P", OR(BR12="P", BR12="O")), AND($I12="O", BR12="O")), "Sim", "Não") ) ) -> Sim | BT12: P | BU12: =IF($G12="N", "N", IF($B12="Não", "Sim", IF(OR( BT12=$G12, AND($G12="B", OR(BT12="B", BT12="P", BT12="O")), AND($G12="P", OR(BT12="P", BT12="O")), AND($G12="O", BT12="O")), "Sim", "Não") ) ) -> N | BV12: B | BW12: =IF($G12="N", "N", IF($B12="Não", "Sim", IF(OR( BV12=$G12, AND($G12="B", OR(BV12="B", BV12="P", BV12="O")), AND($G12="P", OR(BV12="P", BV12="O")), AND($G12="O", BV12="O")), "Sim", "Não") ) ) -> N | BX12: P | BY12: =IF($P12="N", "N", IF($B12="Não", "Sim", IF(OR( BX12=$P12, AND($P12="B", OR(BX12="B", BX12="P", BX12="O")), AND($P12="P", OR(BX12="P", BX12="O")), AND($P12="O", BX12="O")), "Sim", "Não") ) ) -> N | BZ12: B | CA12: =IF($G12="N", "N", IF($B12="Não", "Sim", IF(OR( BZ12=$G12, AND($G12="B", OR(BZ12="B", BZ12="P", BZ12="O")), AND($G12="P", OR(BZ12="P", BZ12="O")), AND($G12="O", BZ12="O")), "Sim", "Não") ) ) -> N
B13: Não | C13: Geral | D13: Sonar: DepencyCheck | E13: N | F13: N | G13: N | H13: N | I13: N | J13: N | K13: B | L13: 1 | N13: N | O13: N | P13: N | Q13: N | R13: N | S13: N | T13: B | U13: 1 | W13: N | X13: N | Y13: N | Z13: N | AA13: B | AB13: 0 | AC13: P | AD13: 0 | AF13: N | AG13: N | AH13: B | AI13: 0 | AJ13: B | AK13: 0 | AL13: P | AM13: 0 | AO13: A | AP13: A | AQ13: A | AR13: A | AT13: D | AU13: =IF($P13="N", "N", IF($B13="Não", "Sim", IF(OR( AT13=$P13, AND($P13="B", OR(AT13="B", AT13="P", AT13="O")), AND($P13="P", OR(AT13="P", AT13="O")), AND($P13="O", AT13="O")), "Sim", "Não") ) ) -> N | AV13: B | AW13: =IF($I13="N", "N", IF($B13="Não", "Sim", IF(OR( AV13=$I13, AND($I13="B", OR(AV13="B", AV13="P", AV13="O")), AND($I13="P", OR(AV13="P", AV13="O")), AND($I13="O", AV13="O")), "Sim", "Não") ) ) -> N | AX13: B | AY13: =IF($R13="N", "N", IF($B13="Não", "Sim", IF(OR( AX13=$R13, AND($R13="B", OR(AX13="B", AX13="P", AX13="O")), AND($R13="P", OR(AX13="P", AX13="O")), AND($R13="O", AX13="O")), "Sim", "Não") ) ) -> N | AZ13: B | BA13: =IF($I13="N", "N", IF($B13="Não", "Sim", IF(OR( AZ13=$I13, AND($I13="B", OR(AZ13="B", AZ13="P", AZ13="O")), AND($I13="P", OR(AZ13="P", AZ13="O")), AND($I13="O", AZ13="O")), "Sim", "Não") ) ) -> N | BB13: B | BC13: =IF($AJ13="N", "N", IF($B13="Não", "Sim", IF(OR( BB13=$AJ13, AND($AJ13="B", OR(BB13="B", BB13="P", BB13="O")), AND($AJ13="P", OR(BB13="P", BB13="O")), AND($AJ13="O", BB13="O")), "Sim", "Não") ) ) -> Sim | BD13: P | BE13: =IF($AC13="N", "N", IF($B13="Não", "Sim", IF(OR( BD13=$AC13, AND($AC13="B", OR(BD13="B", BD13="P", BD13="O")), AND($AC13="P", OR(BD13="P", BD13="O")), AND($AC13="O", BD13="O")), "Sim", "Não") ) ) -> Sim | BF13: B | BG13: =IF($Y13="N", "N", IF($B13="Não", "Sim", IF(OR( BF13=$Y13, AND($Y13="B", OR(BF13="B", BF13="P", BF13="O")), AND($Y13="P", OR(BF13="P", BF13="O")), AND($Y13="O", BF13="O")), "Sim", "Não") ) ) -> N | BH13: P | BI13: =IF($K13="N", "N", IF($B13="Não", "Sim", IF(OR( BH13=$K13, AND($K13="B", OR(BH13="B", BH13="P", BH13="O")), AND($K13="P", OR(BH13="P", BH13="O")), AND($K13="O", BH13="O")), "Sim", "Não") ) ) -> Sim | BJ13: D | BK13: =IF($Y13="N", "N", IF($B13="Não", "Sim", IF(OR( BJ13=$Y13, AND($Y13="B", OR(BJ13="B", BJ13="P", BJ13="O")), AND($Y13="P", OR(BJ13="P", BJ13="O")), AND($Y13="O", BJ13="O")), "Sim", "Não") ) ) -> N | BL13: D | BM13: =IF($Y13="N", "N", IF($B13="Não", "Sim", IF(OR( BL13=$Y13, AND($Y13="B", OR(BL13="B", BL13="P", BL13="O")), AND($Y13="P", OR(BL13="P", BL13="O")), AND($Y13="O", BL13="O")), "Sim", "Não") ) ) -> N | BN13: B | BO13: =IF($AJ13="N", "N", IF($B13="Não", "Sim", IF(OR( BN13=$AJ13, AND($AJ13="B", OR(BN13="B", BN13="P", BN13="O")), AND($AJ13="P", OR(BN13="P", BN13="O")), AND($AJ13="O", BN13="O")), "Sim", "Não") ) ) -> Sim | BP13: B | BQ13: =IF($T13="N", "N", IF($B13="Não", "Sim", IF(OR( BP13=$T13, AND($T13="B", OR(BP13="B", BP13="P", BP13="O")), AND($T13="P", OR(BP13="P", BP13="O")), AND($T13="O", BP13="O")), "Sim", "Não") ) ) -> Sim | BR13: P | BS13: =IF($I13="N", "N", IF($B13="Não", "Sim", IF(OR( BR13=$I13, AND($I13="B", OR(BR13="B", BR13="P", BR13="O")), AND($I13="P", OR(BR13="P", BR13="O")), AND($I13="O", BR13="O")), "Sim", "Não") ) ) -> N | BT13: B | BU13: =IF($G13="N", "N", IF($B13="Não", "Sim", IF(OR( BT13=$G13, AND($G13="B", OR(BT13="B", BT13="P", BT13="O")), AND($G13="P", OR(BT13="P", BT13="O")), AND($G13="O", BT13="O")), "Sim", "Não") ) ) -> N | BV13: B | BW13: =IF($G13="N", "N", IF($B13="Não", "Sim", IF(OR( BV13=$G13, AND($G13="B", OR(BV13="B", BV13="P", BV13="O")), AND($G13="P", OR(BV13="P", BV13="O")), AND($G13="O", BV13="O")), "Sim", "Não") ) ) -> N | BX13: B | BY13: =IF($P13="N", "N", IF($B13="Não", "Sim", IF(OR( BX13=$P13, AND($P13="B", OR(BX13="B", BX13="P", BX13="O")), AND($P13="P", OR(BX13="P", BX13="O")), AND($P13="O", BX13="O")), "Sim", "Não") ) ) -> N | BZ13: B | CA13: =IF($G13="N", "N", IF($B13="Não", "Sim", IF(OR( BZ13=$G13, AND($G13="B", OR(BZ13="B", BZ13="P", BZ13="O")), AND($G13="P", OR(BZ13="P", BZ13="O")), AND($G13="O", BZ13="O")), "Sim", "Não") ) ) -> N
B14: Não | C14: Dev | D14: Boas práticas de uso de Logs | E14: B | F14: 0 | G14: B | H14: 1 | I14: P | J14: 1 | K14: O | L14: 1 | N14: B | O14: 0 | P14: B | Q14: 1 | R14: P | S14: 1 | T14: O | U14: 1 | W14: N | X14: N | Y14: N | Z14: N | AA14: N | AB14: N | AC14: N | AD14: N | AF14: N | AG14: N | AH14: N | AI14: N | AJ14: N | AK14: N | AL14: N | AM14: N | AO14: A | AP14: A | AQ14: I | AR14: I | AT14: P | AU14: =IF($P14="N", "N", IF($B14="Não", "Sim", IF(OR( AT14=$P14, AND($P14="B", OR(AT14="B", AT14="P", AT14="O")), AND($P14="P", OR(AT14="P", AT14="O")), AND($P14="O", AT14="O")), "Sim", "Não") ) ) -> Sim | AV14: O | AW14: =IF($I14="N", "N", IF($B14="Não", "Sim", IF(OR( AV14=$I14, AND($I14="B", OR(AV14="B", AV14="P", AV14="O")), AND($I14="P", OR(AV14="P", AV14="O")), AND($I14="O", AV14="O")), "Sim", "Não") ) ) -> Sim | AX14: P | AY14: =IF($R14="N", "N", IF($B14="Não", "Sim", IF(OR( AX14=$R14, AND($R14="B", OR(AX14="B", AX14="P", AX14="O")), AND($R14="P", OR(AX14="P", AX14="O")), AND($R14="O", AX14="O")), "Sim", "Não") ) ) -> Sim | AZ14: B | BA14: =IF($I14="N", "N", IF($B14="Não", "Sim", IF(OR( AZ14=$I14, AND($I14="B", OR(AZ14="B", AZ14="P", AZ14="O")), AND($I14="P", OR(AZ14="P", AZ14="O")), AND($I14="O", AZ14="O")), "Sim", "Não") ) ) -> Sim | BB14: N | BC14: =IF($AJ14="N", "N", IF($B14="Não", "Sim", IF(OR( BB14=$AJ14, AND($AJ14="B", OR(BB14="B", BB14="P", BB14="O")), AND($AJ14="P", OR(BB14="P", BB14="O")), AND($AJ14="O", BB14="O")), "Sim", "Não") ) ) -> N | BD14: N | BE14: =IF($AC14="N", "N", IF($B14="Não", "Sim", IF(OR( BD14=$AC14, AND($AC14="B", OR(BD14="B", BD14="P", BD14="O")), AND($AC14="P", OR(BD14="P", BD14="O")), AND($AC14="O", BD14="O")), "Sim", "Não") ) ) -> N | BF14: N | BG14: =IF($Y14="N", "N", IF($B14="Não", "Sim", IF(OR( BF14=$Y14, AND($Y14="B", OR(BF14="B", BF14="P", BF14="O")), AND($Y14="P", OR(BF14="P", BF14="O")), AND($Y14="O", BF14="O")), "Sim", "Não") ) ) -> N | BH14: O | BI14: =IF($K14="N", "N", IF($B14="Não", "Sim", IF(OR( BH14=$K14, AND($K14="B", OR(BH14="B", BH14="P", BH14="O")), AND($K14="P", OR(BH14="P", BH14="O")), AND($K14="O", BH14="O")), "Sim", "Não") ) ) -> Sim | BJ14: N | BK14: =IF($Y14="N", "N", IF($B14="Não", "Sim", IF(OR( BJ14=$Y14, AND($Y14="B", OR(BJ14="B", BJ14="P", BJ14="O")), AND($Y14="P", OR(BJ14="P", BJ14="O")), AND($Y14="O", BJ14="O")), "Sim", "Não") ) ) -> N | BL14: N | BM14: =IF($Y14="N", "N", IF($B14="Não", "Sim", IF(OR( BL14=$Y14, AND($Y14="B", OR(BL14="B", BL14="P", BL14="O")), AND($Y14="P", OR(BL14="P", BL14="O")), AND($Y14="O", BL14="O")), "Sim", "Não") ) ) -> N | BN14: N | BO14: =IF($AJ14="N", "N", IF($B14="Não", "Sim", IF(OR( BN14=$AJ14, AND($AJ14="B", OR(BN14="B", BN14="P", BN14="O")), AND($AJ14="P", OR(BN14="P", BN14="O")), AND($AJ14="O", BN14="O")), "Sim", "Não") ) ) -> N | BP14: P | BQ14: =IF($T14="N", "N", IF($B14="Não", "Sim", IF(OR( BP14=$T14, AND($T14="B", OR(BP14="B", BP14="P", BP14="O")), AND($T14="P", OR(BP14="P", BP14="O")), AND($T14="O", BP14="O")), "Sim", "Não") ) ) -> Sim | BR14: P | BS14: =IF($I14="N", "N", IF($B14="Não", "Sim", IF(OR( BR14=$I14, AND($I14="B", OR(BR14="B", BR14="P", BR14="O")), AND($I14="P", OR(BR14="P", BR14="O")), AND($I14="O", BR14="O")), "Sim", "Não") ) ) -> Sim | BT14: P | BU14: =IF($G14="N", "N", IF($B14="Não", "Sim", IF(OR( BT14=$G14, AND($G14="B", OR(BT14="B", BT14="P", BT14="O")), AND($G14="P", OR(BT14="P", BT14="O")), AND($G14="O", BT14="O")), "Sim", "Não") ) ) -> Sim | BV14: B | BW14: =IF($G14="N", "N", IF($B14="Não", "Sim", IF(OR( BV14=$G14, AND($G14="B", OR(BV14="B", BV14="P", BV14="O")), AND($G14="P", OR(BV14="P", BV14="O")), AND($G14="O", BV14="O")), "Sim", "Não") ) ) -> Sim | BX14: P | BY14: =IF($P14="N", "N", IF($B14="Não", "Sim", IF(OR( BX14=$P14, AND($P14="B", OR(BX14="B", BX14="P", BX14="O")), AND($P14="P", OR(BX14="P", BX14="O")), AND($P14="O", BX14="O")), "Sim", "Não") ) ) -> Sim | BZ14: O | CA14: =IF($G14="N", "N", IF($B14="Não", "Sim", IF(OR( BZ14=$G14, AND($G14="B", OR(BZ14="B", BZ14="P", BZ14="O")), AND($G14="P", OR(BZ14="P", BZ14="O")), AND($G14="O", BZ14="O")), "Sim", "Não") ) ) -> Sim
B15: Não | C15: Dev | D15: Padrões Clean Code | E15: B | F15: 0 | G15: B | H15: 0 | I15: P | J15: 1 | K15: O | L15: 1 | N15: B | O15: 0 | P15: B | Q15: 0 | R15: P | S15: 1 | T15: O | U15: 1 | W15: N | X15: N | Y15: N | Z15: N | AA15: N | AB15: N | AC15: N | AD15: N | AF15: N | AG15: N | AH15: N | AI15: N | AJ15: N | AK15: N | AL15: N | AM15: N | AO15: A | AP15: A | AQ15: I | AR15: I | AT15: P | AU15: =IF($P15="N", "N", IF($B15="Não", "Sim", IF(OR( AT15=$P15, AND($P15="B", OR(AT15="B", AT15="P", AT15="O")), AND($P15="P", OR(AT15="P", AT15="O")), AND($P15="O", AT15="O")), "Sim", "Não") ) ) -> Sim | AV15: O | AW15: =IF($I15="N", "N", IF($B15="Não", "Sim", IF(OR( AV15=$I15, AND($I15="B", OR(AV15="B", AV15="P", AV15="O")), AND($I15="P", OR(AV15="P", AV15="O")), AND($I15="O", AV15="O")), "Sim", "Não") ) ) -> Sim | AX15: P | AY15: =IF($R15="N", "N", IF($B15="Não", "Sim", IF(OR( AX15=$R15, AND($R15="B", OR(AX15="B", AX15="P", AX15="O")), AND($R15="P", OR(AX15="P", AX15="O")), AND($R15="O", AX15="O")), "Sim", "Não") ) ) -> Sim | AZ15: P | BA15: =IF($I15="N", "N", IF($B15="Não", "Sim", IF(OR( AZ15=$I15, AND($I15="B", OR(AZ15="B", AZ15="P", AZ15="O")), AND($I15="P", OR(AZ15="P", AZ15="O")), AND($I15="O", AZ15="O")), "Sim", "Não") ) ) -> Sim | BB15: N | BC15: =IF($AJ15="N", "N", IF($B15="Não", "Sim", IF(OR( BB15=$AJ15, AND($AJ15="B", OR(BB15="B", BB15="P", BB15="O")), AND($AJ15="P", OR(BB15="P", BB15="O")), AND($AJ15="O", BB15="O")), "Sim", "Não") ) ) -> N | BD15: N | BE15: =IF($AC15="N", "N", IF($B15="Não", "Sim", IF(OR( BD15=$AC15, AND($AC15="B", OR(BD15="B", BD15="P", BD15="O")), AND($AC15="P", OR(BD15="P", BD15="O")), AND($AC15="O", BD15="O")), "Sim", "Não") ) ) -> N | BF15: N | BG15: =IF($Y15="N", "N", IF($B15="Não", "Sim", IF(OR( BF15=$Y15, AND($Y15="B", OR(BF15="B", BF15="P", BF15="O")), AND($Y15="P", OR(BF15="P", BF15="O")), AND($Y15="O", BF15="O")), "Sim", "Não") ) ) -> N | BH15: P | BI15: =IF($K15="N", "N", IF($B15="Não", "Sim", IF(OR( BH15=$K15, AND($K15="B", OR(BH15="B", BH15="P", BH15="O")), AND($K15="P", OR(BH15="P", BH15="O")), AND($K15="O", BH15="O")), "Sim", "Não") ) ) -> Sim | BJ15: N | BK15: =IF($Y15="N", "N", IF($B15="Não", "Sim", IF(OR( BJ15=$Y15, AND($Y15="B", OR(BJ15="B", BJ15="P", BJ15="O")), AND($Y15="P", OR(BJ15="P", BJ15="O")), AND($Y15="O", BJ15="O")), "Sim", "Não") ) ) -> N | BL15: N | BM15: =IF($Y15="N", "N", IF($B15="Não", "Sim", IF(OR( BL15=$Y15, AND($Y15="B", OR(BL15="B", BL15="P", BL15="O")), AND($Y15="P", OR(BL15="P", BL15="O")), AND($Y15="O", BL15="O")), "Sim", "Não") ) ) -> N | BN15: N | BO15: =IF($AJ15="N", "N", IF($B15="Não", "Sim", IF(OR( BN15=$AJ15, AND($AJ15="B", OR(BN15="B", BN15="P", BN15="O")), AND($AJ15="P", OR(BN15="P", BN15="O")), AND($AJ15="O", BN15="O")), "Sim", "Não") ) ) -> N | BP15: P | BQ15: =IF($T15="N", "N", IF($B15="Não", "Sim", IF(OR( BP15=$T15, AND($T15="B", OR(BP15="B", BP15="P", BP15="O")), AND($T15="P", OR(BP15="P", BP15="O")), AND($T15="O", BP15="O")), "Sim", "Não") ) ) -> Sim | BR15: P | BS15: =IF($I15="N", "N", IF($B15="Não", "Sim", IF(OR( BR15=$I15, AND($I15="B", OR(BR15="B", BR15="P", BR15="O")), AND($I15="P", OR(BR15="P", BR15="O")), AND($I15="O", BR15="O")), "Sim", "Não") ) ) -> Sim | BT15: P | BU15: =IF($G15="N", "N", IF($B15="Não", "Sim", IF(OR( BT15=$G15, AND($G15="B", OR(BT15="B", BT15="P", BT15="O")), AND($G15="P", OR(BT15="P", BT15="O")), AND($G15="O", BT15="O")), "Sim", "Não") ) ) -> Sim | BV15: B | BW15: =IF($G15="N", "N", IF($B15="Não", "Sim", IF(OR( BV15=$G15, AND($G15="B", OR(BV15="B", BV15="P", BV15="O")), AND($G15="P", OR(BV15="P", BV15="O")), AND($G15="O", BV15="O")), "Sim", "Não") ) ) -> Sim | BX15: P | BY15: =IF($P15="N", "N", IF($B15="Não", "Sim", IF(OR( BX15=$P15, AND($P15="B", OR(BX15="B", BX15="P", BX15="O")), AND($P15="P", OR(BX15="P", BX15="O")), AND($P15="O", BX15="O")), "Sim", "Não") ) ) -> Sim | BZ15: P | CA15: =IF($G15="N", "N", IF($B15="Não", "Sim", IF(OR( BZ15=$G15, AND($G15="B", OR(BZ15="B", BZ15="P", BZ15="O")), AND($G15="P", OR(BZ15="P", BZ15="O")), AND($G15="O", BZ15="O")), "Sim", "Não") ) ) -> Sim
B16: Não | C16: Dev | D16: Padrões de projeto de software utilizando SOLID | E16: B | F16: 0 | G16: B | H16: 0 | I16: P | J16: 0 | K16: O | L16: 1 | N16: B | O16: 0 | P16: B | Q16: 0 | R16: P | S16: 0 | T16: O | U16: 1 | W16: N | X16: N | Y16: N | Z16: N | AA16: N | AB16: N | AC16: N | AD16: N | AF16: N | AG16: N | AH16: N | AI16: N | AJ16: N | AK16: N | AL16: N | AM16: N | AO16: A | AP16: A | AQ16: I | AR16: I | AT16: P | AU16: =IF($P16="N", "N", IF($B16="Não", "Sim", IF(OR( AT16=$P16, AND($P16="B", OR(AT16="B", AT16="P", AT16="O")), AND($P16="P", OR(AT16="P", AT16="O")), AND($P16="O", AT16="O")), "Sim", "Não") ) ) -> Sim | AV16: P | AW16: =IF($I16="N", "N", IF($B16="Não", "Sim", IF(OR( AV16=$I16, AND($I16="B", OR(AV16="B", AV16="P", AV16="O")), AND($I16="P", OR(AV16="P", AV16="O")), AND($I16="O", AV16="O")), "Sim", "Não") ) ) -> Sim | AX16: P | AY16: =IF($R16="N", "N", IF($B16="Não", "Sim", IF(OR( AX16=$R16, AND($R16="B", OR(AX16="B", AX16="P", AX16="O")), AND($R16="P", OR(AX16="P", AX16="O")), AND($R16="O", AX16="O")), "Sim", "Não") ) ) -> Sim | AZ16: P | BA16: =IF($I16="N", "N", IF($B16="Não", "Sim", IF(OR( AZ16=$I16, AND($I16="B", OR(AZ16="B", AZ16="P", AZ16="O")), AND($I16="P", OR(AZ16="P", AZ16="O")), AND($I16="O", AZ16="O")), "Sim", "Não") ) ) -> Sim | BB16: N | BC16: =IF($AJ16="N", "N", IF($B16="Não", "Sim", IF(OR( BB16=$AJ16, AND($AJ16="B", OR(BB16="B", BB16="P", BB16="O")), AND($AJ16="P", OR(BB16="P", BB16="O")), AND($AJ16="O", BB16="O")), "Sim", "Não") ) ) -> N | BD16: N | BE16: =IF($AC16="N", "N", IF($B16="Não", "Sim", IF(OR( BD16=$AC16, AND($AC16="B", OR(BD16="B", BD16="P", BD16="O")), AND($AC16="P", OR(BD16="P", BD16="O")), AND($AC16="O", BD16="O")), "Sim", "Não") ) ) -> N | BF16: N | BG16: =IF($Y16="N", "N", IF($B16="Não", "Sim", IF(OR( BF16=$Y16, AND($Y16="B", OR(BF16="B", BF16="P", BF16="O")), AND($Y16="P", OR(BF16="P", BF16="O")), AND($Y16="O", BF16="O")), "Sim", "Não") ) ) -> N | BH16: P | BI16: =IF($K16="N", "N", IF($B16="Não", "Sim", IF(OR( BH16=$K16, AND($K16="B", OR(BH16="B", BH16="P", BH16="O")), AND($K16="P", OR(BH16="P", BH16="O")), AND($K16="O", BH16="O")), "Sim", "Não") ) ) -> Sim | BJ16: N | BK16: =IF($Y16="N", "N", IF($B16="Não", "Sim", IF(OR( BJ16=$Y16, AND($Y16="B", OR(BJ16="B", BJ16="P", BJ16="O")), AND($Y16="P", OR(BJ16="P", BJ16="O")), AND($Y16="O", BJ16="O")), "Sim", "Não") ) ) -> N | BL16: N | BM16: =IF($Y16="N", "N", IF($B16="Não", "Sim", IF(OR( BL16=$Y16, AND($Y16="B", OR(BL16="B", BL16="P", BL16="O")), AND($Y16="P", OR(BL16="P", BL16="O")), AND($Y16="O", BL16="O")), "Sim", "Não") ) ) -> N | BN16: N | BO16: =IF($AJ16="N", "N", IF($B16="Não", "Sim", IF(OR( BN16=$AJ16, AND($AJ16="B", OR(BN16="B", BN16="P", BN16="O")), AND($AJ16="P", OR(BN16="P", BN16="O")), AND($AJ16="O", BN16="O")), "Sim", "Não") ) ) -> N | BP16: P | BQ16: =IF($T16="N", "N", IF($B16="Não", "Sim", IF(OR( BP16=$T16, AND($T16="B", OR(BP16="B", BP16="P", BP16="O")), AND($T16="P", OR(BP16="P", BP16="O")), AND($T16="O", BP16="O")), "Sim", "Não") ) ) -> Sim | BR16: P | BS16: =IF($I16="N", "N", IF($B16="Não", "Sim", IF(OR( BR16=$I16, AND($I16="B", OR(BR16="B", BR16="P", BR16="O")), AND($I16="P", OR(BR16="P", BR16="O")), AND($I16="O", BR16="O")), "Sim", "Não") ) ) -> Sim | BT16: B | BU16: =IF($G16="N", "N", IF($B16="Não", "Sim", IF(OR( BT16=$G16, AND($G16="B", OR(BT16="B", BT16="P", BT16="O")), AND($G16="P", OR(BT16="P", BT16="O")), AND($G16="O", BT16="O")), "Sim", "Não") ) ) -> Sim | BV16: P | BW16: =IF($G16="N", "N", IF($B16="Não", "Sim", IF(OR( BV16=$G16, AND($G16="B", OR(BV16="B", BV16="P", BV16="O")), AND($G16="P", OR(BV16="P", BV16="O")), AND($G16="O", BV16="O")), "Sim", "Não") ) ) -> Sim | BX16: P | BY16: =IF($P16="N", "N", IF($B16="Não", "Sim", IF(OR( BX16=$P16, AND($P16="B", OR(BX16="B", BX16="P", BX16="O")), AND($P16="P", OR(BX16="P", BX16="O")), AND($P16="O", BX16="O")), "Sim", "Não") ) ) -> Sim | BZ16: P | CA16: =IF($G16="N", "N", IF($B16="Não", "Sim", IF(OR( BZ16=$G16, AND($G16="B", OR(BZ16="B", BZ16="P", BZ16="O")), AND($G16="P", OR(BZ16="P", BZ16="O")), AND($G16="O", BZ16="O")), "Sim", "Não") ) ) -> Sim
B17: Não | C17: Geral | D17: GIT | E17: B | F17: 0 | G17: B | H17: 1 | I17: P | J17: 1 | K17: P | L17: 1 | N17: B | O17: 0 | P17: B | Q17: 1 | R17: P | S17: 1 | T17: P | U17: 1 | W17: B | X17: 0 | Y17: B | Z17: 0 | AA17: P | AB17: 0 | AC17: P | AD17: 0 | AF17: B | AG17: 0 | AH17: B | AI17: 1 | AJ17: P | AK17: 1 | AL17: P | AM17: 1 | AO17: A | AP17: A | AQ17: A | AR17: A | AT17: P | AU17: =IF($P17="N", "N", IF($B17="Não", "Sim", IF(OR( AT17=$P17, AND($P17="B", OR(AT17="B", AT17="P", AT17="O")), AND($P17="P", OR(AT17="P", AT17="O")), AND($P17="O", AT17="O")), "Sim", "Não") ) ) -> Sim | AV17: P | AW17: =IF($I17="N", "N", IF($B17="Não", "Sim", IF(OR( AV17=$I17, AND($I17="B", OR(AV17="B", AV17="P", AV17="O")), AND($I17="P", OR(AV17="P", AV17="O")), AND($I17="O", AV17="O")), "Sim", "Não") ) ) -> Sim | AX17: P | AY17: =IF($R17="N", "N", IF($B17="Não", "Sim", IF(OR( AX17=$R17, AND($R17="B", OR(AX17="B", AX17="P", AX17="O")), AND($R17="P", OR(AX17="P", AX17="O")), AND($R17="O", AX17="O")), "Sim", "Não") ) ) -> Sim | AZ17: P | BA17: =IF($I17="N", "N", IF($B17="Não", "Sim", IF(OR( AZ17=$I17, AND($I17="B", OR(AZ17="B", AZ17="P", AZ17="O")), AND($I17="P", OR(AZ17="P", AZ17="O")), AND($I17="O", AZ17="O")), "Sim", "Não") ) ) -> Sim | BB17: P | BC17: =IF($AJ17="N", "N", IF($B17="Não", "Sim", IF(OR( BB17=$AJ17, AND($AJ17="B", OR(BB17="B", BB17="P", BB17="O")), AND($AJ17="P", OR(BB17="P", BB17="O")), AND($AJ17="O", BB17="O")), "Sim", "Não") ) ) -> Sim | BD17: P | BE17: =IF($AC17="N", "N", IF($B17="Não", "Sim", IF(OR( BD17=$AC17, AND($AC17="B", OR(BD17="B", BD17="P", BD17="O")), AND($AC17="P", OR(BD17="P", BD17="O")), AND($AC17="O", BD17="O")), "Sim", "Não") ) ) -> Sim | BF17: P | BG17: =IF($Y17="N", "N", IF($B17="Não", "Sim", IF(OR( BF17=$Y17, AND($Y17="B", OR(BF17="B", BF17="P", BF17="O")), AND($Y17="P", OR(BF17="P", BF17="O")), AND($Y17="O", BF17="O")), "Sim", "Não") ) ) -> Sim | BH17: P | BI17: =IF($K17="N", "N", IF($B17="Não", "Sim", IF(OR( BH17=$K17, AND($K17="B", OR(BH17="B", BH17="P", BH17="O")), AND($K17="P", OR(BH17="P", BH17="O")), AND($K17="O", BH17="O")), "Sim", "Não") ) ) -> Sim | BJ17: B | BK17: =IF($Y17="N", "N", IF($B17="Não", "Sim", IF(OR( BJ17=$Y17, AND($Y17="B", OR(BJ17="B", BJ17="P", BJ17="O")), AND($Y17="P", OR(BJ17="P", BJ17="O")), AND($Y17="O", BJ17="O")), "Sim", "Não") ) ) -> Sim | BL17: B | BM17: =IF($Y17="N", "N", IF($B17="Não", "Sim", IF(OR( BL17=$Y17, AND($Y17="B", OR(BL17="B", BL17="P", BL17="O")), AND($Y17="P", OR(BL17="P", BL17="O")), AND($Y17="O", BL17="O")), "Sim", "Não") ) ) -> Sim | BN17: P | BO17: =IF($AJ17="N", "N", IF($B17="Não", "Sim", IF(OR( BN17=$AJ17, AND($AJ17="B", OR(BN17="B", BN17="P", BN17="O")), AND($AJ17="P", OR(BN17="P", BN17="O")), AND($AJ17="O", BN17="O")), "Sim", "Não") ) ) -> Sim | BP17: P | BQ17: =IF($T17="N", "N", IF($B17="Não", "Sim", IF(OR( BP17=$T17, AND($T17="B", OR(BP17="B", BP17="P", BP17="O")), AND($T17="P", OR(BP17="P", BP17="O")), AND($T17="O", BP17="O")), "Sim", "Não") ) ) -> Sim | BR17: O | BS17: =IF($I17="N", "N", IF($B17="Não", "Sim", IF(OR( BR17=$I17, AND($I17="B", OR(BR17="B", BR17="P", BR17="O")), AND($I17="P", OR(BR17="P", BR17="O")), AND($I17="O", BR17="O")), "Sim", "Não") ) ) -> Sim | BT17: P | BU17: =IF($G17="N", "N", IF($B17="Não", "Sim", IF(OR( BT17=$G17, AND($G17="B", OR(BT17="B", BT17="P", BT17="O")), AND($G17="P", OR(BT17="P", BT17="O")), AND($G17="O", BT17="O")), "Sim", "Não") ) ) -> Sim | BV17: P | BW17: =IF($G17="N", "N", IF($B17="Não", "Sim", IF(OR( BV17=$G17, AND($G17="B", OR(BV17="B", BV17="P", BV17="O")), AND($G17="P", OR(BV17="P", BV17="O")), AND($G17="O", BV17="O")), "Sim", "Não") ) ) -> Sim | BX17: P | BY17: =IF($P17="N", "N", IF($B17="Não", "Sim", IF(OR( BX17=$P17, AND($P17="B", OR(BX17="B", BX17="P", BX17="O")), AND($P17="P", OR(BX17="P", BX17="O")), AND($P17="O", BX17="O")), "Sim", "Não") ) ) -> Sim | BZ17: O | CA17: =IF($G17="N", "N", IF($B17="Não", "Sim", IF(OR( BZ17=$G17, AND($G17="B", OR(BZ17="B", BZ17="P", BZ17="O")), AND($G17="P", OR(BZ17="P", BZ17="O")), AND($G17="O", BZ17="O")), "Sim", "Não") ) ) -> Sim
B18: Não | C18: Geral | D18: Banco de dados Redis (Cache) | E18: B | F18: 0 | G18: B | H18: 0 | I18: P | J18: 1 | K18: P | L18: 1 | N18: B | O18: 0 | P18: B | Q18: 0 | R18: B | S18: 1 | T18: P | U18: 1 | W18: N | X18: N | Y18: B | Z18: 0 | AA18: B | AB18: 1 | AC18: P | AD18: 1 | AF18: B | AG18: 0 | AH18: B | AI18: 1 | AJ18: P | AK18: 1 | AL18: P | AM18: 1 | AO18: A | AP18: A | AQ18: A | AR18: A | AT18: B | AU18: =IF($P18="N", "N", IF($B18="Não", "Sim", IF(OR( AT18=$P18, AND($P18="B", OR(AT18="B", AT18="P", AT18="O")), AND($P18="P", OR(AT18="P", AT18="O")), AND($P18="O", AT18="O")), "Sim", "Não") ) ) -> Sim | AV18: P | AW18: =IF($I18="N", "N", IF($B18="Não", "Sim", IF(OR( AV18=$I18, AND($I18="B", OR(AV18="B", AV18="P", AV18="O")), AND($I18="P", OR(AV18="P", AV18="O")), AND($I18="O", AV18="O")), "Sim", "Não") ) ) -> Sim | AX18: B | AY18: =IF($R18="N", "N", IF($B18="Não", "Sim", IF(OR( AX18=$R18, AND($R18="B", OR(AX18="B", AX18="P", AX18="O")), AND($R18="P", OR(AX18="P", AX18="O")), AND($R18="O", AX18="O")), "Sim", "Não") ) ) -> Sim | AZ18: B | BA18: =IF($I18="N", "N", IF($B18="Não", "Sim", IF(OR( AZ18=$I18, AND($I18="B", OR(AZ18="B", AZ18="P", AZ18="O")), AND($I18="P", OR(AZ18="P", AZ18="O")), AND($I18="O", AZ18="O")), "Sim", "Não") ) ) -> Sim | BB18: P | BC18: =IF($AJ18="N", "N", IF($B18="Não", "Sim", IF(OR( BB18=$AJ18, AND($AJ18="B", OR(BB18="B", BB18="P", BB18="O")), AND($AJ18="P", OR(BB18="P", BB18="O")), AND($AJ18="O", BB18="O")), "Sim", "Não") ) ) -> Sim | BD18: P | BE18: =IF($AC18="N", "N", IF($B18="Não", "Sim", IF(OR( BD18=$AC18, AND($AC18="B", OR(BD18="B", BD18="P", BD18="O")), AND($AC18="P", OR(BD18="P", BD18="O")), AND($AC18="O", BD18="O")), "Sim", "Não") ) ) -> Sim | BF18: B | BG18: =IF($Y18="N", "N", IF($B18="Não", "Sim", IF(OR( BF18=$Y18, AND($Y18="B", OR(BF18="B", BF18="P", BF18="O")), AND($Y18="P", OR(BF18="P", BF18="O")), AND($Y18="O", BF18="O")), "Sim", "Não") ) ) -> Sim | BH18: P | BI18: =IF($K18="N", "N", IF($B18="Não", "Sim", IF(OR( BH18=$K18, AND($K18="B", OR(BH18="B", BH18="P", BH18="O")), AND($K18="P", OR(BH18="P", BH18="O")), AND($K18="O", BH18="O")), "Sim", "Não") ) ) -> Sim | BJ18: D | BK18: =IF($Y18="N", "N", IF($B18="Não", "Sim", IF(OR( BJ18=$Y18, AND($Y18="B", OR(BJ18="B", BJ18="P", BJ18="O")), AND($Y18="P", OR(BJ18="P", BJ18="O")), AND($Y18="O", BJ18="O")), "Sim", "Não") ) ) -> Sim | BL18: D | BM18: =IF($Y18="N", "N", IF($B18="Não", "Sim", IF(OR( BL18=$Y18, AND($Y18="B", OR(BL18="B", BL18="P", BL18="O")), AND($Y18="P", OR(BL18="P", BL18="O")), AND($Y18="O", BL18="O")), "Sim", "Não") ) ) -> Sim | BN18: P | BO18: =IF($AJ18="N", "N", IF($B18="Não", "Sim", IF(OR( BN18=$AJ18, AND($AJ18="B", OR(BN18="B", BN18="P", BN18="O")), AND($AJ18="P", OR(BN18="P", BN18="O")), AND($AJ18="O", BN18="O")), "Sim", "Não") ) ) -> Sim | BP18: B | BQ18: =IF($T18="N", "N", IF($B18="Não", "Sim", IF(OR( BP18=$T18, AND($T18="B", OR(BP18="B", BP18="P", BP18="O")), AND($T18="P", OR(BP18="P", BP18="O")), AND($T18="O", BP18="O")), "Sim", "Não") ) ) -> Sim | BR18: O | BS18: =IF($I18="N", "N", IF($B18="Não", "Sim", IF(OR( BR18=$I18, AND($I18="B", OR(BR18="B", BR18="P", BR18="O")), AND($I18="P", OR(BR18="P", BR18="O")), AND($I18="O", BR18="O")), "Sim", "Não") ) ) -> Sim | BT18: D | BU18: =IF($G18="N", "N", IF($B18="Não", "Sim", IF(OR( BT18=$G18, AND($G18="B", OR(BT18="B", BT18="P", BT18="O")), AND($G18="P", OR(BT18="P", BT18="O")), AND($G18="O", BT18="O")), "Sim", "Não") ) ) -> Sim | BV18: B | BW18: =IF($G18="N", "N", IF($B18="Não", "Sim", IF(OR( BV18=$G18, AND($G18="B", OR(BV18="B", BV18="P", BV18="O")), AND($G18="P", OR(BV18="P", BV18="O")), AND($G18="O", BV18="O")), "Sim", "Não") ) ) -> Sim | BX18: B | BY18: =IF($P18="N", "N", IF($B18="Não", "Sim", IF(OR( BX18=$P18, AND($P18="B", OR(BX18="B", BX18="P", BX18="O")), AND($P18="P", OR(BX18="P", BX18="O")), AND($P18="O", BX18="O")), "Sim", "Não") ) ) -> Sim | BZ18: O | CA18: =IF($G18="N", "N", IF($B18="Não", "Sim", IF(OR( BZ18=$G18, AND($G18="B", OR(BZ18="B", BZ18="P", BZ18="O")), AND($G18="P", OR(BZ18="P", BZ18="O")), AND($G18="O", BZ18="O")), "Sim", "Não") ) ) -> Sim
B19: Não | C19: Dev | D19: C# no .net LTS última versão | E19: B | F19: 1 | G19: B | H19: 1 | I19: P | J19: 1 | K19: O | L19: 1 | N19: B | O19: 0 | P19: B | Q19: 0 | R19: B | S19: 0 | T19: P | U19: 1 | W19: N | X19: N | Y19: N | Z19: N | AA19: N | AB19: N | AC19: N | AD19: N | AF19: N | AG19: N | AH19: N | AI19: N | AJ19: N | AK19: N | AL19: N | AM19: N | AO19: A | AP19: A | AQ19: I | AR19: I | AT19: P | AU19: =IF($P19="N", "N", IF($B19="Não", "Sim", IF(OR( AT19=$P19, AND($P19="B", OR(AT19="B", AT19="P", AT19="O")), AND($P19="P", OR(AT19="P", AT19="O")), AND($P19="O", AT19="O")), "Sim", "Não") ) ) -> Sim | AV19: P | AW19: =IF($I19="N", "N", IF($B19="Não", "Sim", IF(OR( AV19=$I19, AND($I19="B", OR(AV19="B", AV19="P", AV19="O")), AND($I19="P", OR(AV19="P", AV19="O")), AND($I19="O", AV19="O")), "Sim", "Não") ) ) -> Sim | AX19: P | AY19: =IF($R19="N", "N", IF($B19="Não", "Sim", IF(OR( AX19=$R19, AND($R19="B", OR(AX19="B", AX19="P", AX19="O")), AND($R19="P", OR(AX19="P", AX19="O")), AND($R19="O", AX19="O")), "Sim", "Não") ) ) -> Sim | AZ19: P | BA19: =IF($I19="N", "N", IF($B19="Não", "Sim", IF(OR( AZ19=$I19, AND($I19="B", OR(AZ19="B", AZ19="P", AZ19="O")), AND($I19="P", OR(AZ19="P", AZ19="O")), AND($I19="O", AZ19="O")), "Sim", "Não") ) ) -> Sim | BB19: N | BC19: =IF($AJ19="N", "N", IF($B19="Não", "Sim", IF(OR( BB19=$AJ19, AND($AJ19="B", OR(BB19="B", BB19="P", BB19="O")), AND($AJ19="P", OR(BB19="P", BB19="O")), AND($AJ19="O", BB19="O")), "Sim", "Não") ) ) -> N | BD19: N | BE19: =IF($AC19="N", "N", IF($B19="Não", "Sim", IF(OR( BD19=$AC19, AND($AC19="B", OR(BD19="B", BD19="P", BD19="O")), AND($AC19="P", OR(BD19="P", BD19="O")), AND($AC19="O", BD19="O")), "Sim", "Não") ) ) -> N | BF19: N | BG19: =IF($Y19="N", "N", IF($B19="Não", "Sim", IF(OR( BF19=$Y19, AND($Y19="B", OR(BF19="B", BF19="P", BF19="O")), AND($Y19="P", OR(BF19="P", BF19="O")), AND($Y19="O", BF19="O")), "Sim", "Não") ) ) -> N | BH19: P | BI19: =IF($K19="N", "N", IF($B19="Não", "Sim", IF(OR( BH19=$K19, AND($K19="B", OR(BH19="B", BH19="P", BH19="O")), AND($K19="P", OR(BH19="P", BH19="O")), AND($K19="O", BH19="O")), "Sim", "Não") ) ) -> Sim | BJ19: N | BK19: =IF($Y19="N", "N", IF($B19="Não", "Sim", IF(OR( BJ19=$Y19, AND($Y19="B", OR(BJ19="B", BJ19="P", BJ19="O")), AND($Y19="P", OR(BJ19="P", BJ19="O")), AND($Y19="O", BJ19="O")), "Sim", "Não") ) ) -> N | BL19: N | BM19: =IF($Y19="N", "N", IF($B19="Não", "Sim", IF(OR( BL19=$Y19, AND($Y19="B", OR(BL19="B", BL19="P", BL19="O")), AND($Y19="P", OR(BL19="P", BL19="O")), AND($Y19="O", BL19="O")), "Sim", "Não") ) ) -> N | BN19: N | BO19: =IF($AJ19="N", "N", IF($B19="Não", "Sim", IF(OR( BN19=$AJ19, AND($AJ19="B", OR(BN19="B", BN19="P", BN19="O")), AND($AJ19="P", OR(BN19="P", BN19="O")), AND($AJ19="O", BN19="O")), "Sim", "Não") ) ) -> N | BP19: P | BQ19: =IF($T19="N", "N", IF($B19="Não", "Sim", IF(OR( BP19=$T19, AND($T19="B", OR(BP19="B", BP19="P", BP19="O")), AND($T19="P", OR(BP19="P", BP19="O")), AND($T19="O", BP19="O")), "Sim", "Não") ) ) -> Sim | BR19: P | BS19: =IF($I19="N", "N", IF($B19="Não", "Sim", IF(OR( BR19=$I19, AND($I19="B", OR(BR19="B", BR19="P", BR19="O")), AND($I19="P", OR(BR19="P", BR19="O")), AND($I19="O", BR19="O")), "Sim", "Não") ) ) -> Sim | BT19: P | BU19: =IF($G19="N", "N", IF($B19="Não", "Sim", IF(OR( BT19=$G19, AND($G19="B", OR(BT19="B", BT19="P", BT19="O")), AND($G19="P", OR(BT19="P", BT19="O")), AND($G19="O", BT19="O")), "Sim", "Não") ) ) -> Sim | BV19: P | BW19: =IF($G19="N", "N", IF($B19="Não", "Sim", IF(OR( BV19=$G19, AND($G19="B", OR(BV19="B", BV19="P", BV19="O")), AND($G19="P", OR(BV19="P", BV19="O")), AND($G19="O", BV19="O")), "Sim", "Não") ) ) -> Sim | BX19: P | BY19: =IF($P19="N", "N", IF($B19="Não", "Sim", IF(OR( BX19=$P19, AND($P19="B", OR(BX19="B", BX19="P", BX19="O")), AND($P19="P", OR(BX19="P", BX19="O")), AND($P19="O", BX19="O")), "Sim", "Não") ) ) -> Sim | BZ19: P | CA19: =IF($G19="N", "N", IF($B19="Não", "Sim", IF(OR( BZ19=$G19, AND($G19="B", OR(BZ19="B", BZ19="P", BZ19="O")), AND($G19="P", OR(BZ19="P", BZ19="O")), AND($G19="O", BZ19="O")), "Sim", "Não") ) ) -> Sim
B20: Não | C20: Geral | D20: NUGET | E20: B | F20: 0 | G20: B | H20: 0 | I20: P | J20: 1 | K20: P | L20: 1 | N20: N | O20: N | P20: N | Q20: N | R20: N | S20: N | T20: N | U20: N | W20: N | X20: N | Y20: N | Z20: N | AA20: N | AB20: N | AC20: N | AD20: N | AF20: B | AG20: 0 | AH20: B | AI20: 0 | AJ20: B | AK20: 0 | AL20: B | AM20: 0 | AO20: A | AP20: I | AQ20: I | AR20: A | AT20: N | AU20: =IF($P20="N", "N", IF($B20="Não", "Sim", IF(OR( AT20=$P20, AND($P20="B", OR(AT20="B", AT20="P", AT20="O")), AND($P20="P", OR(AT20="P", AT20="O")), AND($P20="O", AT20="O")), "Sim", "Não") ) ) -> N | AV20: P | AW20: =IF($I20="N", "N", IF($B20="Não", "Sim", IF(OR( AV20=$I20, AND($I20="B", OR(AV20="B", AV20="P", AV20="O")), AND($I20="P", OR(AV20="P", AV20="O")), AND($I20="O", AV20="O")), "Sim", "Não") ) ) -> Sim | AX20: P | AY20: =IF($R20="N", "N", IF($B20="Não", "Sim", IF(OR( AX20=$R20, AND($R20="B", OR(AX20="B", AX20="P", AX20="O")), AND($R20="P", OR(AX20="P", AX20="O")), AND($R20="O", AX20="O")), "Sim", "Não") ) ) -> N | AZ20: B | BA20: =IF($I20="N", "N", IF($B20="Não", "Sim", IF(OR( AZ20=$I20, AND($I20="B", OR(AZ20="B", AZ20="P", AZ20="O")), AND($I20="P", OR(AZ20="P", AZ20="O")), AND($I20="O", AZ20="O")), "Sim", "Não") ) ) -> Sim | BB20: B | BC20: =IF($AJ20="N", "N", IF($B20="Não", "Sim", IF(OR( BB20=$AJ20, AND($AJ20="B", OR(BB20="B", BB20="P", BB20="O")), AND($AJ20="P", OR(BB20="P", BB20="O")), AND($AJ20="O", BB20="O")), "Sim", "Não") ) ) -> Sim | BD20: N | BE20: =IF($AC20="N", "N", IF($B20="Não", "Sim", IF(OR( BD20=$AC20, AND($AC20="B", OR(BD20="B", BD20="P", BD20="O")), AND($AC20="P", OR(BD20="P", BD20="O")), AND($AC20="O", BD20="O")), "Sim", "Não") ) ) -> N | BF20: N | BG20: =IF($Y20="N", "N", IF($B20="Não", "Sim", IF(OR( BF20=$Y20, AND($Y20="B", OR(BF20="B", BF20="P", BF20="O")), AND($Y20="P", OR(BF20="P", BF20="O")), AND($Y20="O", BF20="O")), "Sim", "Não") ) ) -> N | BH20: O | BI20: =IF($K20="N", "N", IF($B20="Não", "Sim", IF(OR( BH20=$K20, AND($K20="B", OR(BH20="B", BH20="P", BH20="O")), AND($K20="P", OR(BH20="P", BH20="O")), AND($K20="O", BH20="O")), "Sim", "Não") ) ) -> Sim | BJ20: N | BK20: =IF($Y20="N", "N", IF($B20="Não", "Sim", IF(OR( BJ20=$Y20, AND($Y20="B", OR(BJ20="B", BJ20="P", BJ20="O")), AND($Y20="P", OR(BJ20="P", BJ20="O")), AND($Y20="O", BJ20="O")), "Sim", "Não") ) ) -> N | BL20: N | BM20: =IF($Y20="N", "N", IF($B20="Não", "Sim", IF(OR( BL20=$Y20, AND($Y20="B", OR(BL20="B", BL20="P", BL20="O")), AND($Y20="P", OR(BL20="P", BL20="O")), AND($Y20="O", BL20="O")), "Sim", "Não") ) ) -> N | BN20: P | BO20: =IF($AJ20="N", "N", IF($B20="Não", "Sim", IF(OR( BN20=$AJ20, AND($AJ20="B", OR(BN20="B", BN20="P", BN20="O")), AND($AJ20="P", OR(BN20="P", BN20="O")), AND($AJ20="O", BN20="O")), "Sim", "Não") ) ) -> Sim | BP20: N | BQ20: =IF($T20="N", "N", IF($B20="Não", "Sim", IF(OR( BP20=$T20, AND($T20="B", OR(BP20="B", BP20="P", BP20="O")), AND($T20="P", OR(BP20="P", BP20="O")), AND($T20="O", BP20="O")), "Sim", "Não") ) ) -> N | BR20: P | BS20: =IF($I20="N", "N", IF($B20="Não", "Sim", IF(OR( BR20=$I20, AND($I20="B", OR(BR20="B", BR20="P", BR20="O")), AND($I20="P", OR(BR20="P", BR20="O")), AND($I20="O", BR20="O")), "Sim", "Não") ) ) -> Sim | BT20: P | BU20: =IF($G20="N", "N", IF($B20="Não", "Sim", IF(OR( BT20=$G20, AND($G20="B", OR(BT20="B", BT20="P", BT20="O")), AND($G20="P", OR(BT20="P", BT20="O")), AND($G20="O", BT20="O")), "Sim", "Não") ) ) -> Sim | BV20: P | BW20: =IF($G20="N", "N", IF($B20="Não", "Sim", IF(OR( BV20=$G20, AND($G20="B", OR(BV20="B", BV20="P", BV20="O")), AND($G20="P", OR(BV20="P", BV20="O")), AND($G20="O", BV20="O")), "Sim", "Não") ) ) -> Sim | BX20: N | BY20: =IF($P20="N", "N", IF($B20="Não", "Sim", IF(OR( BX20=$P20, AND($P20="B", OR(BX20="B", BX20="P", BX20="O")), AND($P20="P", OR(BX20="P", BX20="O")), AND($P20="O", BX20="O")), "Sim", "Não") ) ) -> N | BZ20: P | CA20: =IF($G20="N", "N", IF($B20="Não", "Sim", IF(OR( BZ20=$G20, AND($G20="B", OR(BZ20="B", BZ20="P", BZ20="O")), AND($G20="P", OR(BZ20="P", BZ20="O")), AND($G20="O", BZ20="O")), "Sim", "Não") ) ) -> Sim
B21: Não | C21: Dev | D21: Mediator (Biblioteca) | E21: B | F21: 0 | G21: B | H21: 0 | I21: B | J21: 0 | K21: P | L21: 1 | N21: B | O21: 0 | P21: B | Q21: 0 | R21: B | S21: 0 | T21: P | U21: 1 | W21: N | X21: N | Y21: N | Z21: N | AA21: N | AB21: N | AC21: N | AD21: N | AF21: N | AG21: N | AH21: N | AI21: N | AJ21: N | AK21: N | AL21: N | AM21: N | AO21: A | AP21: A | AQ21: I | AR21: I | AT21: P | AU21: =IF($P21="N", "N", IF($B21="Não", "Sim", IF(OR( AT21=$P21, AND($P21="B", OR(AT21="B", AT21="P", AT21="O")), AND($P21="P", OR(AT21="P", AT21="O")), AND($P21="O", AT21="O")), "Sim", "Não") ) ) -> Sim | AV21: P | AW21: =IF($I21="N", "N", IF($B21="Não", "Sim", IF(OR( AV21=$I21, AND($I21="B", OR(AV21="B", AV21="P", AV21="O")), AND($I21="P", OR(AV21="P", AV21="O")), AND($I21="O", AV21="O")), "Sim", "Não") ) ) -> Sim | AX21: P | AY21: =IF($R21="N", "N", IF($B21="Não", "Sim", IF(OR( AX21=$R21, AND($R21="B", OR(AX21="B", AX21="P", AX21="O")), AND($R21="P", OR(AX21="P", AX21="O")), AND($R21="O", AX21="O")), "Sim", "Não") ) ) -> Sim | AZ21: B | BA21: =IF($I21="N", "N", IF($B21="Não", "Sim", IF(OR( AZ21=$I21, AND($I21="B", OR(AZ21="B", AZ21="P", AZ21="O")), AND($I21="P", OR(AZ21="P", AZ21="O")), AND($I21="O", AZ21="O")), "Sim", "Não") ) ) -> Sim | BB21: N | BC21: =IF($AJ21="N", "N", IF($B21="Não", "Sim", IF(OR( BB21=$AJ21, AND($AJ21="B", OR(BB21="B", BB21="P", BB21="O")), AND($AJ21="P", OR(BB21="P", BB21="O")), AND($AJ21="O", BB21="O")), "Sim", "Não") ) ) -> N | BD21: N | BE21: =IF($AC21="N", "N", IF($B21="Não", "Sim", IF(OR( BD21=$AC21, AND($AC21="B", OR(BD21="B", BD21="P", BD21="O")), AND($AC21="P", OR(BD21="P", BD21="O")), AND($AC21="O", BD21="O")), "Sim", "Não") ) ) -> N | BF21: N | BG21: =IF($Y21="N", "N", IF($B21="Não", "Sim", IF(OR( BF21=$Y21, AND($Y21="B", OR(BF21="B", BF21="P", BF21="O")), AND($Y21="P", OR(BF21="P", BF21="O")), AND($Y21="O", BF21="O")), "Sim", "Não") ) ) -> N | BH21: p | BI21: =IF($K21="N", "N", IF($B21="Não", "Sim", IF(OR( BH21=$K21, AND($K21="B", OR(BH21="B", BH21="P", BH21="O")), AND($K21="P", OR(BH21="P", BH21="O")), AND($K21="O", BH21="O")), "Sim", "Não") ) ) -> Sim | BJ21: N | BK21: =IF($Y21="N", "N", IF($B21="Não", "Sim", IF(OR( BJ21=$Y21, AND($Y21="B", OR(BJ21="B", BJ21="P", BJ21="O")), AND($Y21="P", OR(BJ21="P", BJ21="O")), AND($Y21="O", BJ21="O")), "Sim", "Não") ) ) -> N | BL21: N | BM21: =IF($Y21="N", "N", IF($B21="Não", "Sim", IF(OR( BL21=$Y21, AND($Y21="B", OR(BL21="B", BL21="P", BL21="O")), AND($Y21="P", OR(BL21="P", BL21="O")), AND($Y21="O", BL21="O")), "Sim", "Não") ) ) -> N | BN21: N | BO21: =IF($AJ21="N", "N", IF($B21="Não", "Sim", IF(OR( BN21=$AJ21, AND($AJ21="B", OR(BN21="B", BN21="P", BN21="O")), AND($AJ21="P", OR(BN21="P", BN21="O")), AND($AJ21="O", BN21="O")), "Sim", "Não") ) ) -> N | BP21: P | BQ21: =IF($T21="N", "N", IF($B21="Não", "Sim", IF(OR( BP21=$T21, AND($T21="B", OR(BP21="B", BP21="P", BP21="O")), AND($T21="P", OR(BP21="P", BP21="O")), AND($T21="O", BP21="O")), "Sim", "Não") ) ) -> Sim | BR21: P | BS21: =IF($I21="N", "N", IF($B21="Não", "Sim", IF(OR( BR21=$I21, AND($I21="B", OR(BR21="B", BR21="P", BR21="O")), AND($I21="P", OR(BR21="P", BR21="O")), AND($I21="O", BR21="O")), "Sim", "Não") ) ) -> Sim | BT21: D | BU21: =IF($G21="N", "N", IF($B21="Não", "Sim", IF(OR( BT21=$G21, AND($G21="B", OR(BT21="B", BT21="P", BT21="O")), AND($G21="P", OR(BT21="P", BT21="O")), AND($G21="O", BT21="O")), "Sim", "Não") ) ) -> Sim | BV21: B | BW21: =IF($G21="N", "N", IF($B21="Não", "Sim", IF(OR( BV21=$G21, AND($G21="B", OR(BV21="B", BV21="P", BV21="O")), AND($G21="P", OR(BV21="P", BV21="O")), AND($G21="O", BV21="O")), "Sim", "Não") ) ) -> Sim | BX21: P | BY21: =IF($P21="N", "N", IF($B21="Não", "Sim", IF(OR( BX21=$P21, AND($P21="B", OR(BX21="B", BX21="P", BX21="O")), AND($P21="P", OR(BX21="P", BX21="O")), AND($P21="O", BX21="O")), "Sim", "Não") ) ) -> Sim | BZ21: O | CA21: =IF($G21="N", "N", IF($B21="Não", "Sim", IF(OR( BZ21=$G21, AND($G21="B", OR(BZ21="B", BZ21="P", BZ21="O")), AND($G21="P", OR(BZ21="P", BZ21="O")), AND($G21="O", BZ21="O")), "Sim", "Não") ) ) -> Sim
B22: Não | C22: Dev | D22: Odata | E22: B | F22: 0 | G22: B | H22: 0 | I22: P | J22: 1 | K22: P | L22: 1 | N22: B | O22: 0 | P22: B | Q22: 0 | R22: P | S22: 1 | T22: P | U22: 1 | W22: N | X22: N | Y22: N | Z22: N | AA22: N | AB22: N | AC22: N | AD22: N | AF22: N | AG22: N | AH22: N | AI22: N | AJ22: N | AK22: N | AL22: N | AM22: N | AO22: A | AP22: A | AQ22: I | AR22: I | AT22: P | AU22: =IF($P22="N", "N", IF($B22="Não", "Sim", IF(OR( AT22=$P22, AND($P22="B", OR(AT22="B", AT22="P", AT22="O")), AND($P22="P", OR(AT22="P", AT22="O")), AND($P22="O", AT22="O")), "Sim", "Não") ) ) -> Sim | AV22: P | AW22: =IF($I22="N", "N", IF($B22="Não", "Sim", IF(OR( AV22=$I22, AND($I22="B", OR(AV22="B", AV22="P", AV22="O")), AND($I22="P", OR(AV22="P", AV22="O")), AND($I22="O", AV22="O")), "Sim", "Não") ) ) -> Sim | AX22: P | AY22: =IF($R22="N", "N", IF($B22="Não", "Sim", IF(OR( AX22=$R22, AND($R22="B", OR(AX22="B", AX22="P", AX22="O")), AND($R22="P", OR(AX22="P", AX22="O")), AND($R22="O", AX22="O")), "Sim", "Não") ) ) -> Sim | AZ22: D | BA22: =IF($I22="N", "N", IF($B22="Não", "Sim", IF(OR( AZ22=$I22, AND($I22="B", OR(AZ22="B", AZ22="P", AZ22="O")), AND($I22="P", OR(AZ22="P", AZ22="O")), AND($I22="O", AZ22="O")), "Sim", "Não") ) ) -> Sim | BB22: N | BC22: =IF($AJ22="N", "N", IF($B22="Não", "Sim", IF(OR( BB22=$AJ22, AND($AJ22="B", OR(BB22="B", BB22="P", BB22="O")), AND($AJ22="P", OR(BB22="P", BB22="O")), AND($AJ22="O", BB22="O")), "Sim", "Não") ) ) -> N | BD22: N | BE22: =IF($AC22="N", "N", IF($B22="Não", "Sim", IF(OR( BD22=$AC22, AND($AC22="B", OR(BD22="B", BD22="P", BD22="O")), AND($AC22="P", OR(BD22="P", BD22="O")), AND($AC22="O", BD22="O")), "Sim", "Não") ) ) -> N | BF22: N | BG22: =IF($Y22="N", "N", IF($B22="Não", "Sim", IF(OR( BF22=$Y22, AND($Y22="B", OR(BF22="B", BF22="P", BF22="O")), AND($Y22="P", OR(BF22="P", BF22="O")), AND($Y22="O", BF22="O")), "Sim", "Não") ) ) -> N | BH22: P | BI22: =IF($K22="N", "N", IF($B22="Não", "Sim", IF(OR( BH22=$K22, AND($K22="B", OR(BH22="B", BH22="P", BH22="O")), AND($K22="P", OR(BH22="P", BH22="O")), AND($K22="O", BH22="O")), "Sim", "Não") ) ) -> Sim | BJ22: N | BK22: =IF($Y22="N", "N", IF($B22="Não", "Sim", IF(OR( BJ22=$Y22, AND($Y22="B", OR(BJ22="B", BJ22="P", BJ22="O")), AND($Y22="P", OR(BJ22="P", BJ22="O")), AND($Y22="O", BJ22="O")), "Sim", "Não") ) ) -> N | BL22: N | BM22: =IF($Y22="N", "N", IF($B22="Não", "Sim", IF(OR( BL22=$Y22, AND($Y22="B", OR(BL22="B", BL22="P", BL22="O")), AND($Y22="P", OR(BL22="P", BL22="O")), AND($Y22="O", BL22="O")), "Sim", "Não") ) ) -> N | BN22: N | BO22: =IF($AJ22="N", "N", IF($B22="Não", "Sim", IF(OR( BN22=$AJ22, AND($AJ22="B", OR(BN22="B", BN22="P", BN22="O")), AND($AJ22="P", OR(BN22="P", BN22="O")), AND($AJ22="O", BN22="O")), "Sim", "Não") ) ) -> N | BP22: P | BQ22: =IF($T22="N", "N", IF($B22="Não", "Sim", IF(OR( BP22=$T22, AND($T22="B", OR(BP22="B", BP22="P", BP22="O")), AND($T22="P", OR(BP22="P", BP22="O")), AND($T22="O", BP22="O")), "Sim", "Não") ) ) -> Sim | BR22: P | BS22: =IF($I22="N", "N", IF($B22="Não", "Sim", IF(OR( BR22=$I22, AND($I22="B", OR(BR22="B", BR22="P", BR22="O")), AND($I22="P", OR(BR22="P", BR22="O")), AND($I22="O", BR22="O")), "Sim", "Não") ) ) -> Sim | BT22: D | BU22: =IF($G22="N", "N", IF($B22="Não", "Sim", IF(OR( BT22=$G22, AND($G22="B", OR(BT22="B", BT22="P", BT22="O")), AND($G22="P", OR(BT22="P", BT22="O")), AND($G22="O", BT22="O")), "Sim", "Não") ) ) -> Sim | BV22: D | BW22: =IF($G22="N", "N", IF($B22="Não", "Sim", IF(OR( BV22=$G22, AND($G22="B", OR(BV22="B", BV22="P", BV22="O")), AND($G22="P", OR(BV22="P", BV22="O")), AND($G22="O", BV22="O")), "Sim", "Não") ) ) -> Sim | BX22: P | BY22: =IF($P22="N", "N", IF($B22="Não", "Sim", IF(OR( BX22=$P22, AND($P22="B", OR(BX22="B", BX22="P", BX22="O")), AND($P22="P", OR(BX22="P", BX22="O")), AND($P22="O", BX22="O")), "Sim", "Não") ) ) -> Sim | BZ22: D | CA22: =IF($G22="N", "N", IF($B22="Não", "Sim", IF(OR( BZ22=$G22, AND($G22="B", OR(BZ22="B", BZ22="P", BZ22="O")), AND($G22="P", OR(BZ22="P", BZ22="O")), AND($G22="O", BZ22="O")), "Sim", "Não") ) ) -> Sim
B23: Não | C23: Dev | D23: Entity Framework Core | E23: B | F23: 0 | G23: B | H23: 0 | I23: P | J23: 1 | K23: P | L23: 1 | N23: B | O23: 0 | P23: B | Q23: 0 | R23: P | S23: 1 | T23: O | U23: 1 | W23: N | X23: N | Y23: N | Z23: N | AA23: N | AB23: N | AC23: N | AD23: N | AF23: N | AG23: N | AH23: N | AI23: N | AJ23: N | AK23: N | AL23: N | AM23: N | AO23: A | AP23: A | AQ23: I | AR23: I | AT23: P | AU23: =IF($P23="N", "N", IF($B23="Não", "Sim", IF(OR( AT23=$P23, AND($P23="B", OR(AT23="B", AT23="P", AT23="O")), AND($P23="P", OR(AT23="P", AT23="O")), AND($P23="O", AT23="O")), "Sim", "Não") ) ) -> Sim | AV23: P | AW23: =IF($I23="N", "N", IF($B23="Não", "Sim", IF(OR( AV23=$I23, AND($I23="B", OR(AV23="B", AV23="P", AV23="O")), AND($I23="P", OR(AV23="P", AV23="O")), AND($I23="O", AV23="O")), "Sim", "Não") ) ) -> Sim | AX23: P | AY23: =IF($R23="N", "N", IF($B23="Não", "Sim", IF(OR( AX23=$R23, AND($R23="B", OR(AX23="B", AX23="P", AX23="O")), AND($R23="P", OR(AX23="P", AX23="O")), AND($R23="O", AX23="O")), "Sim", "Não") ) ) -> Sim | AZ23: O | BA23: =IF($I23="N", "N", IF($B23="Não", "Sim", IF(OR( AZ23=$I23, AND($I23="B", OR(AZ23="B", AZ23="P", AZ23="O")), AND($I23="P", OR(AZ23="P", AZ23="O")), AND($I23="O", AZ23="O")), "Sim", "Não") ) ) -> Sim | BB23: N | BC23: =IF($AJ23="N", "N", IF($B23="Não", "Sim", IF(OR( BB23=$AJ23, AND($AJ23="B", OR(BB23="B", BB23="P", BB23="O")), AND($AJ23="P", OR(BB23="P", BB23="O")), AND($AJ23="O", BB23="O")), "Sim", "Não") ) ) -> N | BD23: N | BE23: =IF($AC23="N", "N", IF($B23="Não", "Sim", IF(OR( BD23=$AC23, AND($AC23="B", OR(BD23="B", BD23="P", BD23="O")), AND($AC23="P", OR(BD23="P", BD23="O")), AND($AC23="O", BD23="O")), "Sim", "Não") ) ) -> N | BF23: N | BG23: =IF($Y23="N", "N", IF($B23="Não", "Sim", IF(OR( BF23=$Y23, AND($Y23="B", OR(BF23="B", BF23="P", BF23="O")), AND($Y23="P", OR(BF23="P", BF23="O")), AND($Y23="O", BF23="O")), "Sim", "Não") ) ) -> N | BH23: P | BI23: =IF($K23="N", "N", IF($B23="Não", "Sim", IF(OR( BH23=$K23, AND($K23="B", OR(BH23="B", BH23="P", BH23="O")), AND($K23="P", OR(BH23="P", BH23="O")), AND($K23="O", BH23="O")), "Sim", "Não") ) ) -> Sim | BJ23: N | BK23: =IF($Y23="N", "N", IF($B23="Não", "Sim", IF(OR( BJ23=$Y23, AND($Y23="B", OR(BJ23="B", BJ23="P", BJ23="O")), AND($Y23="P", OR(BJ23="P", BJ23="O")), AND($Y23="O", BJ23="O")), "Sim", "Não") ) ) -> N | BL23: N | BM23: =IF($Y23="N", "N", IF($B23="Não", "Sim", IF(OR( BL23=$Y23, AND($Y23="B", OR(BL23="B", BL23="P", BL23="O")), AND($Y23="P", OR(BL23="P", BL23="O")), AND($Y23="O", BL23="O")), "Sim", "Não") ) ) -> N | BN23: N | BO23: =IF($AJ23="N", "N", IF($B23="Não", "Sim", IF(OR( BN23=$AJ23, AND($AJ23="B", OR(BN23="B", BN23="P", BN23="O")), AND($AJ23="P", OR(BN23="P", BN23="O")), AND($AJ23="O", BN23="O")), "Sim", "Não") ) ) -> N | BP23: O | BQ23: =IF($T23="N", "N", IF($B23="Não", "Sim", IF(OR( BP23=$T23, AND($T23="B", OR(BP23="B", BP23="P", BP23="O")), AND($T23="P", OR(BP23="P", BP23="O")), AND($T23="O", BP23="O")), "Sim", "Não") ) ) -> Sim | BR23: P | BS23: =IF($I23="N", "N", IF($B23="Não", "Sim", IF(OR( BR23=$I23, AND($I23="B", OR(BR23="B", BR23="P", BR23="O")), AND($I23="P", OR(BR23="P", BR23="O")), AND($I23="O", BR23="O")), "Sim", "Não") ) ) -> Sim | BT23: P | BU23: =IF($G23="N", "N", IF($B23="Não", "Sim", IF(OR( BT23=$G23, AND($G23="B", OR(BT23="B", BT23="P", BT23="O")), AND($G23="P", OR(BT23="P", BT23="O")), AND($G23="O", BT23="O")), "Sim", "Não") ) ) -> Sim | BV23: P | BW23: =IF($G23="N", "N", IF($B23="Não", "Sim", IF(OR( BV23=$G23, AND($G23="B", OR(BV23="B", BV23="P", BV23="O")), AND($G23="P", OR(BV23="P", BV23="O")), AND($G23="O", BV23="O")), "Sim", "Não") ) ) -> Sim | BX23: P | BY23: =IF($P23="N", "N", IF($B23="Não", "Sim", IF(OR( BX23=$P23, AND($P23="B", OR(BX23="B", BX23="P", BX23="O")), AND($P23="P", OR(BX23="P", BX23="O")), AND($P23="O", BX23="O")), "Sim", "Não") ) ) -> Sim | BZ23: B | CA23: =IF($G23="N", "N", IF($B23="Não", "Sim", IF(OR( BZ23=$G23, AND($G23="B", OR(BZ23="B", BZ23="P", BZ23="O")), AND($G23="P", OR(BZ23="P", BZ23="O")), AND($G23="O", BZ23="O")), "Sim", "Não") ) ) -> Sim
B24: Não | C24: Geral | D24: Ferramentas de Monitoramento ex: APP Insights ou Grafana | E24: N | F24: N | G24: N | H24: N | I24: B | J24: 0 | K24: P | L24: 1 | N24: N | O24: N | P24: N | Q24: N | R24: B | S24: 0 | T24: P | U24: 1 | W24: N | X24: N | Y24: B | Z24: 0 | AA24: B | AB24: 0 | AC24: B | AD24: 0 | AF24: N | AG24: N | AH24: N | AI24: N | AJ24: B | AK24: 0 | AL24: P | AM24: 0 | AO24: A | AP24: A | AQ24: A | AR24: A | AT24: B | AU24: =IF($P24="N", "N", IF($B24="Não", "Sim", IF(OR( AT24=$P24, AND($P24="B", OR(AT24="B", AT24="P", AT24="O")), AND($P24="P", OR(AT24="P", AT24="O")), AND($P24="O", AT24="O")), "Sim", "Não") ) ) -> N | AV24: B | AW24: =IF($I24="N", "N", IF($B24="Não", "Sim", IF(OR( AV24=$I24, AND($I24="B", OR(AV24="B", AV24="P", AV24="O")), AND($I24="P", OR(AV24="P", AV24="O")), AND($I24="O", AV24="O")), "Sim", "Não") ) ) -> Sim | AX24: P | AY24: =IF($R24="N", "N", IF($B24="Não", "Sim", IF(OR( AX24=$R24, AND($R24="B", OR(AX24="B", AX24="P", AX24="O")), AND($R24="P", OR(AX24="P", AX24="O")), AND($R24="O", AX24="O")), "Sim", "Não") ) ) -> Sim | AZ24: B | BA24: =IF($I24="N", "N", IF($B24="Não", "Sim", IF(OR( AZ24=$I24, AND($I24="B", OR(AZ24="B", AZ24="P", AZ24="O")), AND($I24="P", OR(AZ24="P", AZ24="O")), AND($I24="O", AZ24="O")), "Sim", "Não") ) ) -> Sim | BB24: P | BC24: =IF($AJ24="N", "N", IF($B24="Não", "Sim", IF(OR( BB24=$AJ24, AND($AJ24="B", OR(BB24="B", BB24="P", BB24="O")), AND($AJ24="P", OR(BB24="P", BB24="O")), AND($AJ24="O", BB24="O")), "Sim", "Não") ) ) -> Sim | BD24: B | BE24: =IF($AC24="N", "N", IF($B24="Não", "Sim", IF(OR( BD24=$AC24, AND($AC24="B", OR(BD24="B", BD24="P", BD24="O")), AND($AC24="P", OR(BD24="P", BD24="O")), AND($AC24="O", BD24="O")), "Sim", "Não") ) ) -> Sim | BF24: D | BG24: =IF($Y24="N", "N", IF($B24="Não", "Sim", IF(OR( BF24=$Y24, AND($Y24="B", OR(BF24="B", BF24="P", BF24="O")), AND($Y24="P", OR(BF24="P", BF24="O")), AND($Y24="O", BF24="O")), "Sim", "Não") ) ) -> Sim | BH24: B | BI24: =IF($K24="N", "N", IF($B24="Não", "Sim", IF(OR( BH24=$K24, AND($K24="B", OR(BH24="B", BH24="P", BH24="O")), AND($K24="P", OR(BH24="P", BH24="O")), AND($K24="O", BH24="O")), "Sim", "Não") ) ) -> Sim | BJ24: B | BK24: =IF($Y24="N", "N", IF($B24="Não", "Sim", IF(OR( BJ24=$Y24, AND($Y24="B", OR(BJ24="B", BJ24="P", BJ24="O")), AND($Y24="P", OR(BJ24="P", BJ24="O")), AND($Y24="O", BJ24="O")), "Sim", "Não") ) ) -> Sim | BL24: D | BM24: =IF($Y24="N", "N", IF($B24="Não", "Sim", IF(OR( BL24=$Y24, AND($Y24="B", OR(BL24="B", BL24="P", BL24="O")), AND($Y24="P", OR(BL24="P", BL24="O")), AND($Y24="O", BL24="O")), "Sim", "Não") ) ) -> Sim | BN24: O | BO24: =IF($AJ24="N", "N", IF($B24="Não", "Sim", IF(OR( BN24=$AJ24, AND($AJ24="B", OR(BN24="B", BN24="P", BN24="O")), AND($AJ24="P", OR(BN24="P", BN24="O")), AND($AJ24="O", BN24="O")), "Sim", "Não") ) ) -> Sim | BP24: B | BQ24: =IF($T24="N", "N", IF($B24="Não", "Sim", IF(OR( BP24=$T24, AND($T24="B", OR(BP24="B", BP24="P", BP24="O")), AND($T24="P", OR(BP24="P", BP24="O")), AND($T24="O", BP24="O")), "Sim", "Não") ) ) -> Sim | BR24: D | BS24: =IF($I24="N", "N", IF($B24="Não", "Sim", IF(OR( BR24=$I24, AND($I24="B", OR(BR24="B", BR24="P", BR24="O")), AND($I24="P", OR(BR24="P", BR24="O")), AND($I24="O", BR24="O")), "Sim", "Não") ) ) -> Sim | BT24: B | BU24: =IF($G24="N", "N", IF($B24="Não", "Sim", IF(OR( BT24=$G24, AND($G24="B", OR(BT24="B", BT24="P", BT24="O")), AND($G24="P", OR(BT24="P", BT24="O")), AND($G24="O", BT24="O")), "Sim", "Não") ) ) -> N | BV24: D | BW24: =IF($G24="N", "N", IF($B24="Não", "Sim", IF(OR( BV24=$G24, AND($G24="B", OR(BV24="B", BV24="P", BV24="O")), AND($G24="P", OR(BV24="P", BV24="O")), AND($G24="O", BV24="O")), "Sim", "Não") ) ) -> N | BX24: B | BY24: =IF($P24="N", "N", IF($B24="Não", "Sim", IF(OR( BX24=$P24, AND($P24="B", OR(BX24="B", BX24="P", BX24="O")), AND($P24="P", OR(BX24="P", BX24="O")), AND($P24="O", BX24="O")), "Sim", "Não") ) ) -> N | BZ24: D | CA24: =IF($G24="N", "N", IF($B24="Não", "Sim", IF(OR( BZ24=$G24, AND($G24="B", OR(BZ24="B", BZ24="P", BZ24="O")), AND($G24="P", OR(BZ24="P", BZ24="O")), AND($G24="O", BZ24="O")), "Sim", "Não") ) ) -> N
B25: Não | C25: Dev | D25: Angular | E25: N | F25: N | G25: N | H25: N | I25: N | J25: N | K25: N | L25: N | N25: B | O25: 1 | P25: P | Q25: 1 | R25: P | S25: 1 | T25: O | U25: 1 | W25: N | X25: N | Y25: N | Z25: N | AA25: N | AB25: N | AC25: N | AD25: N | AF25: N | AG25: N | AH25: N | AI25: N | AJ25: N | AK25: N | AL25: N | AM25: N | AO25: I | AP25: A | AQ25: I | AR25: I | AT25: P | AU25: =IF($P25="N", "N", IF($B25="Não", "Sim", IF(OR( AT25=$P25, AND($P25="B", OR(AT25="B", AT25="P", AT25="O")), AND($P25="P", OR(AT25="P", AT25="O")), AND($P25="O", AT25="O")), "Sim", "Não") ) ) -> Sim | AV25: N | AW25: =IF($I25="N", "N", IF($B25="Não", "Sim", IF(OR( AV25=$I25, AND($I25="B", OR(AV25="B", AV25="P", AV25="O")), AND($I25="P", OR(AV25="P", AV25="O")), AND($I25="O", AV25="O")), "Sim", "Não") ) ) -> N | AX25: P | AY25: =IF($R25="N", "N", IF($B25="Não", "Sim", IF(OR( AX25=$R25, AND($R25="B", OR(AX25="B", AX25="P", AX25="O")), AND($R25="P", OR(AX25="P", AX25="O")), AND($R25="O", AX25="O")), "Sim", "Não") ) ) -> Sim | AZ25: N | BA25: =IF($I25="N", "N", IF($B25="Não", "Sim", IF(OR( AZ25=$I25, AND($I25="B", OR(AZ25="B", AZ25="P", AZ25="O")), AND($I25="P", OR(AZ25="P", AZ25="O")), AND($I25="O", AZ25="O")), "Sim", "Não") ) ) -> N | BB25: N | BC25: =IF($AJ25="N", "N", IF($B25="Não", "Sim", IF(OR( BB25=$AJ25, AND($AJ25="B", OR(BB25="B", BB25="P", BB25="O")), AND($AJ25="P", OR(BB25="P", BB25="O")), AND($AJ25="O", BB25="O")), "Sim", "Não") ) ) -> N | BD25: N | BE25: =IF($AC25="N", "N", IF($B25="Não", "Sim", IF(OR( BD25=$AC25, AND($AC25="B", OR(BD25="B", BD25="P", BD25="O")), AND($AC25="P", OR(BD25="P", BD25="O")), AND($AC25="O", BD25="O")), "Sim", "Não") ) ) -> N | BF25: N | BG25: =IF($Y25="N", "N", IF($B25="Não", "Sim", IF(OR( BF25=$Y25, AND($Y25="B", OR(BF25="B", BF25="P", BF25="O")), AND($Y25="P", OR(BF25="P", BF25="O")), AND($Y25="O", BF25="O")), "Sim", "Não") ) ) -> N | BH25: N | BI25: =IF($K25="N", "N", IF($B25="Não", "Sim", IF(OR( BH25=$K25, AND($K25="B", OR(BH25="B", BH25="P", BH25="O")), AND($K25="P", OR(BH25="P", BH25="O")), AND($K25="O", BH25="O")), "Sim", "Não") ) ) -> N | BJ25: N | BK25: =IF($Y25="N", "N", IF($B25="Não", "Sim", IF(OR( BJ25=$Y25, AND($Y25="B", OR(BJ25="B", BJ25="P", BJ25="O")), AND($Y25="P", OR(BJ25="P", BJ25="O")), AND($Y25="O", BJ25="O")), "Sim", "Não") ) ) -> N | BL25: N | BM25: =IF($Y25="N", "N", IF($B25="Não", "Sim", IF(OR( BL25=$Y25, AND($Y25="B", OR(BL25="B", BL25="P", BL25="O")), AND($Y25="P", OR(BL25="P", BL25="O")), AND($Y25="O", BL25="O")), "Sim", "Não") ) ) -> N | BN25: N | BO25: =IF($AJ25="N", "N", IF($B25="Não", "Sim", IF(OR( BN25=$AJ25, AND($AJ25="B", OR(BN25="B", BN25="P", BN25="O")), AND($AJ25="P", OR(BN25="P", BN25="O")), AND($AJ25="O", BN25="O")), "Sim", "Não") ) ) -> N | BP25: O | BQ25: =IF($T25="N", "N", IF($B25="Não", "Sim", IF(OR( BP25=$T25, AND($T25="B", OR(BP25="B", BP25="P", BP25="O")), AND($T25="P", OR(BP25="P", BP25="O")), AND($T25="O", BP25="O")), "Sim", "Não") ) ) -> Sim | BR25: N | BS25: =IF($I25="N", "N", IF($B25="Não", "Sim", IF(OR( BR25=$I25, AND($I25="B", OR(BR25="B", BR25="P", BR25="O")), AND($I25="P", OR(BR25="P", BR25="O")), AND($I25="O", BR25="O")), "Sim", "Não") ) ) -> N | BT25: N | BU25: =IF($G25="N", "N", IF($B25="Não", "Sim", IF(OR( BT25=$G25, AND($G25="B", OR(BT25="B", BT25="P", BT25="O")), AND($G25="P", OR(BT25="P", BT25="O")), AND($G25="O", BT25="O")), "Sim", "Não") ) ) -> N | BV25: N | BW25: =IF($G25="N", "N", IF($B25="Não", "Sim", IF(OR( BV25=$G25, AND($G25="B", OR(BV25="B", BV25="P", BV25="O")), AND($G25="P", OR(BV25="P", BV25="O")), AND($G25="O", BV25="O")), "Sim", "Não") ) ) -> N | BX25: P | BY25: =IF($P25="N", "N", IF($B25="Não", "Sim", IF(OR( BX25=$P25, AND($P25="B", OR(BX25="B", BX25="P", BX25="O")), AND($P25="P", OR(BX25="P", BX25="O")), AND($P25="O", BX25="O")), "Sim", "Não") ) ) -> Sim | BZ25: N | CA25: =IF($G25="N", "N", IF($B25="Não", "Sim", IF(OR( BZ25=$G25, AND($G25="B", OR(BZ25="B", BZ25="P", BZ25="O")), AND($G25="P", OR(BZ25="P", BZ25="O")), AND($G25="O", BZ25="O")), "Sim", "Não") ) ) -> N
B26: Não | C26: Dev | D26: NDK/NDS | E26: N | F26: N | G26: N | H26: N | I26: N | J26: N | K26: N | L26: N | N26: B | O26: 0 | P26: B | Q26: 0 | R26: B | S26: 0 | T26: P | U26: 1 | W26: N | X26: N | Y26: N | Z26: N | AA26: N | AB26: N | AC26: N | AD26: N | AF26: N | AG26: N | AH26: N | AI26: N | AJ26: N | AK26: N | AL26: N | AM26: N | AO26: I | AP26: A | AQ26: I | AR26: I | AT26: P | AU26: =IF($P26="N", "N", IF($B26="Não", "Sim", IF(OR( AT26=$P26, AND($P26="B", OR(AT26="B", AT26="P", AT26="O")), AND($P26="P", OR(AT26="P", AT26="O")), AND($P26="O", AT26="O")), "Sim", "Não") ) ) -> Sim | AV26: N | AW26: =IF($I26="N", "N", IF($B26="Não", "Sim", IF(OR( AV26=$I26, AND($I26="B", OR(AV26="B", AV26="P", AV26="O")), AND($I26="P", OR(AV26="P", AV26="O")), AND($I26="O", AV26="O")), "Sim", "Não") ) ) -> N | AX26: O | AY26: =IF($R26="N", "N", IF($B26="Não", "Sim", IF(OR( AX26=$R26, AND($R26="B", OR(AX26="B", AX26="P", AX26="O")), AND($R26="P", OR(AX26="P", AX26="O")), AND($R26="O", AX26="O")), "Sim", "Não") ) ) -> Sim | AZ26: N | BA26: =IF($I26="N", "N", IF($B26="Não", "Sim", IF(OR( AZ26=$I26, AND($I26="B", OR(AZ26="B", AZ26="P", AZ26="O")), AND($I26="P", OR(AZ26="P", AZ26="O")), AND($I26="O", AZ26="O")), "Sim", "Não") ) ) -> N | BB26: N | BC26: =IF($AJ26="N", "N", IF($B26="Não", "Sim", IF(OR( BB26=$AJ26, AND($AJ26="B", OR(BB26="B", BB26="P", BB26="O")), AND($AJ26="P", OR(BB26="P", BB26="O")), AND($AJ26="O", BB26="O")), "Sim", "Não") ) ) -> N | BD26: N | BE26: =IF($AC26="N", "N", IF($B26="Não", "Sim", IF(OR( BD26=$AC26, AND($AC26="B", OR(BD26="B", BD26="P", BD26="O")), AND($AC26="P", OR(BD26="P", BD26="O")), AND($AC26="O", BD26="O")), "Sim", "Não") ) ) -> N | BF26: N | BG26: =IF($Y26="N", "N", IF($B26="Não", "Sim", IF(OR( BF26=$Y26, AND($Y26="B", OR(BF26="B", BF26="P", BF26="O")), AND($Y26="P", OR(BF26="P", BF26="O")), AND($Y26="O", BF26="O")), "Sim", "Não") ) ) -> N | BH26: N | BI26: =IF($K26="N", "N", IF($B26="Não", "Sim", IF(OR( BH26=$K26, AND($K26="B", OR(BH26="B", BH26="P", BH26="O")), AND($K26="P", OR(BH26="P", BH26="O")), AND($K26="O", BH26="O")), "Sim", "Não") ) ) -> N | BJ26: N | BK26: =IF($Y26="N", "N", IF($B26="Não", "Sim", IF(OR( BJ26=$Y26, AND($Y26="B", OR(BJ26="B", BJ26="P", BJ26="O")), AND($Y26="P", OR(BJ26="P", BJ26="O")), AND($Y26="O", BJ26="O")), "Sim", "Não") ) ) -> N | BL26: N | BM26: =IF($Y26="N", "N", IF($B26="Não", "Sim", IF(OR( BL26=$Y26, AND($Y26="B", OR(BL26="B", BL26="P", BL26="O")), AND($Y26="P", OR(BL26="P", BL26="O")), AND($Y26="O", BL26="O")), "Sim", "Não") ) ) -> N | BN26: N | BO26: =IF($AJ26="N", "N", IF($B26="Não", "Sim", IF(OR( BN26=$AJ26, AND($AJ26="B", OR(BN26="B", BN26="P", BN26="O")), AND($AJ26="P", OR(BN26="P", BN26="O")), AND($AJ26="O", BN26="O")), "Sim", "Não") ) ) -> N | BP26: P | BQ26: =IF($T26="N", "N", IF($B26="Não", "Sim", IF(OR( BP26=$T26, AND($T26="B", OR(BP26="B", BP26="P", BP26="O")), AND($T26="P", OR(BP26="P", BP26="O")), AND($T26="O", BP26="O")), "Sim", "Não") ) ) -> Sim | BR26: N | BS26: =IF($I26="N", "N", IF($B26="Não", "Sim", IF(OR( BR26=$I26, AND($I26="B", OR(BR26="B", BR26="P", BR26="O")), AND($I26="P", OR(BR26="P", BR26="O")), AND($I26="O", BR26="O")), "Sim", "Não") ) ) -> N | BT26: N | BU26: =IF($G26="N", "N", IF($B26="Não", "Sim", IF(OR( BT26=$G26, AND($G26="B", OR(BT26="B", BT26="P", BT26="O")), AND($G26="P", OR(BT26="P", BT26="O")), AND($G26="O", BT26="O")), "Sim", "Não") ) ) -> N | BV26: N | BW26: =IF($G26="N", "N", IF($B26="Não", "Sim", IF(OR( BV26=$G26, AND($G26="B", OR(BV26="B", BV26="P", BV26="O")), AND($G26="P", OR(BV26="P", BV26="O")), AND($G26="O", BV26="O")), "Sim", "Não") ) ) -> N | BX26: P | BY26: =IF($P26="N", "N", IF($B26="Não", "Sim", IF(OR( BX26=$P26, AND($P26="B", OR(BX26="B", BX26="P", BX26="O")), AND($P26="P", OR(BX26="P", BX26="O")), AND($P26="O", BX26="O")), "Sim", "Não") ) ) -> Sim | BZ26: N | CA26: =IF($G26="N", "N", IF($B26="Não", "Sim", IF(OR( BZ26=$G26, AND($G26="B", OR(BZ26="B", BZ26="P", BZ26="O")), AND($G26="P", OR(BZ26="P", BZ26="O")), AND($G26="O", BZ26="O")), "Sim", "Não") ) ) -> N
B27: Não | C27: Dev | D27: Bootstrap, Flexbox e CSS | E27: N | F27: N | G27: N | H27: N | I27: N | J27: N | K27: N | L27: N | N27: B | O27: 0 | P27: B | Q27: 0 | R27: B | S27: 0 | T27: P | U27: 1 | W27: N | X27: N | Y27: N | Z27: N | AA27: N | AB27: N | AC27: N | AD27: N | AF27: N | AG27: N | AH27: N | AI27: N | AJ27: N | AK27: N | AL27: N | AM27: N | AO27: I | AP27: A | AQ27: I | AR27: I | AT27: P | AU27: =IF($P27="N", "N", IF($B27="Não", "Sim", IF(OR( AT27=$P27, AND($P27="B", OR(AT27="B", AT27="P", AT27="O")), AND($P27="P", OR(AT27="P", AT27="O")), AND($P27="O", AT27="O")), "Sim", "Não") ) ) -> Sim | AV27: N | AW27: =IF($I27="N", "N", IF($B27="Não", "Sim", IF(OR( AV27=$I27, AND($I27="B", OR(AV27="B", AV27="P", AV27="O")), AND($I27="P", OR(AV27="P", AV27="O")), AND($I27="O", AV27="O")), "Sim", "Não") ) ) -> N | AX27: P | AY27: =IF($R27="N", "N", IF($B27="Não", "Sim", IF(OR( AX27=$R27, AND($R27="B", OR(AX27="B", AX27="P", AX27="O")), AND($R27="P", OR(AX27="P", AX27="O")), AND($R27="O", AX27="O")), "Sim", "Não") ) ) -> Sim | AZ27: N | BA27: =IF($I27="N", "N", IF($B27="Não", "Sim", IF(OR( AZ27=$I27, AND($I27="B", OR(AZ27="B", AZ27="P", AZ27="O")), AND($I27="P", OR(AZ27="P", AZ27="O")), AND($I27="O", AZ27="O")), "Sim", "Não") ) ) -> N | BB27: N | BC27: =IF($AJ27="N", "N", IF($B27="Não", "Sim", IF(OR( BB27=$AJ27, AND($AJ27="B", OR(BB27="B", BB27="P", BB27="O")), AND($AJ27="P", OR(BB27="P", BB27="O")), AND($AJ27="O", BB27="O")), "Sim", "Não") ) ) -> N | BD27: N | BE27: =IF($AC27="N", "N", IF($B27="Não", "Sim", IF(OR( BD27=$AC27, AND($AC27="B", OR(BD27="B", BD27="P", BD27="O")), AND($AC27="P", OR(BD27="P", BD27="O")), AND($AC27="O", BD27="O")), "Sim", "Não") ) ) -> N | BF27: N | BG27: =IF($Y27="N", "N", IF($B27="Não", "Sim", IF(OR( BF27=$Y27, AND($Y27="B", OR(BF27="B", BF27="P", BF27="O")), AND($Y27="P", OR(BF27="P", BF27="O")), AND($Y27="O", BF27="O")), "Sim", "Não") ) ) -> N | BH27: N | BI27: =IF($K27="N", "N", IF($B27="Não", "Sim", IF(OR( BH27=$K27, AND($K27="B", OR(BH27="B", BH27="P", BH27="O")), AND($K27="P", OR(BH27="P", BH27="O")), AND($K27="O", BH27="O")), "Sim", "Não") ) ) -> N | BJ27: N | BK27: =IF($Y27="N", "N", IF($B27="Não", "Sim", IF(OR( BJ27=$Y27, AND($Y27="B", OR(BJ27="B", BJ27="P", BJ27="O")), AND($Y27="P", OR(BJ27="P", BJ27="O")), AND($Y27="O", BJ27="O")), "Sim", "Não") ) ) -> N | BL27: N | BM27: =IF($Y27="N", "N", IF($B27="Não", "Sim", IF(OR( BL27=$Y27, AND($Y27="B", OR(BL27="B", BL27="P", BL27="O")), AND($Y27="P", OR(BL27="P", BL27="O")), AND($Y27="O", BL27="O")), "Sim", "Não") ) ) -> N | BN27: N | BO27: =IF($AJ27="N", "N", IF($B27="Não", "Sim", IF(OR( BN27=$AJ27, AND($AJ27="B", OR(BN27="B", BN27="P", BN27="O")), AND($AJ27="P", OR(BN27="P", BN27="O")), AND($AJ27="O", BN27="O")), "Sim", "Não") ) ) -> N | BP27: P | BQ27: =IF($T27="N", "N", IF($B27="Não", "Sim", IF(OR( BP27=$T27, AND($T27="B", OR(BP27="B", BP27="P", BP27="O")), AND($T27="P", OR(BP27="P", BP27="O")), AND($T27="O", BP27="O")), "Sim", "Não") ) ) -> Sim | BR27: N | BS27: =IF($I27="N", "N", IF($B27="Não", "Sim", IF(OR( BR27=$I27, AND($I27="B", OR(BR27="B", BR27="P", BR27="O")), AND($I27="P", OR(BR27="P", BR27="O")), AND($I27="O", BR27="O")), "Sim", "Não") ) ) -> N | BT27: N | BU27: =IF($G27="N", "N", IF($B27="Não", "Sim", IF(OR( BT27=$G27, AND($G27="B", OR(BT27="B", BT27="P", BT27="O")), AND($G27="P", OR(BT27="P", BT27="O")), AND($G27="O", BT27="O")), "Sim", "Não") ) ) -> N | BV27: N | BW27: =IF($G27="N", "N", IF($B27="Não", "Sim", IF(OR( BV27=$G27, AND($G27="B", OR(BV27="B", BV27="P", BV27="O")), AND($G27="P", OR(BV27="P", BV27="O")), AND($G27="O", BV27="O")), "Sim", "Não") ) ) -> N | BX27: P | BY27: =IF($P27="N", "N", IF($B27="Não", "Sim", IF(OR( BX27=$P27, AND($P27="B", OR(BX27="B", BX27="P", BX27="O")), AND($P27="P", OR(BX27="P", BX27="O")), AND($P27="O", BX27="O")), "Sim", "Não") ) ) -> Sim | BZ27: N | CA27: =IF($G27="N", "N", IF($B27="Não", "Sim", IF(OR( BZ27=$G27, AND($G27="B", OR(BZ27="B", BZ27="P", BZ27="O")), AND($G27="P", OR(BZ27="P", BZ27="O")), AND($G27="O", BZ27="O")), "Sim", "Não") ) ) -> N
B28: Não | C28: Geral | D28: NodeJS 16+ | E28: N | F28: N | G28: N | H28: N | I28: N | J28: N | K28: N | L28: N | N28: B | O28: 0 | P28: B | Q28: 0 | R28: B | S28: 0 | T28: P | U28: 1 | W28: N | X28: N | Y28: N | Z28: N | AA28: N | AB28: N | AC28: N | AD28: N | AF28: N | AG28: N | AH28: N | AI28: N | AJ28: N | AK28: N | AL28: N | AM28: N | AO28: I | AP28: A | AQ28: I | AR28: I | AT28: P | AU28: =IF($P28="N", "N", IF($B28="Não", "Sim", IF(OR( AT28=$P28, AND($P28="B", OR(AT28="B", AT28="P", AT28="O")), AND($P28="P", OR(AT28="P", AT28="O")), AND($P28="O", AT28="O")), "Sim", "Não") ) ) -> Sim | AV28: N | AW28: =IF($I28="N", "N", IF($B28="Não", "Sim", IF(OR( AV28=$I28, AND($I28="B", OR(AV28="B", AV28="P", AV28="O")), AND($I28="P", OR(AV28="P", AV28="O")), AND($I28="O", AV28="O")), "Sim", "Não") ) ) -> N | AX28: P | AY28: =IF($R28="N", "N", IF($B28="Não", "Sim", IF(OR( AX28=$R28, AND($R28="B", OR(AX28="B", AX28="P", AX28="O")), AND($R28="P", OR(AX28="P", AX28="O")), AND($R28="O", AX28="O")), "Sim", "Não") ) ) -> Sim | AZ28: N | BA28: =IF($I28="N", "N", IF($B28="Não", "Sim", IF(OR( AZ28=$I28, AND($I28="B", OR(AZ28="B", AZ28="P", AZ28="O")), AND($I28="P", OR(AZ28="P", AZ28="O")), AND($I28="O", AZ28="O")), "Sim", "Não") ) ) -> N | BB28: N | BC28: =IF($AJ28="N", "N", IF($B28="Não", "Sim", IF(OR( BB28=$AJ28, AND($AJ28="B", OR(BB28="B", BB28="P", BB28="O")), AND($AJ28="P", OR(BB28="P", BB28="O")), AND($AJ28="O", BB28="O")), "Sim", "Não") ) ) -> N | BD28: N | BE28: =IF($AC28="N", "N", IF($B28="Não", "Sim", IF(OR( BD28=$AC28, AND($AC28="B", OR(BD28="B", BD28="P", BD28="O")), AND($AC28="P", OR(BD28="P", BD28="O")), AND($AC28="O", BD28="O")), "Sim", "Não") ) ) -> N | BF28: N | BG28: =IF($Y28="N", "N", IF($B28="Não", "Sim", IF(OR( BF28=$Y28, AND($Y28="B", OR(BF28="B", BF28="P", BF28="O")), AND($Y28="P", OR(BF28="P", BF28="O")), AND($Y28="O", BF28="O")), "Sim", "Não") ) ) -> N | BH28: N | BI28: =IF($K28="N", "N", IF($B28="Não", "Sim", IF(OR( BH28=$K28, AND($K28="B", OR(BH28="B", BH28="P", BH28="O")), AND($K28="P", OR(BH28="P", BH28="O")), AND($K28="O", BH28="O")), "Sim", "Não") ) ) -> N | BJ28: N | BK28: =IF($Y28="N", "N", IF($B28="Não", "Sim", IF(OR( BJ28=$Y28, AND($Y28="B", OR(BJ28="B", BJ28="P", BJ28="O")), AND($Y28="P", OR(BJ28="P", BJ28="O")), AND($Y28="O", BJ28="O")), "Sim", "Não") ) ) -> N | BL28: N | BM28: =IF($Y28="N", "N", IF($B28="Não", "Sim", IF(OR( BL28=$Y28, AND($Y28="B", OR(BL28="B", BL28="P", BL28="O")), AND($Y28="P", OR(BL28="P", BL28="O")), AND($Y28="O", BL28="O")), "Sim", "Não") ) ) -> N | BN28: N | BO28: =IF($AJ28="N", "N", IF($B28="Não", "Sim", IF(OR( BN28=$AJ28, AND($AJ28="B", OR(BN28="B", BN28="P", BN28="O")), AND($AJ28="P", OR(BN28="P", BN28="O")), AND($AJ28="O", BN28="O")), "Sim", "Não") ) ) -> N | BP28: P | BQ28: =IF($T28="N", "N", IF($B28="Não", "Sim", IF(OR( BP28=$T28, AND($T28="B", OR(BP28="B", BP28="P", BP28="O")), AND($T28="P", OR(BP28="P", BP28="O")), AND($T28="O", BP28="O")), "Sim", "Não") ) ) -> Sim | BR28: N | BS28: =IF($I28="N", "N", IF($B28="Não", "Sim", IF(OR( BR28=$I28, AND($I28="B", OR(BR28="B", BR28="P", BR28="O")), AND($I28="P", OR(BR28="P", BR28="O")), AND($I28="O", BR28="O")), "Sim", "Não") ) ) -> N | BT28: N | BU28: =IF($G28="N", "N", IF($B28="Não", "Sim", IF(OR( BT28=$G28, AND($G28="B", OR(BT28="B", BT28="P", BT28="O")), AND($G28="P", OR(BT28="P", BT28="O")), AND($G28="O", BT28="O")), "Sim", "Não") ) ) -> N | BV28: N | BW28: =IF($G28="N", "N", IF($B28="Não", "Sim", IF(OR( BV28=$G28, AND($G28="B", OR(BV28="B", BV28="P", BV28="O")), AND($G28="P", OR(BV28="P", BV28="O")), AND($G28="O", BV28="O")), "Sim", "Não") ) ) -> N | BX28: P | BY28: =IF($P28="N", "N", IF($B28="Não", "Sim", IF(OR( BX28=$P28, AND($P28="B", OR(BX28="B", BX28="P", BX28="O")), AND($P28="P", OR(BX28="P", BX28="O")), AND($P28="O", BX28="O")), "Sim", "Não") ) ) -> Sim | BZ28: N | CA28: =IF($G28="N", "N", IF($B28="Não", "Sim", IF(OR( BZ28=$G28, AND($G28="B", OR(BZ28="B", BZ28="P", BZ28="O")), AND($G28="P", OR(BZ28="P", BZ28="O")), AND($G28="O", BZ28="O")), "Sim", "Não") ) ) -> N
B29: Não | C29: Dev | D29: TypeScript | E29: N | F29: N | G29: N | H29: N | I29: N | J29: N | K29: N | L29: N | N29: B | O29: 0 | P29: B | Q29: 1 | R29: P | S29: 1 | T29: O | U29: 1 | W29: N | X29: N | Y29: N | Z29: N | AA29: N | AB29: N | AC29: N | AD29: N | AF29: N | AG29: N | AH29: N | AI29: N | AJ29: N | AK29: N | AL29: N | AM29: N | AO29: I | AP29: A | AQ29: I | AR29: I | AT29: P | AU29: =IF($P29="N", "N", IF($B29="Não", "Sim", IF(OR( AT29=$P29, AND($P29="B", OR(AT29="B", AT29="P", AT29="O")), AND($P29="P", OR(AT29="P", AT29="O")), AND($P29="O", AT29="O")), "Sim", "Não") ) ) -> Sim | AV29: N | AW29: =IF($I29="N", "N", IF($B29="Não", "Sim", IF(OR( AV29=$I29, AND($I29="B", OR(AV29="B", AV29="P", AV29="O")), AND($I29="P", OR(AV29="P", AV29="O")), AND($I29="O", AV29="O")), "Sim", "Não") ) ) -> N | AX29: P | AY29: =IF($R29="N", "N", IF($B29="Não", "Sim", IF(OR( AX29=$R29, AND($R29="B", OR(AX29="B", AX29="P", AX29="O")), AND($R29="P", OR(AX29="P", AX29="O")), AND($R29="O", AX29="O")), "Sim", "Não") ) ) -> Sim | AZ29: N | BA29: =IF($I29="N", "N", IF($B29="Não", "Sim", IF(OR( AZ29=$I29, AND($I29="B", OR(AZ29="B", AZ29="P", AZ29="O")), AND($I29="P", OR(AZ29="P", AZ29="O")), AND($I29="O", AZ29="O")), "Sim", "Não") ) ) -> N | BB29: N | BC29: =IF($AJ29="N", "N", IF($B29="Não", "Sim", IF(OR( BB29=$AJ29, AND($AJ29="B", OR(BB29="B", BB29="P", BB29="O")), AND($AJ29="P", OR(BB29="P", BB29="O")), AND($AJ29="O", BB29="O")), "Sim", "Não") ) ) -> N | BD29: N | BE29: =IF($AC29="N", "N", IF($B29="Não", "Sim", IF(OR( BD29=$AC29, AND($AC29="B", OR(BD29="B", BD29="P", BD29="O")), AND($AC29="P", OR(BD29="P", BD29="O")), AND($AC29="O", BD29="O")), "Sim", "Não") ) ) -> N | BF29: N | BG29: =IF($Y29="N", "N", IF($B29="Não", "Sim", IF(OR( BF29=$Y29, AND($Y29="B", OR(BF29="B", BF29="P", BF29="O")), AND($Y29="P", OR(BF29="P", BF29="O")), AND($Y29="O", BF29="O")), "Sim", "Não") ) ) -> N | BH29: N | BI29: =IF($K29="N", "N", IF($B29="Não", "Sim", IF(OR( BH29=$K29, AND($K29="B", OR(BH29="B", BH29="P", BH29="O")), AND($K29="P", OR(BH29="P", BH29="O")), AND($K29="O", BH29="O")), "Sim", "Não") ) ) -> N | BJ29: N | BK29: =IF($Y29="N", "N", IF($B29="Não", "Sim", IF(OR( BJ29=$Y29, AND($Y29="B", OR(BJ29="B", BJ29="P", BJ29="O")), AND($Y29="P", OR(BJ29="P", BJ29="O")), AND($Y29="O", BJ29="O")), "Sim", "Não") ) ) -> N | BL29: N | BM29: =IF($Y29="N", "N", IF($B29="Não", "Sim", IF(OR( BL29=$Y29, AND($Y29="B", OR(BL29="B", BL29="P", BL29="O")), AND($Y29="P", OR(BL29="P", BL29="O")), AND($Y29="O", BL29="O")), "Sim", "Não") ) ) -> N | BN29: N | BO29: =IF($AJ29="N", "N", IF($B29="Não", "Sim", IF(OR( BN29=$AJ29, AND($AJ29="B", OR(BN29="B", BN29="P", BN29="O")), AND($AJ29="P", OR(BN29="P", BN29="O")), AND($AJ29="O", BN29="O")), "Sim", "Não") ) ) -> N | BP29: P | BQ29: =IF($T29="N", "N", IF($B29="Não", "Sim", IF(OR( BP29=$T29, AND($T29="B", OR(BP29="B", BP29="P", BP29="O")), AND($T29="P", OR(BP29="P", BP29="O")), AND($T29="O", BP29="O")), "Sim", "Não") ) ) -> Sim | BR29: N | BS29: =IF($I29="N", "N", IF($B29="Não", "Sim", IF(OR( BR29=$I29, AND($I29="B", OR(BR29="B", BR29="P", BR29="O")), AND($I29="P", OR(BR29="P", BR29="O")), AND($I29="O", BR29="O")), "Sim", "Não") ) ) -> N | BT29: N | BU29: =IF($G29="N", "N", IF($B29="Não", "Sim", IF(OR( BT29=$G29, AND($G29="B", OR(BT29="B", BT29="P", BT29="O")), AND($G29="P", OR(BT29="P", BT29="O")), AND($G29="O", BT29="O")), "Sim", "Não") ) ) -> N | BV29: N | BW29: =IF($G29="N", "N", IF($B29="Não", "Sim", IF(OR( BV29=$G29, AND($G29="B", OR(BV29="B", BV29="P", BV29="O")), AND($G29="P", OR(BV29="P", BV29="O")), AND($G29="O", BV29="O")), "Sim", "Não") ) ) -> N | BX29: P | BY29: =IF($P29="N", "N", IF($B29="Não", "Sim", IF(OR( BX29=$P29, AND($P29="B", OR(BX29="B", BX29="P", BX29="O")), AND($P29="P", OR(BX29="P", BX29="O")), AND($P29="O", BX29="O")), "Sim", "Não") ) ) -> Sim | BZ29: N | CA29: =IF($G29="N", "N", IF($B29="Não", "Sim", IF(OR( BZ29=$G29, AND($G29="B", OR(BZ29="B", BZ29="P", BZ29="O")), AND($G29="P", OR(BZ29="P", BZ29="O")), AND($G29="O", BZ29="O")), "Sim", "Não") ) ) -> N
B30: Não | C30: Geral | D30: Gateway | E30: B | F30: 0 | G30: B | H30: 1 | I30: B | J30: 1 | K30: B | L30: 1 | N30: B | O30: 0 | P30: B | Q30: 1 | R30: P | S30: 1 | T30: P | U30: 1 | W30: B | X30: 0 | Y30: B | Z30: 1 | AA30: P | AB30: 1 | AC30: P | AD30: 1 | AF30: N | AG30: N | AH30: N | AI30: N | AJ30: N | AK30: N | AL30: N | AM30: N | AO30: A | AP30: A | AQ30: A | AR30: I | AT30: B | AU30: =IF($P30="N", "N", IF($B30="Não", "Sim", IF(OR( AT30=$P30, AND($P30="B", OR(AT30="B", AT30="P", AT30="O")), AND($P30="P", OR(AT30="P", AT30="O")), AND($P30="O", AT30="O")), "Sim", "Não") ) ) -> Sim | AV30: B | AW30: =IF($I30="N", "N", IF($B30="Não", "Sim", IF(OR( AV30=$I30, AND($I30="B", OR(AV30="B", AV30="P", AV30="O")), AND($I30="P", OR(AV30="P", AV30="O")), AND($I30="O", AV30="O")), "Sim", "Não") ) ) -> Sim | AX30: P | AY30: =IF($R30="N", "N", IF($B30="Não", "Sim", IF(OR( AX30=$R30, AND($R30="B", OR(AX30="B", AX30="P", AX30="O")), AND($R30="P", OR(AX30="P", AX30="O")), AND($R30="O", AX30="O")), "Sim", "Não") ) ) -> Sim | AZ30: B | BA30: =IF($I30="N", "N", IF($B30="Não", "Sim", IF(OR( AZ30=$I30, AND($I30="B", OR(AZ30="B", AZ30="P", AZ30="O")), AND($I30="P", OR(AZ30="P", AZ30="O")), AND($I30="O", AZ30="O")), "Sim", "Não") ) ) -> Sim | BB30: N | BC30: =IF($AJ30="N", "N", IF($B30="Não", "Sim", IF(OR( BB30=$AJ30, AND($AJ30="B", OR(BB30="B", BB30="P", BB30="O")), AND($AJ30="P", OR(BB30="P", BB30="O")), AND($AJ30="O", BB30="O")), "Sim", "Não") ) ) -> N | BD30: P | BE30: =IF($AC30="N", "N", IF($B30="Não", "Sim", IF(OR( BD30=$AC30, AND($AC30="B", OR(BD30="B", BD30="P", BD30="O")), AND($AC30="P", OR(BD30="P", BD30="O")), AND($AC30="O", BD30="O")), "Sim", "Não") ) ) -> Sim | BF30: B | BG30: =IF($Y30="N", "N", IF($B30="Não", "Sim", IF(OR( BF30=$Y30, AND($Y30="B", OR(BF30="B", BF30="P", BF30="O")), AND($Y30="P", OR(BF30="P", BF30="O")), AND($Y30="O", BF30="O")), "Sim", "Não") ) ) -> Sim | BH30: B | BI30: =IF($K30="N", "N", IF($B30="Não", "Sim", IF(OR( BH30=$K30, AND($K30="B", OR(BH30="B", BH30="P", BH30="O")), AND($K30="P", OR(BH30="P", BH30="O")), AND($K30="O", BH30="O")), "Sim", "Não") ) ) -> Sim | BJ30: B | BK30: =IF($Y30="N", "N", IF($B30="Não", "Sim", IF(OR( BJ30=$Y30, AND($Y30="B", OR(BJ30="B", BJ30="P", BJ30="O")), AND($Y30="P", OR(BJ30="P", BJ30="O")), AND($Y30="O", BJ30="O")), "Sim", "Não") ) ) -> Sim | BL30: B | BM30: =IF($Y30="N", "N", IF($B30="Não", "Sim", IF(OR( BL30=$Y30, AND($Y30="B", OR(BL30="B", BL30="P", BL30="O")), AND($Y30="P", OR(BL30="P", BL30="O")), AND($Y30="O", BL30="O")), "Sim", "Não") ) ) -> Sim | BN30: N | BO30: =IF($AJ30="N", "N", IF($B30="Não", "Sim", IF(OR( BN30=$AJ30, AND($AJ30="B", OR(BN30="B", BN30="P", BN30="O")), AND($AJ30="P", OR(BN30="P", BN30="O")), AND($AJ30="O", BN30="O")), "Sim", "Não") ) ) -> N | BP30: B | BQ30: =IF($T30="N", "N", IF($B30="Não", "Sim", IF(OR( BP30=$T30, AND($T30="B", OR(BP30="B", BP30="P", BP30="O")), AND($T30="P", OR(BP30="P", BP30="O")), AND($T30="O", BP30="O")), "Sim", "Não") ) ) -> Sim | BR30: B | BS30: =IF($I30="N", "N", IF($B30="Não", "Sim", IF(OR( BR30=$I30, AND($I30="B", OR(BR30="B", BR30="P", BR30="O")), AND($I30="P", OR(BR30="P", BR30="O")), AND($I30="O", BR30="O")), "Sim", "Não") ) ) -> Sim | BT30: B | BU30: =IF($G30="N", "N", IF($B30="Não", "Sim", IF(OR( BT30=$G30, AND($G30="B", OR(BT30="B", BT30="P", BT30="O")), AND($G30="P", OR(BT30="P", BT30="O")), AND($G30="O", BT30="O")), "Sim", "Não") ) ) -> Sim | BV30: B | BW30: =IF($G30="N", "N", IF($B30="Não", "Sim", IF(OR( BV30=$G30, AND($G30="B", OR(BV30="B", BV30="P", BV30="O")), AND($G30="P", OR(BV30="P", BV30="O")), AND($G30="O", BV30="O")), "Sim", "Não") ) ) -> Sim | BX30: P | BY30: =IF($P30="N", "N", IF($B30="Não", "Sim", IF(OR( BX30=$P30, AND($P30="B", OR(BX30="B", BX30="P", BX30="O")), AND($P30="P", OR(BX30="P", BX30="O")), AND($P30="O", BX30="O")), "Sim", "Não") ) ) -> Sim | BZ30: B | CA30: =IF($G30="N", "N", IF($B30="Não", "Sim", IF(OR( BZ30=$G30, AND($G30="B", OR(BZ30="B", BZ30="P", BZ30="O")), AND($G30="P", OR(BZ30="P", BZ30="O")), AND($G30="O", BZ30="O")), "Sim", "Não") ) ) -> Sim
B31: Não | C31: Geral | D31: Publicação e Instalação do produto Plataforma Space | E31: B | F31: 0 | G31: B | H31: 1 | I31: P | J31: 1 | K31: P | L31: 1 | N31: B | O31: 0 | P31: B | Q31: 1 | R31: P | S31: 1 | T31: P | U31: 1 | W31: B | X31: 0 | Y31: B | Z31: 1 | AA31: P | AB31: 1 | AC31: P | AD31: 1 | AF31: B | AG31: 0 | AH31: B | AI31: 1 | AJ31: P | AK31: 1 | AL31: P | AM31: 1 | AO31: A | AP31: A | AQ31: A | AR31: A | AT31: B | AU31: =IF($P31="N", "N", IF($B31="Não", "Sim", IF(OR( AT31=$P31, AND($P31="B", OR(AT31="B", AT31="P", AT31="O")), AND($P31="P", OR(AT31="P", AT31="O")), AND($P31="O", AT31="O")), "Sim", "Não") ) ) -> Sim | AV31: P | AW31: =IF($I31="N", "N", IF($B31="Não", "Sim", IF(OR( AV31=$I31, AND($I31="B", OR(AV31="B", AV31="P", AV31="O")), AND($I31="P", OR(AV31="P", AV31="O")), AND($I31="O", AV31="O")), "Sim", "Não") ) ) -> Sim | AX31: O | AY31: =IF($R31="N", "N", IF($B31="Não", "Sim", IF(OR( AX31=$R31, AND($R31="B", OR(AX31="B", AX31="P", AX31="O")), AND($R31="P", OR(AX31="P", AX31="O")), AND($R31="O", AX31="O")), "Sim", "Não") ) ) -> Sim | AZ31: B | BA31: =IF($I31="N", "N", IF($B31="Não", "Sim", IF(OR( AZ31=$I31, AND($I31="B", OR(AZ31="B", AZ31="P", AZ31="O")), AND($I31="P", OR(AZ31="P", AZ31="O")), AND($I31="O", AZ31="O")), "Sim", "Não") ) ) -> Sim | BB31: O | BC31: =IF($AJ31="N", "N", IF($B31="Não", "Sim", IF(OR( BB31=$AJ31, AND($AJ31="B", OR(BB31="B", BB31="P", BB31="O")), AND($AJ31="P", OR(BB31="P", BB31="O")), AND($AJ31="O", BB31="O")), "Sim", "Não") ) ) -> Sim | BD31: O | BE31: =IF($AC31="N", "N", IF($B31="Não", "Sim", IF(OR( BD31=$AC31, AND($AC31="B", OR(BD31="B", BD31="P", BD31="O")), AND($AC31="P", OR(BD31="P", BD31="O")), AND($AC31="O", BD31="O")), "Sim", "Não") ) ) -> Sim | BF31: B | BG31: =IF($Y31="N", "N", IF($B31="Não", "Sim", IF(OR( BF31=$Y31, AND($Y31="B", OR(BF31="B", BF31="P", BF31="O")), AND($Y31="P", OR(BF31="P", BF31="O")), AND($Y31="O", BF31="O")), "Sim", "Não") ) ) -> Sim | BH31: P | BI31: =IF($K31="N", "N", IF($B31="Não", "Sim", IF(OR( BH31=$K31, AND($K31="B", OR(BH31="B", BH31="P", BH31="O")), AND($K31="P", OR(BH31="P", BH31="O")), AND($K31="O", BH31="O")), "Sim", "Não") ) ) -> Sim | BJ31: B | BK31: =IF($Y31="N", "N", IF($B31="Não", "Sim", IF(OR( BJ31=$Y31, AND($Y31="B", OR(BJ31="B", BJ31="P", BJ31="O")), AND($Y31="P", OR(BJ31="P", BJ31="O")), AND($Y31="O", BJ31="O")), "Sim", "Não") ) ) -> Sim | BL31: B | BM31: =IF($Y31="N", "N", IF($B31="Não", "Sim", IF(OR( BL31=$Y31, AND($Y31="B", OR(BL31="B", BL31="P", BL31="O")), AND($Y31="P", OR(BL31="P", BL31="O")), AND($Y31="O", BL31="O")), "Sim", "Não") ) ) -> Sim | BN31: O | BO31: =IF($AJ31="N", "N", IF($B31="Não", "Sim", IF(OR( BN31=$AJ31, AND($AJ31="B", OR(BN31="B", BN31="P", BN31="O")), AND($AJ31="P", OR(BN31="P", BN31="O")), AND($AJ31="O", BN31="O")), "Sim", "Não") ) ) -> Sim | BP31: B | BQ31: =IF($T31="N", "N", IF($B31="Não", "Sim", IF(OR( BP31=$T31, AND($T31="B", OR(BP31="B", BP31="P", BP31="O")), AND($T31="P", OR(BP31="P", BP31="O")), AND($T31="O", BP31="O")), "Sim", "Não") ) ) -> Sim | BR31: P | BS31: =IF($I31="N", "N", IF($B31="Não", "Sim", IF(OR( BR31=$I31, AND($I31="B", OR(BR31="B", BR31="P", BR31="O")), AND($I31="P", OR(BR31="P", BR31="O")), AND($I31="O", BR31="O")), "Sim", "Não") ) ) -> Sim | BT31: B | BU31: =IF($G31="N", "N", IF($B31="Não", "Sim", IF(OR( BT31=$G31, AND($G31="B", OR(BT31="B", BT31="P", BT31="O")), AND($G31="P", OR(BT31="P", BT31="O")), AND($G31="O", BT31="O")), "Sim", "Não") ) ) -> Sim | BV31: B | BW31: =IF($G31="N", "N", IF($B31="Não", "Sim", IF(OR( BV31=$G31, AND($G31="B", OR(BV31="B", BV31="P", BV31="O")), AND($G31="P", OR(BV31="P", BV31="O")), AND($G31="O", BV31="O")), "Sim", "Não") ) ) -> Sim | BX31: B | BY31: =IF($P31="N", "N", IF($B31="Não", "Sim", IF(OR( BX31=$P31, AND($P31="B", OR(BX31="B", BX31="P", BX31="O")), AND($P31="P", OR(BX31="P", BX31="O")), AND($P31="O", BX31="O")), "Sim", "Não") ) ) -> Sim | BZ31: P | CA31: =IF($G31="N", "N", IF($B31="Não", "Sim", IF(OR( BZ31=$G31, AND($G31="B", OR(BZ31="B", BZ31="P", BZ31="O")), AND($G31="P", OR(BZ31="P", BZ31="O")), AND($G31="O", BZ31="O")), "Sim", "Não") ) ) -> Sim
B32: Não | C32: Geral | D32: Analisar e Estimar Demandas | E32: B | F32: 0 | G32: B | H32: 1 | I32: P | J32: 1 | K32: O | L32: 1 | N32: B | O32: 0 | P32: B | Q32: 1 | R32: P | S32: 1 | T32: O | U32: 1 | W32: B | X32: 0 | Y32: B | Z32: 1 | AA32: P | AB32: 1 | AC32: O | AD32: 1 | AF32: N | AG32: N | AH32: N | AI32: N | AJ32: N | AK32: N | AL32: N | AM32: N | AO32: A | AP32: A | AQ32: A | AR32: I | AT32: P | AU32: =IF($P32="N", "N", IF($B32="Não", "Sim", IF(OR( AT32=$P32, AND($P32="B", OR(AT32="B", AT32="P", AT32="O")), AND($P32="P", OR(AT32="P", AT32="O")), AND($P32="O", AT32="O")), "Sim", "Não") ) ) -> Sim | AV32: P | AW32: =IF($I32="N", "N", IF($B32="Não", "Sim", IF(OR( AV32=$I32, AND($I32="B", OR(AV32="B", AV32="P", AV32="O")), AND($I32="P", OR(AV32="P", AV32="O")), AND($I32="O", AV32="O")), "Sim", "Não") ) ) -> Sim | AX32: P | AY32: =IF($R32="N", "N", IF($B32="Não", "Sim", IF(OR( AX32=$R32, AND($R32="B", OR(AX32="B", AX32="P", AX32="O")), AND($R32="P", OR(AX32="P", AX32="O")), AND($R32="O", AX32="O")), "Sim", "Não") ) ) -> Sim | AZ32: B | BA32: =IF($I32="N", "N", IF($B32="Não", "Sim", IF(OR( AZ32=$I32, AND($I32="B", OR(AZ32="B", AZ32="P", AZ32="O")), AND($I32="P", OR(AZ32="P", AZ32="O")), AND($I32="O", AZ32="O")), "Sim", "Não") ) ) -> Sim | BB32: N | BC32: =IF($AJ32="N", "N", IF($B32="Não", "Sim", IF(OR( BB32=$AJ32, AND($AJ32="B", OR(BB32="B", BB32="P", BB32="O")), AND($AJ32="P", OR(BB32="P", BB32="O")), AND($AJ32="O", BB32="O")), "Sim", "Não") ) ) -> N | BD32: O | BE32: =IF($AC32="N", "N", IF($B32="Não", "Sim", IF(OR( BD32=$AC32, AND($AC32="B", OR(BD32="B", BD32="P", BD32="O")), AND($AC32="P", OR(BD32="P", BD32="O")), AND($AC32="O", BD32="O")), "Sim", "Não") ) ) -> Sim | BF32: B | BG32: =IF($Y32="N", "N", IF($B32="Não", "Sim", IF(OR( BF32=$Y32, AND($Y32="B", OR(BF32="B", BF32="P", BF32="O")), AND($Y32="P", OR(BF32="P", BF32="O")), AND($Y32="O", BF32="O")), "Sim", "Não") ) ) -> Sim | BH32: O | BI32: =IF($K32="N", "N", IF($B32="Não", "Sim", IF(OR( BH32=$K32, AND($K32="B", OR(BH32="B", BH32="P", BH32="O")), AND($K32="P", OR(BH32="P", BH32="O")), AND($K32="O", BH32="O")), "Sim", "Não") ) ) -> Sim | BJ32: B | BK32: =IF($Y32="N", "N", IF($B32="Não", "Sim", IF(OR( BJ32=$Y32, AND($Y32="B", OR(BJ32="B", BJ32="P", BJ32="O")), AND($Y32="P", OR(BJ32="P", BJ32="O")), AND($Y32="O", BJ32="O")), "Sim", "Não") ) ) -> Sim | BL32: B | BM32: =IF($Y32="N", "N", IF($B32="Não", "Sim", IF(OR( BL32=$Y32, AND($Y32="B", OR(BL32="B", BL32="P", BL32="O")), AND($Y32="P", OR(BL32="P", BL32="O")), AND($Y32="O", BL32="O")), "Sim", "Não") ) ) -> Sim | BN32: N | BO32: =IF($AJ32="N", "N", IF($B32="Não", "Sim", IF(OR( BN32=$AJ32, AND($AJ32="B", OR(BN32="B", BN32="P", BN32="O")), AND($AJ32="P", OR(BN32="P", BN32="O")), AND($AJ32="O", BN32="O")), "Sim", "Não") ) ) -> N | BP32: P | BQ32: =IF($T32="N", "N", IF($B32="Não", "Sim", IF(OR( BP32=$T32, AND($T32="B", OR(BP32="B", BP32="P", BP32="O")), AND($T32="P", OR(BP32="P", BP32="O")), AND($T32="O", BP32="O")), "Sim", "Não") ) ) -> Sim | BR32: P | BS32: =IF($I32="N", "N", IF($B32="Não", "Sim", IF(OR( BR32=$I32, AND($I32="B", OR(BR32="B", BR32="P", BR32="O")), AND($I32="P", OR(BR32="P", BR32="O")), AND($I32="O", BR32="O")), "Sim", "Não") ) ) -> Sim | BT32: B | BU32: =IF($G32="N", "N", IF($B32="Não", "Sim", IF(OR( BT32=$G32, AND($G32="B", OR(BT32="B", BT32="P", BT32="O")), AND($G32="P", OR(BT32="P", BT32="O")), AND($G32="O", BT32="O")), "Sim", "Não") ) ) -> Sim | BV32: B | BW32: =IF($G32="N", "N", IF($B32="Não", "Sim", IF(OR( BV32=$G32, AND($G32="B", OR(BV32="B", BV32="P", BV32="O")), AND($G32="P", OR(BV32="P", BV32="O")), AND($G32="O", BV32="O")), "Sim", "Não") ) ) -> Sim | BX32: P | BY32: =IF($P32="N", "N", IF($B32="Não", "Sim", IF(OR( BX32=$P32, AND($P32="B", OR(BX32="B", BX32="P", BX32="O")), AND($P32="P", OR(BX32="P", BX32="O")), AND($P32="O", BX32="O")), "Sim", "Não") ) ) -> Sim | BZ32: B | CA32: =IF($G32="N", "N", IF($B32="Não", "Sim", IF(OR( BZ32=$G32, AND($G32="B", OR(BZ32="B", BZ32="P", BZ32="O")), AND($G32="P", OR(BZ32="P", BZ32="O")), AND($G32="O", BZ32="O")), "Sim", "Não") ) ) -> Sim
B33: Não | C33: Geral | D33: Gerar Documentação Técnica + Fluxograma + UML + APIARY | E33: B | F33: 0 | G33: B | H33: 1 | I33: P | J33: 1 | K33: O | L33: 1 | N33: B | O33: 0 | P33: B | Q33: 1 | R33: P | S33: 1 | T33: O | U33: 1 | W33: B | X33: 1 | Y33: B | Z33: 1 | AA33: P | AB33: 1 | AC33: O | AD33: 1 | AF33: B | AG33: 0 | AH33: B | AI33: 1 | AJ33: P | AK33: 1 | AL33: O | AM33: 1 | AO33: A | AP33: A | AQ33: A | AR33: A | AT33: B | AU33: =IF($P33="N", "N", IF($B33="Não", "Sim", IF(OR( AT33=$P33, AND($P33="B", OR(AT33="B", AT33="P", AT33="O")), AND($P33="P", OR(AT33="P", AT33="O")), AND($P33="O", AT33="O")), "Sim", "Não") ) ) -> Sim | AV33: P | AW33: =IF($I33="N", "N", IF($B33="Não", "Sim", IF(OR( AV33=$I33, AND($I33="B", OR(AV33="B", AV33="P", AV33="O")), AND($I33="P", OR(AV33="P", AV33="O")), AND($I33="O", AV33="O")), "Sim", "Não") ) ) -> Sim | AX33: P | AY33: =IF($R33="N", "N", IF($B33="Não", "Sim", IF(OR( AX33=$R33, AND($R33="B", OR(AX33="B", AX33="P", AX33="O")), AND($R33="P", OR(AX33="P", AX33="O")), AND($R33="O", AX33="O")), "Sim", "Não") ) ) -> Sim | AZ33: O | BA33: =IF($I33="N", "N", IF($B33="Não", "Sim", IF(OR( AZ33=$I33, AND($I33="B", OR(AZ33="B", AZ33="P", AZ33="O")), AND($I33="P", OR(AZ33="P", AZ33="O")), AND($I33="O", AZ33="O")), "Sim", "Não") ) ) -> Sim | BB33: O | BC33: =IF($AJ33="N", "N", IF($B33="Não", "Sim", IF(OR( BB33=$AJ33, AND($AJ33="B", OR(BB33="B", BB33="P", BB33="O")), AND($AJ33="P", OR(BB33="P", BB33="O")), AND($AJ33="O", BB33="O")), "Sim", "Não") ) ) -> Sim | BD33: O | BE33: =IF($AC33="N", "N", IF($B33="Não", "Sim", IF(OR( BD33=$AC33, AND($AC33="B", OR(BD33="B", BD33="P", BD33="O")), AND($AC33="P", OR(BD33="P", BD33="O")), AND($AC33="O", BD33="O")), "Sim", "Não") ) ) -> Sim | BF33: B | BG33: =IF($Y33="N", "N", IF($B33="Não", "Sim", IF(OR( BF33=$Y33, AND($Y33="B", OR(BF33="B", BF33="P", BF33="O")), AND($Y33="P", OR(BF33="P", BF33="O")), AND($Y33="O", BF33="O")), "Sim", "Não") ) ) -> Sim | BH33: P | BI33: =IF($K33="N", "N", IF($B33="Não", "Sim", IF(OR( BH33=$K33, AND($K33="B", OR(BH33="B", BH33="P", BH33="O")), AND($K33="P", OR(BH33="P", BH33="O")), AND($K33="O", BH33="O")), "Sim", "Não") ) ) -> Sim | BJ33: B | BK33: =IF($Y33="N", "N", IF($B33="Não", "Sim", IF(OR( BJ33=$Y33, AND($Y33="B", OR(BJ33="B", BJ33="P", BJ33="O")), AND($Y33="P", OR(BJ33="P", BJ33="O")), AND($Y33="O", BJ33="O")), "Sim", "Não") ) ) -> Sim | BL33: P | BM33: =IF($Y33="N", "N", IF($B33="Não", "Sim", IF(OR( BL33=$Y33, AND($Y33="B", OR(BL33="B", BL33="P", BL33="O")), AND($Y33="P", OR(BL33="P", BL33="O")), AND($Y33="O", BL33="O")), "Sim", "Não") ) ) -> Sim | BN33: P | BO33: =IF($AJ33="N", "N", IF($B33="Não", "Sim", IF(OR( BN33=$AJ33, AND($AJ33="B", OR(BN33="B", BN33="P", BN33="O")), AND($AJ33="P", OR(BN33="P", BN33="O")), AND($AJ33="O", BN33="O")), "Sim", "Não") ) ) -> Sim | BP33: P | BQ33: =IF($T33="N", "N", IF($B33="Não", "Sim", IF(OR( BP33=$T33, AND($T33="B", OR(BP33="B", BP33="P", BP33="O")), AND($T33="P", OR(BP33="P", BP33="O")), AND($T33="O", BP33="O")), "Sim", "Não") ) ) -> Sim | BR33: P | BS33: =IF($I33="N", "N", IF($B33="Não", "Sim", IF(OR( BR33=$I33, AND($I33="B", OR(BR33="B", BR33="P", BR33="O")), AND($I33="P", OR(BR33="P", BR33="O")), AND($I33="O", BR33="O")), "Sim", "Não") ) ) -> Sim | BT33: B | BU33: =IF($G33="N", "N", IF($B33="Não", "Sim", IF(OR( BT33=$G33, AND($G33="B", OR(BT33="B", BT33="P", BT33="O")), AND($G33="P", OR(BT33="P", BT33="O")), AND($G33="O", BT33="O")), "Sim", "Não") ) ) -> Sim | BV33: D | BW33: =IF($G33="N", "N", IF($B33="Não", "Sim", IF(OR( BV33=$G33, AND($G33="B", OR(BV33="B", BV33="P", BV33="O")), AND($G33="P", OR(BV33="P", BV33="O")), AND($G33="O", BV33="O")), "Sim", "Não") ) ) -> Sim | BX33: B | BY33: =IF($P33="N", "N", IF($B33="Não", "Sim", IF(OR( BX33=$P33, AND($P33="B", OR(BX33="B", BX33="P", BX33="O")), AND($P33="P", OR(BX33="P", BX33="O")), AND($P33="O", BX33="O")), "Sim", "Não") ) ) -> Sim | BZ33: P | CA33: =IF($G33="N", "N", IF($B33="Não", "Sim", IF(OR( BZ33=$G33, AND($G33="B", OR(BZ33="B", BZ33="P", BZ33="O")), AND($G33="P", OR(BZ33="P", BZ33="O")), AND($G33="O", BZ33="O")), "Sim", "Não") ) ) -> Sim
B34: Não | C34: Geral | D34: Automatização de Builds TFS (Configuração e Criação) | E34: B | F34: 0 | G34: B | H34: 0 | I34: P | J34: 1 | K34: P | L34: 1 | N34: B | O34: 0 | P34: B | Q34: 0 | R34: P | S34: 1 | T34: P | U34: 1 | W34: B | X34: 0 | Y34: B | Z34: 0 | AA34: P | AB34: 1 | AC34: P | AD34: 1 | AF34: B | AG34: 0 | AH34: B | AI34: 1 | AJ34: P | AK34: 1 | AL34: O | AM34: 1 | AO34: A | AP34: A | AQ34: A | AR34: A | AT34: B | AU34: =IF($P34="N", "N", IF($B34="Não", "Sim", IF(OR( AT34=$P34, AND($P34="B", OR(AT34="B", AT34="P", AT34="O")), AND($P34="P", OR(AT34="P", AT34="O")), AND($P34="O", AT34="O")), "Sim", "Não") ) ) -> Sim | AV34: P | AW34: =IF($I34="N", "N", IF($B34="Não", "Sim", IF(OR( AV34=$I34, AND($I34="B", OR(AV34="B", AV34="P", AV34="O")), AND($I34="P", OR(AV34="P", AV34="O")), AND($I34="O", AV34="O")), "Sim", "Não") ) ) -> Sim | AX34: P | AY34: =IF($R34="N", "N", IF($B34="Não", "Sim", IF(OR( AX34=$R34, AND($R34="B", OR(AX34="B", AX34="P", AX34="O")), AND($R34="P", OR(AX34="P", AX34="O")), AND($R34="O", AX34="O")), "Sim", "Não") ) ) -> Sim | AZ34: B | BA34: =IF($I34="N", "N", IF($B34="Não", "Sim", IF(OR( AZ34=$I34, AND($I34="B", OR(AZ34="B", AZ34="P", AZ34="O")), AND($I34="P", OR(AZ34="P", AZ34="O")), AND($I34="O", AZ34="O")), "Sim", "Não") ) ) -> Sim | BB34: O | BC34: =IF($AJ34="N", "N", IF($B34="Não", "Sim", IF(OR( BB34=$AJ34, AND($AJ34="B", OR(BB34="B", BB34="P", BB34="O")), AND($AJ34="P", OR(BB34="P", BB34="O")), AND($AJ34="O", BB34="O")), "Sim", "Não") ) ) -> Sim | BD34: P | BE34: =IF($AC34="N", "N", IF($B34="Não", "Sim", IF(OR( BD34=$AC34, AND($AC34="B", OR(BD34="B", BD34="P", BD34="O")), AND($AC34="P", OR(BD34="P", BD34="O")), AND($AC34="O", BD34="O")), "Sim", "Não") ) ) -> Sim | BF34: B | BG34: =IF($Y34="N", "N", IF($B34="Não", "Sim", IF(OR( BF34=$Y34, AND($Y34="B", OR(BF34="B", BF34="P", BF34="O")), AND($Y34="P", OR(BF34="P", BF34="O")), AND($Y34="O", BF34="O")), "Sim", "Não") ) ) -> Sim | BH34: P | BI34: =IF($K34="N", "N", IF($B34="Não", "Sim", IF(OR( BH34=$K34, AND($K34="B", OR(BH34="B", BH34="P", BH34="O")), AND($K34="P", OR(BH34="P", BH34="O")), AND($K34="O", BH34="O")), "Sim", "Não") ) ) -> Sim | BJ34: B | BK34: =IF($Y34="N", "N", IF($B34="Não", "Sim", IF(OR( BJ34=$Y34, AND($Y34="B", OR(BJ34="B", BJ34="P", BJ34="O")), AND($Y34="P", OR(BJ34="P", BJ34="O")), AND($Y34="O", BJ34="O")), "Sim", "Não") ) ) -> Sim | BL34: B | BM34: =IF($Y34="N", "N", IF($B34="Não", "Sim", IF(OR( BL34=$Y34, AND($Y34="B", OR(BL34="B", BL34="P", BL34="O")), AND($Y34="P", OR(BL34="P", BL34="O")), AND($Y34="O", BL34="O")), "Sim", "Não") ) ) -> Sim | BN34: O | BO34: =IF($AJ34="N", "N", IF($B34="Não", "Sim", IF(OR( BN34=$AJ34, AND($AJ34="B", OR(BN34="B", BN34="P", BN34="O")), AND($AJ34="P", OR(BN34="P", BN34="O")), AND($AJ34="O", BN34="O")), "Sim", "Não") ) ) -> Sim | BP34: B | BQ34: =IF($T34="N", "N", IF($B34="Não", "Sim", IF(OR( BP34=$T34, AND($T34="B", OR(BP34="B", BP34="P", BP34="O")), AND($T34="P", OR(BP34="P", BP34="O")), AND($T34="O", BP34="O")), "Sim", "Não") ) ) -> Sim | BR34: P | BS34: =IF($I34="N", "N", IF($B34="Não", "Sim", IF(OR( BR34=$I34, AND($I34="B", OR(BR34="B", BR34="P", BR34="O")), AND($I34="P", OR(BR34="P", BR34="O")), AND($I34="O", BR34="O")), "Sim", "Não") ) ) -> Sim | BT34: P | BU34: =IF($G34="N", "N", IF($B34="Não", "Sim", IF(OR( BT34=$G34, AND($G34="B", OR(BT34="B", BT34="P", BT34="O")), AND($G34="P", OR(BT34="P", BT34="O")), AND($G34="O", BT34="O")), "Sim", "Não") ) ) -> Sim | BV34: D | BW34: =IF($G34="N", "N", IF($B34="Não", "Sim", IF(OR( BV34=$G34, AND($G34="B", OR(BV34="B", BV34="P", BV34="O")), AND($G34="P", OR(BV34="P", BV34="O")), AND($G34="O", BV34="O")), "Sim", "Não") ) ) -> Sim | BX34: P | BY34: =IF($P34="N", "N", IF($B34="Não", "Sim", IF(OR( BX34=$P34, AND($P34="B", OR(BX34="B", BX34="P", BX34="O")), AND($P34="P", OR(BX34="P", BX34="O")), AND($P34="O", BX34="O")), "Sim", "Não") ) ) -> Sim | BZ34: B | CA34: =IF($G34="N", "N", IF($B34="Não", "Sim", IF(OR( BZ34=$G34, AND($G34="B", OR(BZ34="B", BZ34="P", BZ34="O")), AND($G34="P", OR(BZ34="P", BZ34="O")), AND($G34="O", BZ34="O")), "Sim", "Não") ) ) -> Sim
B35: Não | C35: Geral | D35: SQL para SQLServer (Criar Querys) | E35: B | F35: 0 | G35: B | H35: 0 | I35: P | J35: 1 | K35: O | L35: 1 | N35: B | O35: 0 | P35: B | Q35: 0 | R35: P | S35: 1 | T35: O | U35: 1 | W35: B | X35: 1 | Y35: B | Z35: 1 | AA35: P | AB35: 1 | AC35: P | AD35: 1 | AF35: B | AG35: 0 | AH35: B | AI35: 1 | AJ35: P | AK35: 1 | AL35: P | AM35: 1 | AO35: A | AP35: A | AQ35: A | AR35: A | AT35: P | AU35: =IF($P35="N", "N", IF($B35="Não", "Sim", IF(OR( AT35=$P35, AND($P35="B", OR(AT35="B", AT35="P", AT35="O")), AND($P35="P", OR(AT35="P", AT35="O")), AND($P35="O", AT35="O")), "Sim", "Não") ) ) -> Sim | AV35: P | AW35: =IF($I35="N", "N", IF($B35="Não", "Sim", IF(OR( AV35=$I35, AND($I35="B", OR(AV35="B", AV35="P", AV35="O")), AND($I35="P", OR(AV35="P", AV35="O")), AND($I35="O", AV35="O")), "Sim", "Não") ) ) -> Sim | AX35: P | AY35: =IF($R35="N", "N", IF($B35="Não", "Sim", IF(OR( AX35=$R35, AND($R35="B", OR(AX35="B", AX35="P", AX35="O")), AND($R35="P", OR(AX35="P", AX35="O")), AND($R35="O", AX35="O")), "Sim", "Não") ) ) -> Sim | AZ35: O | BA35: =IF($I35="N", "N", IF($B35="Não", "Sim", IF(OR( AZ35=$I35, AND($I35="B", OR(AZ35="B", AZ35="P", AZ35="O")), AND($I35="P", OR(AZ35="P", AZ35="O")), AND($I35="O", AZ35="O")), "Sim", "Não") ) ) -> Sim | BB35: P | BC35: =IF($AJ35="N", "N", IF($B35="Não", "Sim", IF(OR( BB35=$AJ35, AND($AJ35="B", OR(BB35="B", BB35="P", BB35="O")), AND($AJ35="P", OR(BB35="P", BB35="O")), AND($AJ35="O", BB35="O")), "Sim", "Não") ) ) -> Sim | BD35: P | BE35: =IF($AC35="N", "N", IF($B35="Não", "Sim", IF(OR( BD35=$AC35, AND($AC35="B", OR(BD35="B", BD35="P", BD35="O")), AND($AC35="P", OR(BD35="P", BD35="O")), AND($AC35="O", BD35="O")), "Sim", "Não") ) ) -> Sim | BF35: B | BG35: =IF($Y35="N", "N", IF($B35="Não", "Sim", IF(OR( BF35=$Y35, AND($Y35="B", OR(BF35="B", BF35="P", BF35="O")), AND($Y35="P", OR(BF35="P", BF35="O")), AND($Y35="O", BF35="O")), "Sim", "Não") ) ) -> Sim | BH35: O | BI35: =IF($K35="N", "N", IF($B35="Não", "Sim", IF(OR( BH35=$K35, AND($K35="B", OR(BH35="B", BH35="P", BH35="O")), AND($K35="P", OR(BH35="P", BH35="O")), AND($K35="O", BH35="O")), "Sim", "Não") ) ) -> Sim | BJ35: P | BK35: =IF($Y35="N", "N", IF($B35="Não", "Sim", IF(OR( BJ35=$Y35, AND($Y35="B", OR(BJ35="B", BJ35="P", BJ35="O")), AND($Y35="P", OR(BJ35="P", BJ35="O")), AND($Y35="O", BJ35="O")), "Sim", "Não") ) ) -> Sim | BL35: P | BM35: =IF($Y35="N", "N", IF($B35="Não", "Sim", IF(OR( BL35=$Y35, AND($Y35="B", OR(BL35="B", BL35="P", BL35="O")), AND($Y35="P", OR(BL35="P", BL35="O")), AND($Y35="O", BL35="O")), "Sim", "Não") ) ) -> Sim | BN35: P | BO35: =IF($AJ35="N", "N", IF($B35="Não", "Sim", IF(OR( BN35=$AJ35, AND($AJ35="B", OR(BN35="B", BN35="P", BN35="O")), AND($AJ35="P", OR(BN35="P", BN35="O")), AND($AJ35="O", BN35="O")), "Sim", "Não") ) ) -> Sim | BP35: O | BQ35: =IF($T35="N", "N", IF($B35="Não", "Sim", IF(OR( BP35=$T35, AND($T35="B", OR(BP35="B", BP35="P", BP35="O")), AND($T35="P", OR(BP35="P", BP35="O")), AND($T35="O", BP35="O")), "Sim", "Não") ) ) -> Sim | BR35: P | BS35: =IF($I35="N", "N", IF($B35="Não", "Sim", IF(OR( BR35=$I35, AND($I35="B", OR(BR35="B", BR35="P", BR35="O")), AND($I35="P", OR(BR35="P", BR35="O")), AND($I35="O", BR35="O")), "Sim", "Não") ) ) -> Sim | BT35: B | BU35: =IF($G35="N", "N", IF($B35="Não", "Sim", IF(OR( BT35=$G35, AND($G35="B", OR(BT35="B", BT35="P", BT35="O")), AND($G35="P", OR(BT35="P", BT35="O")), AND($G35="O", BT35="O")), "Sim", "Não") ) ) -> Sim | BV35: P | BW35: =IF($G35="N", "N", IF($B35="Não", "Sim", IF(OR( BV35=$G35, AND($G35="B", OR(BV35="B", BV35="P", BV35="O")), AND($G35="P", OR(BV35="P", BV35="O")), AND($G35="O", BV35="O")), "Sim", "Não") ) ) -> Sim | BX35: P | BY35: =IF($P35="N", "N", IF($B35="Não", "Sim", IF(OR( BX35=$P35, AND($P35="B", OR(BX35="B", BX35="P", BX35="O")), AND($P35="P", OR(BX35="P", BX35="O")), AND($P35="O", BX35="O")), "Sim", "Não") ) ) -> Sim | BZ35: P | CA35: =IF($G35="N", "N", IF($B35="Não", "Sim", IF(OR( BZ35=$G35, AND($G35="B", OR(BZ35="B", BZ35="P", BZ35="O")), AND($G35="P", OR(BZ35="P", BZ35="O")), AND($G35="O", BZ35="O")), "Sim", "Não") ) ) -> Sim
B36: Não | C36: Geral | D36: Gerenciamento de banco de dados (Gerenciar). Ex: SQL SERVER MANAGMENT, Query Plan, Profiler | E36: N | F36: N | G36: N | H36: N | I36: B | J36: 0 | K36: P | L36: 1 | N36: N | O36: N | P36: N | Q36: N | R36: B | S36: 0 | T36: P | U36: 1 | W36: N | X36: N | Y36: N | Z36: N | AA36: N | AB36: N | AC36: N | AD36: N | AF36: N | AG36: N | AH36: N | AI36: N | AJ36: N | AK36: N | AL36: N | AM36: N | AO36: A | AP36: A | AQ36: I | AR36: I | AT36: B | AU36: =IF($P36="N", "N", IF($B36="Não", "Sim", IF(OR( AT36=$P36, AND($P36="B", OR(AT36="B", AT36="P", AT36="O")), AND($P36="P", OR(AT36="P", AT36="O")), AND($P36="O", AT36="O")), "Sim", "Não") ) ) -> N | AV36: B | AW36: =IF($I36="N", "N", IF($B36="Não", "Sim", IF(OR( AV36=$I36, AND($I36="B", OR(AV36="B", AV36="P", AV36="O")), AND($I36="P", OR(AV36="P", AV36="O")), AND($I36="O", AV36="O")), "Sim", "Não") ) ) -> Sim | AX36: P | AY36: =IF($R36="N", "N", IF($B36="Não", "Sim", IF(OR( AX36=$R36, AND($R36="B", OR(AX36="B", AX36="P", AX36="O")), AND($R36="P", OR(AX36="P", AX36="O")), AND($R36="O", AX36="O")), "Sim", "Não") ) ) -> Sim | AZ36: P | BA36: =IF($I36="N", "N", IF($B36="Não", "Sim", IF(OR( AZ36=$I36, AND($I36="B", OR(AZ36="B", AZ36="P", AZ36="O")), AND($I36="P", OR(AZ36="P", AZ36="O")), AND($I36="O", AZ36="O")), "Sim", "Não") ) ) -> Sim | BB36: N | BC36: =IF($AJ36="N", "N", IF($B36="Não", "Sim", IF(OR( BB36=$AJ36, AND($AJ36="B", OR(BB36="B", BB36="P", BB36="O")), AND($AJ36="P", OR(BB36="P", BB36="O")), AND($AJ36="O", BB36="O")), "Sim", "Não") ) ) -> N | BD36: N | BE36: =IF($AC36="N", "N", IF($B36="Não", "Sim", IF(OR( BD36=$AC36, AND($AC36="B", OR(BD36="B", BD36="P", BD36="O")), AND($AC36="P", OR(BD36="P", BD36="O")), AND($AC36="O", BD36="O")), "Sim", "Não") ) ) -> N | BF36: N | BG36: =IF($Y36="N", "N", IF($B36="Não", "Sim", IF(OR( BF36=$Y36, AND($Y36="B", OR(BF36="B", BF36="P", BF36="O")), AND($Y36="P", OR(BF36="P", BF36="O")), AND($Y36="O", BF36="O")), "Sim", "Não") ) ) -> N | BH36: P | BI36: =IF($K36="N", "N", IF($B36="Não", "Sim", IF(OR( BH36=$K36, AND($K36="B", OR(BH36="B", BH36="P", BH36="O")), AND($K36="P", OR(BH36="P", BH36="O")), AND($K36="O", BH36="O")), "Sim", "Não") ) ) -> Sim | BJ36: N | BK36: =IF($Y36="N", "N", IF($B36="Não", "Sim", IF(OR( BJ36=$Y36, AND($Y36="B", OR(BJ36="B", BJ36="P", BJ36="O")), AND($Y36="P", OR(BJ36="P", BJ36="O")), AND($Y36="O", BJ36="O")), "Sim", "Não") ) ) -> N | BL36: N | BM36: =IF($Y36="N", "N", IF($B36="Não", "Sim", IF(OR( BL36=$Y36, AND($Y36="B", OR(BL36="B", BL36="P", BL36="O")), AND($Y36="P", OR(BL36="P", BL36="O")), AND($Y36="O", BL36="O")), "Sim", "Não") ) ) -> N | BN36: N | BO36: =IF($AJ36="N", "N", IF($B36="Não", "Sim", IF(OR( BN36=$AJ36, AND($AJ36="B", OR(BN36="B", BN36="P", BN36="O")), AND($AJ36="P", OR(BN36="P", BN36="O")), AND($AJ36="O", BN36="O")), "Sim", "Não") ) ) -> N | BP36: P | BQ36: =IF($T36="N", "N", IF($B36="Não", "Sim", IF(OR( BP36=$T36, AND($T36="B", OR(BP36="B", BP36="P", BP36="O")), AND($T36="P", OR(BP36="P", BP36="O")), AND($T36="O", BP36="O")), "Sim", "Não") ) ) -> Sim | BR36: P | BS36: =IF($I36="N", "N", IF($B36="Não", "Sim", IF(OR( BR36=$I36, AND($I36="B", OR(BR36="B", BR36="P", BR36="O")), AND($I36="P", OR(BR36="P", BR36="O")), AND($I36="O", BR36="O")), "Sim", "Não") ) ) -> Sim | BT36: D | BU36: =IF($G36="N", "N", IF($B36="Não", "Sim", IF(OR( BT36=$G36, AND($G36="B", OR(BT36="B", BT36="P", BT36="O")), AND($G36="P", OR(BT36="P", BT36="O")), AND($G36="O", BT36="O")), "Sim", "Não") ) ) -> N | BV36: P | BW36: =IF($G36="N", "N", IF($B36="Não", "Sim", IF(OR( BV36=$G36, AND($G36="B", OR(BV36="B", BV36="P", BV36="O")), AND($G36="P", OR(BV36="P", BV36="O")), AND($G36="O", BV36="O")), "Sim", "Não") ) ) -> N | BX36: B | BY36: =IF($P36="N", "N", IF($B36="Não", "Sim", IF(OR( BX36=$P36, AND($P36="B", OR(BX36="B", BX36="P", BX36="O")), AND($P36="P", OR(BX36="P", BX36="O")), AND($P36="O", BX36="O")), "Sim", "Não") ) ) -> N | BZ36: B | CA36: =IF($G36="N", "N", IF($B36="Não", "Sim", IF(OR( BZ36=$G36, AND($G36="B", OR(BZ36="B", BZ36="P", BZ36="O")), AND($G36="P", OR(BZ36="P", BZ36="O")), AND($G36="O", BZ36="O")), "Sim", "Não") ) ) -> N
B37: Não | C37: Geral | D37: Rabbit MQ (Message broker) | E37: B | F37: 0 | G37: B | H37: 0 | I37: P | J37: 1 | K37: O | L37: 1 | N37: B | O37: 0 | P37: B | Q37: 0 | R37: P | S37: 1 | T37: O | U37: 1 | W37: N | X37: N | Y37: B | Z37: 1 | AA37: P | AB37: 1 | AC37: P | AD37: 1 | AF37: B | AG37: 0 | AH37: B | AI37: 1 | AJ37: P | AK37: 1 | AL37: P | AM37: 1 | AO37: A | AP37: A | AQ37: A | AR37: A | AT37: P | AU37: =IF($P37="N", "N", IF($B37="Não", "Sim", IF(OR( AT37=$P37, AND($P37="B", OR(AT37="B", AT37="P", AT37="O")), AND($P37="P", OR(AT37="P", AT37="O")), AND($P37="O", AT37="O")), "Sim", "Não") ) ) -> Sim | AV37: P | AW37: =IF($I37="N", "N", IF($B37="Não", "Sim", IF(OR( AV37=$I37, AND($I37="B", OR(AV37="B", AV37="P", AV37="O")), AND($I37="P", OR(AV37="P", AV37="O")), AND($I37="O", AV37="O")), "Sim", "Não") ) ) -> Sim | AX37: P | AY37: =IF($R37="N", "N", IF($B37="Não", "Sim", IF(OR( AX37=$R37, AND($R37="B", OR(AX37="B", AX37="P", AX37="O")), AND($R37="P", OR(AX37="P", AX37="O")), AND($R37="O", AX37="O")), "Sim", "Não") ) ) -> Sim | AZ37: B | BA37: =IF($I37="N", "N", IF($B37="Não", "Sim", IF(OR( AZ37=$I37, AND($I37="B", OR(AZ37="B", AZ37="P", AZ37="O")), AND($I37="P", OR(AZ37="P", AZ37="O")), AND($I37="O", AZ37="O")), "Sim", "Não") ) ) -> Sim | BB37: P | BC37: =IF($AJ37="N", "N", IF($B37="Não", "Sim", IF(OR( BB37=$AJ37, AND($AJ37="B", OR(BB37="B", BB37="P", BB37="O")), AND($AJ37="P", OR(BB37="P", BB37="O")), AND($AJ37="O", BB37="O")), "Sim", "Não") ) ) -> Sim | BD37: P | BE37: =IF($AC37="N", "N", IF($B37="Não", "Sim", IF(OR( BD37=$AC37, AND($AC37="B", OR(BD37="B", BD37="P", BD37="O")), AND($AC37="P", OR(BD37="P", BD37="O")), AND($AC37="O", BD37="O")), "Sim", "Não") ) ) -> Sim | BF37: B | BG37: =IF($Y37="N", "N", IF($B37="Não", "Sim", IF(OR( BF37=$Y37, AND($Y37="B", OR(BF37="B", BF37="P", BF37="O")), AND($Y37="P", OR(BF37="P", BF37="O")), AND($Y37="O", BF37="O")), "Sim", "Não") ) ) -> Sim | BH37: O | BI37: =IF($K37="N", "N", IF($B37="Não", "Sim", IF(OR( BH37=$K37, AND($K37="B", OR(BH37="B", BH37="P", BH37="O")), AND($K37="P", OR(BH37="P", BH37="O")), AND($K37="O", BH37="O")), "Sim", "Não") ) ) -> Sim | BJ37: B | BK37: =IF($Y37="N", "N", IF($B37="Não", "Sim", IF(OR( BJ37=$Y37, AND($Y37="B", OR(BJ37="B", BJ37="P", BJ37="O")), AND($Y37="P", OR(BJ37="P", BJ37="O")), AND($Y37="O", BJ37="O")), "Sim", "Não") ) ) -> Sim | BL37: P | BM37: =IF($Y37="N", "N", IF($B37="Não", "Sim", IF(OR( BL37=$Y37, AND($Y37="B", OR(BL37="B", BL37="P", BL37="O")), AND($Y37="P", OR(BL37="P", BL37="O")), AND($Y37="O", BL37="O")), "Sim", "Não") ) ) -> Sim | BN37: P | BO37: =IF($AJ37="N", "N", IF($B37="Não", "Sim", IF(OR( BN37=$AJ37, AND($AJ37="B", OR(BN37="B", BN37="P", BN37="O")), AND($AJ37="P", OR(BN37="P", BN37="O")), AND($AJ37="O", BN37="O")), "Sim", "Não") ) ) -> Sim | BP37: B | BQ37: =IF($T37="N", "N", IF($B37="Não", "Sim", IF(OR( BP37=$T37, AND($T37="B", OR(BP37="B", BP37="P", BP37="O")), AND($T37="P", OR(BP37="P", BP37="O")), AND($T37="O", BP37="O")), "Sim", "Não") ) ) -> Sim | BR37: P | BS37: =IF($I37="N", "N", IF($B37="Não", "Sim", IF(OR( BR37=$I37, AND($I37="B", OR(BR37="B", BR37="P", BR37="O")), AND($I37="P", OR(BR37="P", BR37="O")), AND($I37="O", BR37="O")), "Sim", "Não") ) ) -> Sim | BT37: B | BU37: =IF($G37="N", "N", IF($B37="Não", "Sim", IF(OR( BT37=$G37, AND($G37="B", OR(BT37="B", BT37="P", BT37="O")), AND($G37="P", OR(BT37="P", BT37="O")), AND($G37="O", BT37="O")), "Sim", "Não") ) ) -> Sim | BV37: B | BW37: =IF($G37="N", "N", IF($B37="Não", "Sim", IF(OR( BV37=$G37, AND($G37="B", OR(BV37="B", BV37="P", BV37="O")), AND($G37="P", OR(BV37="P", BV37="O")), AND($G37="O", BV37="O")), "Sim", "Não") ) ) -> Sim | BX37: B | BY37: =IF($P37="N", "N", IF($B37="Não", "Sim", IF(OR( BX37=$P37, AND($P37="B", OR(BX37="B", BX37="P", BX37="O")), AND($P37="P", OR(BX37="P", BX37="O")), AND($P37="O", BX37="O")), "Sim", "Não") ) ) -> Sim | BZ37: P | CA37: =IF($G37="N", "N", IF($B37="Não", "Sim", IF(OR( BZ37=$G37, AND($G37="B", OR(BZ37="B", BZ37="P", BZ37="O")), AND($G37="P", OR(BZ37="P", BZ37="O")), AND($G37="O", BZ37="O")), "Sim", "Não") ) ) -> Sim
B38: Não | C38: Geral | D38: Estruturas de arquivos TXT, XML e JSON | E38: B | F38: 1 | G38: P | H38: 1 | I38: O | J38: 1 | K38: O | L38: 1 | N38: B | O38: 1 | P38: P | Q38: 1 | R38: O | S38: 1 | T38: O | U38: 1 | W38: B | X38: 1 | Y38: B | Z38: 1 | AA38: P | AB38: 1 | AC38: P | AD38: 1 | AF38: B | AG38: 1 | AH38: B | AI38: 1 | AJ38: P | AK38: 1 | AL38: P | AM38: 1 | AO38: A | AP38: A | AQ38: A | AR38: A | AT38: P | AU38: =IF($P38="N", "N", IF($B38="Não", "Sim", IF(OR( AT38=$P38, AND($P38="B", OR(AT38="B", AT38="P", AT38="O")), AND($P38="P", OR(AT38="P", AT38="O")), AND($P38="O", AT38="O")), "Sim", "Não") ) ) -> Sim | AV38: O | AW38: =IF($I38="N", "N", IF($B38="Não", "Sim", IF(OR( AV38=$I38, AND($I38="B", OR(AV38="B", AV38="P", AV38="O")), AND($I38="P", OR(AV38="P", AV38="O")), AND($I38="O", AV38="O")), "Sim", "Não") ) ) -> Sim | AX38: O | AY38: =IF($R38="N", "N", IF($B38="Não", "Sim", IF(OR( AX38=$R38, AND($R38="B", OR(AX38="B", AX38="P", AX38="O")), AND($R38="P", OR(AX38="P", AX38="O")), AND($R38="O", AX38="O")), "Sim", "Não") ) ) -> Sim | AZ38: O | BA38: =IF($I38="N", "N", IF($B38="Não", "Sim", IF(OR( AZ38=$I38, AND($I38="B", OR(AZ38="B", AZ38="P", AZ38="O")), AND($I38="P", OR(AZ38="P", AZ38="O")), AND($I38="O", AZ38="O")), "Sim", "Não") ) ) -> Sim | BB38: P | BC38: =IF($AJ38="N", "N", IF($B38="Não", "Sim", IF(OR( BB38=$AJ38, AND($AJ38="B", OR(BB38="B", BB38="P", BB38="O")), AND($AJ38="P", OR(BB38="P", BB38="O")), AND($AJ38="O", BB38="O")), "Sim", "Não") ) ) -> Sim | BD38: P | BE38: =IF($AC38="N", "N", IF($B38="Não", "Sim", IF(OR( BD38=$AC38, AND($AC38="B", OR(BD38="B", BD38="P", BD38="O")), AND($AC38="P", OR(BD38="P", BD38="O")), AND($AC38="O", BD38="O")), "Sim", "Não") ) ) -> Sim | BF38: B | BG38: =IF($Y38="N", "N", IF($B38="Não", "Sim", IF(OR( BF38=$Y38, AND($Y38="B", OR(BF38="B", BF38="P", BF38="O")), AND($Y38="P", OR(BF38="P", BF38="O")), AND($Y38="O", BF38="O")), "Sim", "Não") ) ) -> Sim | BH38: O | BI38: =IF($K38="N", "N", IF($B38="Não", "Sim", IF(OR( BH38=$K38, AND($K38="B", OR(BH38="B", BH38="P", BH38="O")), AND($K38="P", OR(BH38="P", BH38="O")), AND($K38="O", BH38="O")), "Sim", "Não") ) ) -> Sim | BJ38: P | BK38: =IF($Y38="N", "N", IF($B38="Não", "Sim", IF(OR( BJ38=$Y38, AND($Y38="B", OR(BJ38="B", BJ38="P", BJ38="O")), AND($Y38="P", OR(BJ38="P", BJ38="O")), AND($Y38="O", BJ38="O")), "Sim", "Não") ) ) -> Sim | BL38: P | BM38: =IF($Y38="N", "N", IF($B38="Não", "Sim", IF(OR( BL38=$Y38, AND($Y38="B", OR(BL38="B", BL38="P", BL38="O")), AND($Y38="P", OR(BL38="P", BL38="O")), AND($Y38="O", BL38="O")), "Sim", "Não") ) ) -> Sim | BN38: O | BO38: =IF($AJ38="N", "N", IF($B38="Não", "Sim", IF(OR( BN38=$AJ38, AND($AJ38="B", OR(BN38="B", BN38="P", BN38="O")), AND($AJ38="P", OR(BN38="P", BN38="O")), AND($AJ38="O", BN38="O")), "Sim", "Não") ) ) -> Sim | BP38: P | BQ38: =IF($T38="N", "N", IF($B38="Não", "Sim", IF(OR( BP38=$T38, AND($T38="B", OR(BP38="B", BP38="P", BP38="O")), AND($T38="P", OR(BP38="P", BP38="O")), AND($T38="O", BP38="O")), "Sim", "Não") ) ) -> Sim | BR38: O | BS38: =IF($I38="N", "N", IF($B38="Não", "Sim", IF(OR( BR38=$I38, AND($I38="B", OR(BR38="B", BR38="P", BR38="O")), AND($I38="P", OR(BR38="P", BR38="O")), AND($I38="O", BR38="O")), "Sim", "Não") ) ) -> Sim | BT38: P | BU38: =IF($G38="N", "N", IF($B38="Não", "Sim", IF(OR( BT38=$G38, AND($G38="B", OR(BT38="B", BT38="P", BT38="O")), AND($G38="P", OR(BT38="P", BT38="O")), AND($G38="O", BT38="O")), "Sim", "Não") ) ) -> Sim | BV38: P | BW38: =IF($G38="N", "N", IF($B38="Não", "Sim", IF(OR( BV38=$G38, AND($G38="B", OR(BV38="B", BV38="P", BV38="O")), AND($G38="P", OR(BV38="P", BV38="O")), AND($G38="O", BV38="O")), "Sim", "Não") ) ) -> Sim | BX38: P | BY38: =IF($P38="N", "N", IF($B38="Não", "Sim", IF(OR( BX38=$P38, AND($P38="B", OR(BX38="B", BX38="P", BX38="O")), AND($P38="P", OR(BX38="P", BX38="O")), AND($P38="O", BX38="O")), "Sim", "Não") ) ) -> Sim | BZ38: O | CA38: =IF($G38="N", "N", IF($B38="Não", "Sim", IF(OR( BZ38=$G38, AND($G38="B", OR(BZ38="B", BZ38="P", BZ38="O")), AND($G38="P", OR(BZ38="P", BZ38="O")), AND($G38="O", BZ38="O")), "Sim", "Não") ) ) -> Sim
B39: Não | C39: Geral | D39: Automatização de testes Frontend (Cypress) | E39: N | F39: N | G39: N | H39: N | I39: N | J39: N | K39: N | L39: N | N39: B | O39: 0 | P39: B | Q39: 0 | R39: B | S39: 0 | T39: P | U39: 0 | W39: B | X39: 0 | Y39: B | Z39: 1 | AA39: P | AB39: 1 | AC39: O | AD39: 1 | AF39: N | AG39: N | AH39: N | AI39: N | AJ39: N | AK39: N | AL39: N | AM39: N | AO39: I | AP39: A | AQ39: A | AR39: I | AT39: P | AU39: =IF($P39="N", "N", IF($B39="Não", "Sim", IF(OR( AT39=$P39, AND($P39="B", OR(AT39="B", AT39="P", AT39="O")), AND($P39="P", OR(AT39="P", AT39="O")), AND($P39="O", AT39="O")), "Sim", "Não") ) ) -> Sim | AV39: N | AW39: =IF($I39="N", "N", IF($B39="Não", "Sim", IF(OR( AV39=$I39, AND($I39="B", OR(AV39="B", AV39="P", AV39="O")), AND($I39="P", OR(AV39="P", AV39="O")), AND($I39="O", AV39="O")), "Sim", "Não") ) ) -> N | AX39: P | AY39: =IF($R39="N", "N", IF($B39="Não", "Sim", IF(OR( AX39=$R39, AND($R39="B", OR(AX39="B", AX39="P", AX39="O")), AND($R39="P", OR(AX39="P", AX39="O")), AND($R39="O", AX39="O")), "Sim", "Não") ) ) -> Sim | AZ39: N | BA39: =IF($I39="N", "N", IF($B39="Não", "Sim", IF(OR( AZ39=$I39, AND($I39="B", OR(AZ39="B", AZ39="P", AZ39="O")), AND($I39="P", OR(AZ39="P", AZ39="O")), AND($I39="O", AZ39="O")), "Sim", "Não") ) ) -> N | BB39: N | BC39: =IF($AJ39="N", "N", IF($B39="Não", "Sim", IF(OR( BB39=$AJ39, AND($AJ39="B", OR(BB39="B", BB39="P", BB39="O")), AND($AJ39="P", OR(BB39="P", BB39="O")), AND($AJ39="O", BB39="O")), "Sim", "Não") ) ) -> N | BD39: O | BE39: =IF($AC39="N", "N", IF($B39="Não", "Sim", IF(OR( BD39=$AC39, AND($AC39="B", OR(BD39="B", BD39="P", BD39="O")), AND($AC39="P", OR(BD39="P", BD39="O")), AND($AC39="O", BD39="O")), "Sim", "Não") ) ) -> Sim | BF39: P | BG39: =IF($Y39="N", "N", IF($B39="Não", "Sim", IF(OR( BF39=$Y39, AND($Y39="B", OR(BF39="B", BF39="P", BF39="O")), AND($Y39="P", OR(BF39="P", BF39="O")), AND($Y39="O", BF39="O")), "Sim", "Não") ) ) -> Sim | BH39: N | BI39: =IF($K39="N", "N", IF($B39="Não", "Sim", IF(OR( BH39=$K39, AND($K39="B", OR(BH39="B", BH39="P", BH39="O")), AND($K39="P", OR(BH39="P", BH39="O")), AND($K39="O", BH39="O")), "Sim", "Não") ) ) -> N | BJ39: B | BK39: =IF($Y39="N", "N", IF($B39="Não", "Sim", IF(OR( BJ39=$Y39, AND($Y39="B", OR(BJ39="B", BJ39="P", BJ39="O")), AND($Y39="P", OR(BJ39="P", BJ39="O")), AND($Y39="O", BJ39="O")), "Sim", "Não") ) ) -> Sim | BL39: P | BM39: =IF($Y39="N", "N", IF($B39="Não", "Sim", IF(OR( BL39=$Y39, AND($Y39="B", OR(BL39="B", BL39="P", BL39="O")), AND($Y39="P", OR(BL39="P", BL39="O")), AND($Y39="O", BL39="O")), "Sim", "Não") ) ) -> Sim | BN39: N | BO39: =IF($AJ39="N", "N", IF($B39="Não", "Sim", IF(OR( BN39=$AJ39, AND($AJ39="B", OR(BN39="B", BN39="P", BN39="O")), AND($AJ39="P", OR(BN39="P", BN39="O")), AND($AJ39="O", BN39="O")), "Sim", "Não") ) ) -> N | BP39: P | BQ39: =IF($T39="N", "N", IF($B39="Não", "Sim", IF(OR( BP39=$T39, AND($T39="B", OR(BP39="B", BP39="P", BP39="O")), AND($T39="P", OR(BP39="P", BP39="O")), AND($T39="O", BP39="O")), "Sim", "Não") ) ) -> Sim | BR39: N | BS39: =IF($I39="N", "N", IF($B39="Não", "Sim", IF(OR( BR39=$I39, AND($I39="B", OR(BR39="B", BR39="P", BR39="O")), AND($I39="P", OR(BR39="P", BR39="O")), AND($I39="O", BR39="O")), "Sim", "Não") ) ) -> N | BT39: N | BU39: =IF($G39="N", "N", IF($B39="Não", "Sim", IF(OR( BT39=$G39, AND($G39="B", OR(BT39="B", BT39="P", BT39="O")), AND($G39="P", OR(BT39="P", BT39="O")), AND($G39="O", BT39="O")), "Sim", "Não") ) ) -> N | BV39: N | BW39: =IF($G39="N", "N", IF($B39="Não", "Sim", IF(OR( BV39=$G39, AND($G39="B", OR(BV39="B", BV39="P", BV39="O")), AND($G39="P", OR(BV39="P", BV39="O")), AND($G39="O", BV39="O")), "Sim", "Não") ) ) -> N | BX39: P | BY39: =IF($P39="N", "N", IF($B39="Não", "Sim", IF(OR( BX39=$P39, AND($P39="B", OR(BX39="B", BX39="P", BX39="O")), AND($P39="P", OR(BX39="P", BX39="O")), AND($P39="O", BX39="O")), "Sim", "Não") ) ) -> Sim | BZ39: N | CA39: =IF($G39="N", "N", IF($B39="Não", "Sim", IF(OR( BZ39=$G39, AND($G39="B", OR(BZ39="B", BZ39="P", BZ39="O")), AND($G39="P", OR(BZ39="P", BZ39="O")), AND($G39="O", BZ39="O")), "Sim", "Não") ) ) -> N
B40: Não | C40: Geral | D40: Desenvolvimento Seguro (WAF CSP e PenTest) | E40: N | F40: N | G40: B | H40: 0 | I40: P | J40: 1 | K40: P | L40: 1 | N40: B | O40: 0 | P40: B | Q40: 1 | R40: P | S40: 1 | T40: P | U40: 1 | W40: N | X40: N | Y40: B | Z40: 0 | AA40: B | AB40: 1 | AC40: P | AD40: 1 | AF40: N | AG40: N | AH40: N | AI40: N | AJ40: B | AK40: 0 | AL40: B | AM40: 0 | AO40: A | AP40: A | AQ40: A | AR40: A | AT40: B | AU40: =IF($P40="N", "N", IF($B40="Não", "Sim", IF(OR( AT40=$P40, AND($P40="B", OR(AT40="B", AT40="P", AT40="O")), AND($P40="P", OR(AT40="P", AT40="O")), AND($P40="O", AT40="O")), "Sim", "Não") ) ) -> Sim | AV40: P | AW40: =IF($I40="N", "N", IF($B40="Não", "Sim", IF(OR( AV40=$I40, AND($I40="B", OR(AV40="B", AV40="P", AV40="O")), AND($I40="P", OR(AV40="P", AV40="O")), AND($I40="O", AV40="O")), "Sim", "Não") ) ) -> Sim | AX40: P | AY40: =IF($R40="N", "N", IF($B40="Não", "Sim", IF(OR( AX40=$R40, AND($R40="B", OR(AX40="B", AX40="P", AX40="O")), AND($R40="P", OR(AX40="P", AX40="O")), AND($R40="O", AX40="O")), "Sim", "Não") ) ) -> Sim | AZ40: D | BA40: =IF($I40="N", "N", IF($B40="Não", "Sim", IF(OR( AZ40=$I40, AND($I40="B", OR(AZ40="B", AZ40="P", AZ40="O")), AND($I40="P", OR(AZ40="P", AZ40="O")), AND($I40="O", AZ40="O")), "Sim", "Não") ) ) -> Sim | BB40: P | BC40: =IF($AJ40="N", "N", IF($B40="Não", "Sim", IF(OR( BB40=$AJ40, AND($AJ40="B", OR(BB40="B", BB40="P", BB40="O")), AND($AJ40="P", OR(BB40="P", BB40="O")), AND($AJ40="O", BB40="O")), "Sim", "Não") ) ) -> Sim | BD40: P | BE40: =IF($AC40="N", "N", IF($B40="Não", "Sim", IF(OR( BD40=$AC40, AND($AC40="B", OR(BD40="B", BD40="P", BD40="O")), AND($AC40="P", OR(BD40="P", BD40="O")), AND($AC40="O", BD40="O")), "Sim", "Não") ) ) -> Sim | BF40: D | BG40: =IF($Y40="N", "N", IF($B40="Não", "Sim", IF(OR( BF40=$Y40, AND($Y40="B", OR(BF40="B", BF40="P", BF40="O")), AND($Y40="P", OR(BF40="P", BF40="O")), AND($Y40="O", BF40="O")), "Sim", "Não") ) ) -> Sim | BH40: P | BI40: =IF($K40="N", "N", IF($B40="Não", "Sim", IF(OR( BH40=$K40, AND($K40="B", OR(BH40="B", BH40="P", BH40="O")), AND($K40="P", OR(BH40="P", BH40="O")), AND($K40="O", BH40="O")), "Sim", "Não") ) ) -> Sim | BJ40: D | BK40: =IF($Y40="N", "N", IF($B40="Não", "Sim", IF(OR( BJ40=$Y40, AND($Y40="B", OR(BJ40="B", BJ40="P", BJ40="O")), AND($Y40="P", OR(BJ40="P", BJ40="O")), AND($Y40="O", BJ40="O")), "Sim", "Não") ) ) -> Sim | BL40: D | BM40: =IF($Y40="N", "N", IF($B40="Não", "Sim", IF(OR( BL40=$Y40, AND($Y40="B", OR(BL40="B", BL40="P", BL40="O")), AND($Y40="P", OR(BL40="P", BL40="O")), AND($Y40="O", BL40="O")), "Sim", "Não") ) ) -> Sim | BN40: P | BO40: =IF($AJ40="N", "N", IF($B40="Não", "Sim", IF(OR( BN40=$AJ40, AND($AJ40="B", OR(BN40="B", BN40="P", BN40="O")), AND($AJ40="P", OR(BN40="P", BN40="O")), AND($AJ40="O", BN40="O")), "Sim", "Não") ) ) -> Sim | BP40: B | BQ40: =IF($T40="N", "N", IF($B40="Não", "Sim", IF(OR( BP40=$T40, AND($T40="B", OR(BP40="B", BP40="P", BP40="O")), AND($T40="P", OR(BP40="P", BP40="O")), AND($T40="O", BP40="O")), "Sim", "Não") ) ) -> Sim | BR40: P | BS40: =IF($I40="N", "N", IF($B40="Não", "Sim", IF(OR( BR40=$I40, AND($I40="B", OR(BR40="B", BR40="P", BR40="O")), AND($I40="P", OR(BR40="P", BR40="O")), AND($I40="O", BR40="O")), "Sim", "Não") ) ) -> Sim | BT40: B | BU40: =IF($G40="N", "N", IF($B40="Não", "Sim", IF(OR( BT40=$G40, AND($G40="B", OR(BT40="B", BT40="P", BT40="O")), AND($G40="P", OR(BT40="P", BT40="O")), AND($G40="O", BT40="O")), "Sim", "Não") ) ) -> Sim | BV40: B | BW40: =IF($G40="N", "N", IF($B40="Não", "Sim", IF(OR( BV40=$G40, AND($G40="B", OR(BV40="B", BV40="P", BV40="O")), AND($G40="P", OR(BV40="P", BV40="O")), AND($G40="O", BV40="O")), "Sim", "Não") ) ) -> Sim | BX40: B | BY40: =IF($P40="N", "N", IF($B40="Não", "Sim", IF(OR( BX40=$P40, AND($P40="B", OR(BX40="B", BX40="P", BX40="O")), AND($P40="P", OR(BX40="P", BX40="O")), AND($P40="O", BX40="O")), "Sim", "Não") ) ) -> Sim | BZ40: B | CA40: =IF($G40="N", "N", IF($B40="Não", "Sim", IF(OR( BZ40=$G40, AND($G40="B", OR(BZ40="B", BZ40="P", BZ40="O")), AND($G40="P", OR(BZ40="P", BZ40="O")), AND($G40="O", BZ40="O")), "Sim", "Não") ) ) -> Sim
B41: Não | C41: Testes | D41: Logica de programação | E41: N | F41: N | G41: N | H41: N | I41: N | J41: N | K41: N | L41: N | N41: N | O41: N | P41: N | Q41: N | R41: N | S41: N | T41: N | U41: N | W41: B | X41: 0 | Y41: B | Z41: 0 | AA41: P | AB41: 0 | AC41: P | AD41: 0 | AF41: N | AG41: N | AH41: N | AI41: N | AJ41: N | AK41: N | AL41: N | AM41: N | AO41: I | AP41: I | AQ41: A | AR41: I | AT41: N | AU41: =IF($P41="N", "N", IF($B41="Não", "Sim", IF(OR( AT41=$P41, AND($P41="B", OR(AT41="B", AT41="P", AT41="O")), AND($P41="P", OR(AT41="P", AT41="O")), AND($P41="O", AT41="O")), "Sim", "Não") ) ) -> N | AV41: N | AW41: =IF($I41="N", "N", IF($B41="Não", "Sim", IF(OR( AV41=$I41, AND($I41="B", OR(AV41="B", AV41="P", AV41="O")), AND($I41="P", OR(AV41="P", AV41="O")), AND($I41="O", AV41="O")), "Sim", "Não") ) ) -> N | AX41: N | AY41: =IF($R41="N", "N", IF($B41="Não", "Sim", IF(OR( AX41=$R41, AND($R41="B", OR(AX41="B", AX41="P", AX41="O")), AND($R41="P", OR(AX41="P", AX41="O")), AND($R41="O", AX41="O")), "Sim", "Não") ) ) -> N | AZ41: N | BA41: =IF($I41="N", "N", IF($B41="Não", "Sim", IF(OR( AZ41=$I41, AND($I41="B", OR(AZ41="B", AZ41="P", AZ41="O")), AND($I41="P", OR(AZ41="P", AZ41="O")), AND($I41="O", AZ41="O")), "Sim", "Não") ) ) -> N | BB41: N | BC41: =IF($AJ41="N", "N", IF($B41="Não", "Sim", IF(OR( BB41=$AJ41, AND($AJ41="B", OR(BB41="B", BB41="P", BB41="O")), AND($AJ41="P", OR(BB41="P", BB41="O")), AND($AJ41="O", BB41="O")), "Sim", "Não") ) ) -> N | BD41: P | BE41: =IF($AC41="N", "N", IF($B41="Não", "Sim", IF(OR( BD41=$AC41, AND($AC41="B", OR(BD41="B", BD41="P", BD41="O")), AND($AC41="P", OR(BD41="P", BD41="O")), AND($AC41="O", BD41="O")), "Sim", "Não") ) ) -> Sim | BF41: P | BG41: =IF($Y41="N", "N", IF($B41="Não", "Sim", IF(OR( BF41=$Y41, AND($Y41="B", OR(BF41="B", BF41="P", BF41="O")), AND($Y41="P", OR(BF41="P", BF41="O")), AND($Y41="O", BF41="O")), "Sim", "Não") ) ) -> Sim | BH41: N | BI41: =IF($K41="N", "N", IF($B41="Não", "Sim", IF(OR( BH41=$K41, AND($K41="B", OR(BH41="B", BH41="P", BH41="O")), AND($K41="P", OR(BH41="P", BH41="O")), AND($K41="O", BH41="O")), "Sim", "Não") ) ) -> N | BJ41: P | BK41: =IF($Y41="N", "N", IF($B41="Não", "Sim", IF(OR( BJ41=$Y41, AND($Y41="B", OR(BJ41="B", BJ41="P", BJ41="O")), AND($Y41="P", OR(BJ41="P", BJ41="O")), AND($Y41="O", BJ41="O")), "Sim", "Não") ) ) -> Sim | BL41: P | BM41: =IF($Y41="N", "N", IF($B41="Não", "Sim", IF(OR( BL41=$Y41, AND($Y41="B", OR(BL41="B", BL41="P", BL41="O")), AND($Y41="P", OR(BL41="P", BL41="O")), AND($Y41="O", BL41="O")), "Sim", "Não") ) ) -> Sim | BN41: N | BO41: =IF($AJ41="N", "N", IF($B41="Não", "Sim", IF(OR( BN41=$AJ41, AND($AJ41="B", OR(BN41="B", BN41="P", BN41="O")), AND($AJ41="P", OR(BN41="P", BN41="O")), AND($AJ41="O", BN41="O")), "Sim", "Não") ) ) -> N | BP41: N | BQ41: =IF($T41="N", "N", IF($B41="Não", "Sim", IF(OR( BP41=$T41, AND($T41="B", OR(BP41="B", BP41="P", BP41="O")), AND($T41="P", OR(BP41="P", BP41="O")), AND($T41="O", BP41="O")), "Sim", "Não") ) ) -> N | BR41: N | BS41: =IF($I41="N", "N", IF($B41="Não", "Sim", IF(OR( BR41=$I41, AND($I41="B", OR(BR41="B", BR41="P", BR41="O")), AND($I41="P", OR(BR41="P", BR41="O")), AND($I41="O", BR41="O")), "Sim", "Não") ) ) -> N | BT41: N | BU41: =IF($G41="N", "N", IF($B41="Não", "Sim", IF(OR( BT41=$G41, AND($G41="B", OR(BT41="B", BT41="P", BT41="O")), AND($G41="P", OR(BT41="P", BT41="O")), AND($G41="O", BT41="O")), "Sim", "Não") ) ) -> N | BV41: N | BW41: =IF($G41="N", "N", IF($B41="Não", "Sim", IF(OR( BV41=$G41, AND($G41="B", OR(BV41="B", BV41="P", BV41="O")), AND($G41="P", OR(BV41="P", BV41="O")), AND($G41="O", BV41="O")), "Sim", "Não") ) ) -> N | BX41: N | BY41: =IF($P41="N", "N", IF($B41="Não", "Sim", IF(OR( BX41=$P41, AND($P41="B", OR(BX41="B", BX41="P", BX41="O")), AND($P41="P", OR(BX41="P", BX41="O")), AND($P41="O", BX41="O")), "Sim", "Não") ) ) -> N | BZ41: N | CA41: =IF($G41="N", "N", IF($B41="Não", "Sim", IF(OR( BZ41=$G41, AND($G41="B", OR(BZ41="B", BZ41="P", BZ41="O")), AND($G41="P", OR(BZ41="P", BZ41="O")), AND($G41="O", BZ41="O")), "Sim", "Não") ) ) -> N
B42: Não | C42: Testes | D42: Fundamentos de Teste de Software | E42: N | F42: N | G42: N | H42: N | I42: N | J42: N | K42: N | L42: N | N42: N | O42: N | P42: N | Q42: N | R42: N | S42: N | T42: N | U42: N | W42: B | X42: 0 | Y42: B | Z42: 1 | AA42: P | AB42: 1 | AC42: O | AD42: 1 | AF42: N | AG42: N | AH42: N | AI42: N | AJ42: N | AK42: N | AL42: N | AM42: N | AO42: I | AP42: I | AQ42: A | AR42: I | AT42: N | AU42: =IF($P42="N", "N", IF($B42="Não", "Sim", IF(OR( AT42=$P42, AND($P42="B", OR(AT42="B", AT42="P", AT42="O")), AND($P42="P", OR(AT42="P", AT42="O")), AND($P42="O", AT42="O")), "Sim", "Não") ) ) -> N | AV42: N | AW42: =IF($I42="N", "N", IF($B42="Não", "Sim", IF(OR( AV42=$I42, AND($I42="B", OR(AV42="B", AV42="P", AV42="O")), AND($I42="P", OR(AV42="P", AV42="O")), AND($I42="O", AV42="O")), "Sim", "Não") ) ) -> N | AX42: N | AY42: =IF($R42="N", "N", IF($B42="Não", "Sim", IF(OR( AX42=$R42, AND($R42="B", OR(AX42="B", AX42="P", AX42="O")), AND($R42="P", OR(AX42="P", AX42="O")), AND($R42="O", AX42="O")), "Sim", "Não") ) ) -> N | AZ42: N | BA42: =IF($I42="N", "N", IF($B42="Não", "Sim", IF(OR( AZ42=$I42, AND($I42="B", OR(AZ42="B", AZ42="P", AZ42="O")), AND($I42="P", OR(AZ42="P", AZ42="O")), AND($I42="O", AZ42="O")), "Sim", "Não") ) ) -> N | BB42: N | BC42: =IF($AJ42="N", "N", IF($B42="Não", "Sim", IF(OR( BB42=$AJ42, AND($AJ42="B", OR(BB42="B", BB42="P", BB42="O")), AND($AJ42="P", OR(BB42="P", BB42="O")), AND($AJ42="O", BB42="O")), "Sim", "Não") ) ) -> N | BD42: O | BE42: =IF($AC42="N", "N", IF($B42="Não", "Sim", IF(OR( BD42=$AC42, AND($AC42="B", OR(BD42="B", BD42="P", BD42="O")), AND($AC42="P", OR(BD42="P", BD42="O")), AND($AC42="O", BD42="O")), "Sim", "Não") ) ) -> Sim | BF42: B | BG42: =IF($Y42="N", "N", IF($B42="Não", "Sim", IF(OR( BF42=$Y42, AND($Y42="B", OR(BF42="B", BF42="P", BF42="O")), AND($Y42="P", OR(BF42="P", BF42="O")), AND($Y42="O", BF42="O")), "Sim", "Não") ) ) -> Sim | BH42: N | BI42: =IF($K42="N", "N", IF($B42="Não", "Sim", IF(OR( BH42=$K42, AND($K42="B", OR(BH42="B", BH42="P", BH42="O")), AND($K42="P", OR(BH42="P", BH42="O")), AND($K42="O", BH42="O")), "Sim", "Não") ) ) -> N | BJ42: B | BK42: =IF($Y42="N", "N", IF($B42="Não", "Sim", IF(OR( BJ42=$Y42, AND($Y42="B", OR(BJ42="B", BJ42="P", BJ42="O")), AND($Y42="P", OR(BJ42="P", BJ42="O")), AND($Y42="O", BJ42="O")), "Sim", "Não") ) ) -> Sim | BL42: P | BM42: =IF($Y42="N", "N", IF($B42="Não", "Sim", IF(OR( BL42=$Y42, AND($Y42="B", OR(BL42="B", BL42="P", BL42="O")), AND($Y42="P", OR(BL42="P", BL42="O")), AND($Y42="O", BL42="O")), "Sim", "Não") ) ) -> Sim | BN42: N | BO42: =IF($AJ42="N", "N", IF($B42="Não", "Sim", IF(OR( BN42=$AJ42, AND($AJ42="B", OR(BN42="B", BN42="P", BN42="O")), AND($AJ42="P", OR(BN42="P", BN42="O")), AND($AJ42="O", BN42="O")), "Sim", "Não") ) ) -> N | BP42: N | BQ42: =IF($T42="N", "N", IF($B42="Não", "Sim", IF(OR( BP42=$T42, AND($T42="B", OR(BP42="B", BP42="P", BP42="O")), AND($T42="P", OR(BP42="P", BP42="O")), AND($T42="O", BP42="O")), "Sim", "Não") ) ) -> N | BR42: N | BS42: =IF($I42="N", "N", IF($B42="Não", "Sim", IF(OR( BR42=$I42, AND($I42="B", OR(BR42="B", BR42="P", BR42="O")), AND($I42="P", OR(BR42="P", BR42="O")), AND($I42="O", BR42="O")), "Sim", "Não") ) ) -> N | BT42: N | BU42: =IF($G42="N", "N", IF($B42="Não", "Sim", IF(OR( BT42=$G42, AND($G42="B", OR(BT42="B", BT42="P", BT42="O")), AND($G42="P", OR(BT42="P", BT42="O")), AND($G42="O", BT42="O")), "Sim", "Não") ) ) -> N | BV42: N | BW42: =IF($G42="N", "N", IF($B42="Não", "Sim", IF(OR( BV42=$G42, AND($G42="B", OR(BV42="B", BV42="P", BV42="O")), AND($G42="P", OR(BV42="P", BV42="O")), AND($G42="O", BV42="O")), "Sim", "Não") ) ) -> N | BX42: N | BY42: =IF($P42="N", "N", IF($B42="Não", "Sim", IF(OR( BX42=$P42, AND($P42="B", OR(BX42="B", BX42="P", BX42="O")), AND($P42="P", OR(BX42="P", BX42="O")), AND($P42="O", BX42="O")), "Sim", "Não") ) ) -> N | BZ42: N | CA42: =IF($G42="N", "N", IF($B42="Não", "Sim", IF(OR( BZ42=$G42, AND($G42="B", OR(BZ42="B", BZ42="P", BZ42="O")), AND($G42="P", OR(BZ42="P", BZ42="O")), AND($G42="O", BZ42="O")), "Sim", "Não") ) ) -> N
B43: Não | C43: Geral | D43: IIS - Publicações/Utilizar/Configurações | E43: B | F43: 0 | G43: B | H43: 0 | I43: B | J43: 0 | K43: P | L43: 1 | N43: B | O43: 0 | P43: B | Q43: 0 | R43: P | S43: 1 | T43: P | U43: 1 | W43: B | X43: 0 | Y43: B | Z43: 0 | AA43: P | AB43: 1 | AC43: P | AD43: 1 | AF43: B | AG43: 0 | AH43: B | AI43: 1 | AJ43: P | AK43: 1 | AL43: P | AM43: 1 | AO43: A | AP43: A | AQ43: A | AR43: A | AT43: P | AU43: =IF($P43="N", "N", IF($B43="Não", "Sim", IF(OR( AT43=$P43, AND($P43="B", OR(AT43="B", AT43="P", AT43="O")), AND($P43="P", OR(AT43="P", AT43="O")), AND($P43="O", AT43="O")), "Sim", "Não") ) ) -> Sim | AV43: P | AW43: =IF($I43="N", "N", IF($B43="Não", "Sim", IF(OR( AV43=$I43, AND($I43="B", OR(AV43="B", AV43="P", AV43="O")), AND($I43="P", OR(AV43="P", AV43="O")), AND($I43="O", AV43="O")), "Sim", "Não") ) ) -> Sim | AX43: P | AY43: =IF($R43="N", "N", IF($B43="Não", "Sim", IF(OR( AX43=$R43, AND($R43="B", OR(AX43="B", AX43="P", AX43="O")), AND($R43="P", OR(AX43="P", AX43="O")), AND($R43="O", AX43="O")), "Sim", "Não") ) ) -> Sim | AZ43: P | BA43: =IF($I43="N", "N", IF($B43="Não", "Sim", IF(OR( AZ43=$I43, AND($I43="B", OR(AZ43="B", AZ43="P", AZ43="O")), AND($I43="P", OR(AZ43="P", AZ43="O")), AND($I43="O", AZ43="O")), "Sim", "Não") ) ) -> Sim | BB43: P | BC43: =IF($AJ43="N", "N", IF($B43="Não", "Sim", IF(OR( BB43=$AJ43, AND($AJ43="B", OR(BB43="B", BB43="P", BB43="O")), AND($AJ43="P", OR(BB43="P", BB43="O")), AND($AJ43="O", BB43="O")), "Sim", "Não") ) ) -> Sim | BD43: P | BE43: =IF($AC43="N", "N", IF($B43="Não", "Sim", IF(OR( BD43=$AC43, AND($AC43="B", OR(BD43="B", BD43="P", BD43="O")), AND($AC43="P", OR(BD43="P", BD43="O")), AND($AC43="O", BD43="O")), "Sim", "Não") ) ) -> Sim | BF43: B | BG43: =IF($Y43="N", "N", IF($B43="Não", "Sim", IF(OR( BF43=$Y43, AND($Y43="B", OR(BF43="B", BF43="P", BF43="O")), AND($Y43="P", OR(BF43="P", BF43="O")), AND($Y43="O", BF43="O")), "Sim", "Não") ) ) -> Sim | BH43: P | BI43: =IF($K43="N", "N", IF($B43="Não", "Sim", IF(OR( BH43=$K43, AND($K43="B", OR(BH43="B", BH43="P", BH43="O")), AND($K43="P", OR(BH43="P", BH43="O")), AND($K43="O", BH43="O")), "Sim", "Não") ) ) -> Sim | BJ43: B | BK43: =IF($Y43="N", "N", IF($B43="Não", "Sim", IF(OR( BJ43=$Y43, AND($Y43="B", OR(BJ43="B", BJ43="P", BJ43="O")), AND($Y43="P", OR(BJ43="P", BJ43="O")), AND($Y43="O", BJ43="O")), "Sim", "Não") ) ) -> Sim | BL43: B | BM43: =IF($Y43="N", "N", IF($B43="Não", "Sim", IF(OR( BL43=$Y43, AND($Y43="B", OR(BL43="B", BL43="P", BL43="O")), AND($Y43="P", OR(BL43="P", BL43="O")), AND($Y43="O", BL43="O")), "Sim", "Não") ) ) -> Sim | BN43: P | BO43: =IF($AJ43="N", "N", IF($B43="Não", "Sim", IF(OR( BN43=$AJ43, AND($AJ43="B", OR(BN43="B", BN43="P", BN43="O")), AND($AJ43="P", OR(BN43="P", BN43="O")), AND($AJ43="O", BN43="O")), "Sim", "Não") ) ) -> Sim | BP43: B | BQ43: =IF($T43="N", "N", IF($B43="Não", "Sim", IF(OR( BP43=$T43, AND($T43="B", OR(BP43="B", BP43="P", BP43="O")), AND($T43="P", OR(BP43="P", BP43="O")), AND($T43="O", BP43="O")), "Sim", "Não") ) ) -> Sim | BR43: D | BS43: =IF($I43="N", "N", IF($B43="Não", "Sim", IF(OR( BR43=$I43, AND($I43="B", OR(BR43="B", BR43="P", BR43="O")), AND($I43="P", OR(BR43="P", BR43="O")), AND($I43="O", BR43="O")), "Sim", "Não") ) ) -> Sim | BT43: B | BU43: =IF($G43="N", "N", IF($B43="Não", "Sim", IF(OR( BT43=$G43, AND($G43="B", OR(BT43="B", BT43="P", BT43="O")), AND($G43="P", OR(BT43="P", BT43="O")), AND($G43="O", BT43="O")), "Sim", "Não") ) ) -> Sim | BV43: D | BW43: =IF($G43="N", "N", IF($B43="Não", "Sim", IF(OR( BV43=$G43, AND($G43="B", OR(BV43="B", BV43="P", BV43="O")), AND($G43="P", OR(BV43="P", BV43="O")), AND($G43="O", BV43="O")), "Sim", "Não") ) ) -> Sim | BX43: P | BY43: =IF($P43="N", "N", IF($B43="Não", "Sim", IF(OR( BX43=$P43, AND($P43="B", OR(BX43="B", BX43="P", BX43="O")), AND($P43="P", OR(BX43="P", BX43="O")), AND($P43="O", BX43="O")), "Sim", "Não") ) ) -> Sim | BZ43: P | CA43: =IF($G43="N", "N", IF($B43="Não", "Sim", IF(OR( BZ43=$G43, AND($G43="B", OR(BZ43="B", BZ43="P", BZ43="O")), AND($G43="P", OR(BZ43="P", BZ43="O")), AND($G43="O", BZ43="O")), "Sim", "Não") ) ) -> Sim
B44: Não | C44: Testes | D44: Framework de automação - K6 | E44: N | F44: N | G44: N | H44: N | I44: N | J44: N | K44: N | L44: N | N44: N | O44: N | P44: N | Q44: N | R44: N | S44: N | T44: N | U44: N | W44: B | X44: 0 | Y44: B | Z44: 0 | AA44: P | AB44: 0 | AC44: P | AD44: 1 | AF44: N | AG44: N | AH44: N | AI44: N | AJ44: N | AK44: N | AL44: N | AM44: N | AO44: I | AP44: I | AQ44: A | AR44: I | AT44: N | AU44: =IF($P44="N", "N", IF($B44="Não", "Sim", IF(OR( AT44=$P44, AND($P44="B", OR(AT44="B", AT44="P", AT44="O")), AND($P44="P", OR(AT44="P", AT44="O")), AND($P44="O", AT44="O")), "Sim", "Não") ) ) -> N | AV44: N | AW44: =IF($I44="N", "N", IF($B44="Não", "Sim", IF(OR( AV44=$I44, AND($I44="B", OR(AV44="B", AV44="P", AV44="O")), AND($I44="P", OR(AV44="P", AV44="O")), AND($I44="O", AV44="O")), "Sim", "Não") ) ) -> N | AX44: N | AY44: =IF($R44="N", "N", IF($B44="Não", "Sim", IF(OR( AX44=$R44, AND($R44="B", OR(AX44="B", AX44="P", AX44="O")), AND($R44="P", OR(AX44="P", AX44="O")), AND($R44="O", AX44="O")), "Sim", "Não") ) ) -> N | AZ44: N | BA44: =IF($I44="N", "N", IF($B44="Não", "Sim", IF(OR( AZ44=$I44, AND($I44="B", OR(AZ44="B", AZ44="P", AZ44="O")), AND($I44="P", OR(AZ44="P", AZ44="O")), AND($I44="O", AZ44="O")), "Sim", "Não") ) ) -> N | BB44: N | BC44: =IF($AJ44="N", "N", IF($B44="Não", "Sim", IF(OR( BB44=$AJ44, AND($AJ44="B", OR(BB44="B", BB44="P", BB44="O")), AND($AJ44="P", OR(BB44="P", BB44="O")), AND($AJ44="O", BB44="O")), "Sim", "Não") ) ) -> N | BD44: P | BE44: =IF($AC44="N", "N", IF($B44="Não", "Sim", IF(OR( BD44=$AC44, AND($AC44="B", OR(BD44="B", BD44="P", BD44="O")), AND($AC44="P", OR(BD44="P", BD44="O")), AND($AC44="O", BD44="O")), "Sim", "Não") ) ) -> Sim | BF44: D | BG44: =IF($Y44="N", "N", IF($B44="Não", "Sim", IF(OR( BF44=$Y44, AND($Y44="B", OR(BF44="B", BF44="P", BF44="O")), AND($Y44="P", OR(BF44="P", BF44="O")), AND($Y44="O", BF44="O")), "Sim", "Não") ) ) -> Sim | BH44: N | BI44: =IF($K44="N", "N", IF($B44="Não", "Sim", IF(OR( BH44=$K44, AND($K44="B", OR(BH44="B", BH44="P", BH44="O")), AND($K44="P", OR(BH44="P", BH44="O")), AND($K44="O", BH44="O")), "Sim", "Não") ) ) -> N | BJ44: D | BK44: =IF($Y44="N", "N", IF($B44="Não", "Sim", IF(OR( BJ44=$Y44, AND($Y44="B", OR(BJ44="B", BJ44="P", BJ44="O")), AND($Y44="P", OR(BJ44="P", BJ44="O")), AND($Y44="O", BJ44="O")), "Sim", "Não") ) ) -> Sim | BL44: D | BM44: =IF($Y44="N", "N", IF($B44="Não", "Sim", IF(OR( BL44=$Y44, AND($Y44="B", OR(BL44="B", BL44="P", BL44="O")), AND($Y44="P", OR(BL44="P", BL44="O")), AND($Y44="O", BL44="O")), "Sim", "Não") ) ) -> Sim | BN44: N | BO44: =IF($AJ44="N", "N", IF($B44="Não", "Sim", IF(OR( BN44=$AJ44, AND($AJ44="B", OR(BN44="B", BN44="P", BN44="O")), AND($AJ44="P", OR(BN44="P", BN44="O")), AND($AJ44="O", BN44="O")), "Sim", "Não") ) ) -> N | BP44: N | BQ44: =IF($T44="N", "N", IF($B44="Não", "Sim", IF(OR( BP44=$T44, AND($T44="B", OR(BP44="B", BP44="P", BP44="O")), AND($T44="P", OR(BP44="P", BP44="O")), AND($T44="O", BP44="O")), "Sim", "Não") ) ) -> N | BR44: N | BS44: =IF($I44="N", "N", IF($B44="Não", "Sim", IF(OR( BR44=$I44, AND($I44="B", OR(BR44="B", BR44="P", BR44="O")), AND($I44="P", OR(BR44="P", BR44="O")), AND($I44="O", BR44="O")), "Sim", "Não") ) ) -> N | BT44: N | BU44: =IF($G44="N", "N", IF($B44="Não", "Sim", IF(OR( BT44=$G44, AND($G44="B", OR(BT44="B", BT44="P", BT44="O")), AND($G44="P", OR(BT44="P", BT44="O")), AND($G44="O", BT44="O")), "Sim", "Não") ) ) -> N | BV44: N | BW44: =IF($G44="N", "N", IF($B44="Não", "Sim", IF(OR( BV44=$G44, AND($G44="B", OR(BV44="B", BV44="P", BV44="O")), AND($G44="P", OR(BV44="P", BV44="O")), AND($G44="O", BV44="O")), "Sim", "Não") ) ) -> N | BX44: N | BY44: =IF($P44="N", "N", IF($B44="Não", "Sim", IF(OR( BX44=$P44, AND($P44="B", OR(BX44="B", BX44="P", BX44="O")), AND($P44="P", OR(BX44="P", BX44="O")), AND($P44="O", BX44="O")), "Sim", "Não") ) ) -> N | BZ44: N | CA44: =IF($G44="N", "N", IF($B44="Não", "Sim", IF(OR( BZ44=$G44, AND($G44="B", OR(BZ44="B", BZ44="P", BZ44="O")), AND($G44="P", OR(BZ44="P", BZ44="O")), AND($G44="O", BZ44="O")), "Sim", "Não") ) ) -> N
B45: Não | C45: Testes | D45: Ferramenta de cybersegurança - Burp Suite | E45: N | F45: N | G45: N | H45: N | I45: N | J45: N | K45: N | L45: N | N45: N | O45: N | P45: N | Q45: N | R45: N | S45: N | T45: N | U45: N | W45: N | X45: N | Y45: N | Z45: N | AA45: B | AB45: 1 | AC45: P | AD45: 1 | AF45: N | AG45: N | AH45: N | AI45: N | AJ45: N | AK45: N | AL45: N | AM45: N | AO45: I | AP45: I | AQ45: A | AR45: I | AT45: N | AU45: =IF($P45="N", "N", IF($B45="Não", "Sim", IF(OR( AT45=$P45, AND($P45="B", OR(AT45="B", AT45="P", AT45="O")), AND($P45="P", OR(AT45="P", AT45="O")), AND($P45="O", AT45="O")), "Sim", "Não") ) ) -> N | AV45: N | AW45: =IF($I45="N", "N", IF($B45="Não", "Sim", IF(OR( AV45=$I45, AND($I45="B", OR(AV45="B", AV45="P", AV45="O")), AND($I45="P", OR(AV45="P", AV45="O")), AND($I45="O", AV45="O")), "Sim", "Não") ) ) -> N | AX45: N | AY45: =IF($R45="N", "N", IF($B45="Não", "Sim", IF(OR( AX45=$R45, AND($R45="B", OR(AX45="B", AX45="P", AX45="O")), AND($R45="P", OR(AX45="P", AX45="O")), AND($R45="O", AX45="O")), "Sim", "Não") ) ) -> N | AZ45: N | BA45: =IF($I45="N", "N", IF($B45="Não", "Sim", IF(OR( AZ45=$I45, AND($I45="B", OR(AZ45="B", AZ45="P", AZ45="O")), AND($I45="P", OR(AZ45="P", AZ45="O")), AND($I45="O", AZ45="O")), "Sim", "Não") ) ) -> N | BB45: N | BC45: =IF($AJ45="N", "N", IF($B45="Não", "Sim", IF(OR( BB45=$AJ45, AND($AJ45="B", OR(BB45="B", BB45="P", BB45="O")), AND($AJ45="P", OR(BB45="P", BB45="O")), AND($AJ45="O", BB45="O")), "Sim", "Não") ) ) -> N | BD45: P | BE45: =IF($AC45="N", "N", IF($B45="Não", "Sim", IF(OR( BD45=$AC45, AND($AC45="B", OR(BD45="B", BD45="P", BD45="O")), AND($AC45="P", OR(BD45="P", BD45="O")), AND($AC45="O", BD45="O")), "Sim", "Não") ) ) -> Sim | BF45: D | BG45: =IF($Y45="N", "N", IF($B45="Não", "Sim", IF(OR( BF45=$Y45, AND($Y45="B", OR(BF45="B", BF45="P", BF45="O")), AND($Y45="P", OR(BF45="P", BF45="O")), AND($Y45="O", BF45="O")), "Sim", "Não") ) ) -> N | BH45: N | BI45: =IF($K45="N", "N", IF($B45="Não", "Sim", IF(OR( BH45=$K45, AND($K45="B", OR(BH45="B", BH45="P", BH45="O")), AND($K45="P", OR(BH45="P", BH45="O")), AND($K45="O", BH45="O")), "Sim", "Não") ) ) -> N | BJ45: D | BK45: =IF($Y45="N", "N", IF($B45="Não", "Sim", IF(OR( BJ45=$Y45, AND($Y45="B", OR(BJ45="B", BJ45="P", BJ45="O")), AND($Y45="P", OR(BJ45="P", BJ45="O")), AND($Y45="O", BJ45="O")), "Sim", "Não") ) ) -> N | BL45: D | BM45: =IF($Y45="N", "N", IF($B45="Não", "Sim", IF(OR( BL45=$Y45, AND($Y45="B", OR(BL45="B", BL45="P", BL45="O")), AND($Y45="P", OR(BL45="P", BL45="O")), AND($Y45="O", BL45="O")), "Sim", "Não") ) ) -> N | BN45: N | BO45: =IF($AJ45="N", "N", IF($B45="Não", "Sim", IF(OR( BN45=$AJ45, AND($AJ45="B", OR(BN45="B", BN45="P", BN45="O")), AND($AJ45="P", OR(BN45="P", BN45="O")), AND($AJ45="O", BN45="O")), "Sim", "Não") ) ) -> N | BP45: N | BQ45: =IF($T45="N", "N", IF($B45="Não", "Sim", IF(OR( BP45=$T45, AND($T45="B", OR(BP45="B", BP45="P", BP45="O")), AND($T45="P", OR(BP45="P", BP45="O")), AND($T45="O", BP45="O")), "Sim", "Não") ) ) -> N | BR45: N | BS45: =IF($I45="N", "N", IF($B45="Não", "Sim", IF(OR( BR45=$I45, AND($I45="B", OR(BR45="B", BR45="P", BR45="O")), AND($I45="P", OR(BR45="P", BR45="O")), AND($I45="O", BR45="O")), "Sim", "Não") ) ) -> N | BT45: N | BU45: =IF($G45="N", "N", IF($B45="Não", "Sim", IF(OR( BT45=$G45, AND($G45="B", OR(BT45="B", BT45="P", BT45="O")), AND($G45="P", OR(BT45="P", BT45="O")), AND($G45="O", BT45="O")), "Sim", "Não") ) ) -> N | BV45: N | BW45: =IF($G45="N", "N", IF($B45="Não", "Sim", IF(OR( BV45=$G45, AND($G45="B", OR(BV45="B", BV45="P", BV45="O")), AND($G45="P", OR(BV45="P", BV45="O")), AND($G45="O", BV45="O")), "Sim", "Não") ) ) -> N | BX45: N | BY45: =IF($P45="N", "N", IF($B45="Não", "Sim", IF(OR( BX45=$P45, AND($P45="B", OR(BX45="B", BX45="P", BX45="O")), AND($P45="P", OR(BX45="P", BX45="O")), AND($P45="O", BX45="O")), "Sim", "Não") ) ) -> N | BZ45: N | CA45: =IF($G45="N", "N", IF($B45="Não", "Sim", IF(OR( BZ45=$G45, AND($G45="B", OR(BZ45="B", BZ45="P", BZ45="O")), AND($G45="P", OR(BZ45="P", BZ45="O")), AND($G45="O", BZ45="O")), "Sim", "Não") ) ) -> N
B46: Não | C46: Testes | D46: Framework de escrita de testes - Cucumber | E46: N | F46: N | G46: N | H46: N | I46: N | J46: N | K46: N | L46: N | N46: N | O46: N | P46: N | Q46: N | R46: N | S46: N | T46: N | U46: N | W46: N | X46: N | Y46: N | Z46: N | AA46: B | AB46: 0 | AC46: P | AD46: 0 | AF46: N | AG46: N | AH46: N | AI46: N | AJ46: N | AK46: N | AL46: N | AM46: N | AO46: I | AP46: I | AQ46: A | AR46: I | AT46: N | AU46: =IF($P46="N", "N", IF($B46="Não", "Sim", IF(OR( AT46=$P46, AND($P46="B", OR(AT46="B", AT46="P", AT46="O")), AND($P46="P", OR(AT46="P", AT46="O")), AND($P46="O", AT46="O")), "Sim", "Não") ) ) -> N | AV46: N | AW46: =IF($I46="N", "N", IF($B46="Não", "Sim", IF(OR( AV46=$I46, AND($I46="B", OR(AV46="B", AV46="P", AV46="O")), AND($I46="P", OR(AV46="P", AV46="O")), AND($I46="O", AV46="O")), "Sim", "Não") ) ) -> N | AX46: N | AY46: =IF($R46="N", "N", IF($B46="Não", "Sim", IF(OR( AX46=$R46, AND($R46="B", OR(AX46="B", AX46="P", AX46="O")), AND($R46="P", OR(AX46="P", AX46="O")), AND($R46="O", AX46="O")), "Sim", "Não") ) ) -> N | AZ46: N | BA46: =IF($I46="N", "N", IF($B46="Não", "Sim", IF(OR( AZ46=$I46, AND($I46="B", OR(AZ46="B", AZ46="P", AZ46="O")), AND($I46="P", OR(AZ46="P", AZ46="O")), AND($I46="O", AZ46="O")), "Sim", "Não") ) ) -> N | BB46: N | BC46: =IF($AJ46="N", "N", IF($B46="Não", "Sim", IF(OR( BB46=$AJ46, AND($AJ46="B", OR(BB46="B", BB46="P", BB46="O")), AND($AJ46="P", OR(BB46="P", BB46="O")), AND($AJ46="O", BB46="O")), "Sim", "Não") ) ) -> N | BD46: O | BE46: =IF($AC46="N", "N", IF($B46="Não", "Sim", IF(OR( BD46=$AC46, AND($AC46="B", OR(BD46="B", BD46="P", BD46="O")), AND($AC46="P", OR(BD46="P", BD46="O")), AND($AC46="O", BD46="O")), "Sim", "Não") ) ) -> Sim | BF46: B | BG46: =IF($Y46="N", "N", IF($B46="Não", "Sim", IF(OR( BF46=$Y46, AND($Y46="B", OR(BF46="B", BF46="P", BF46="O")), AND($Y46="P", OR(BF46="P", BF46="O")), AND($Y46="O", BF46="O")), "Sim", "Não") ) ) -> N | BH46: N | BI46: =IF($K46="N", "N", IF($B46="Não", "Sim", IF(OR( BH46=$K46, AND($K46="B", OR(BH46="B", BH46="P", BH46="O")), AND($K46="P", OR(BH46="P", BH46="O")), AND($K46="O", BH46="O")), "Sim", "Não") ) ) -> N | BJ46: D | BK46: =IF($Y46="N", "N", IF($B46="Não", "Sim", IF(OR( BJ46=$Y46, AND($Y46="B", OR(BJ46="B", BJ46="P", BJ46="O")), AND($Y46="P", OR(BJ46="P", BJ46="O")), AND($Y46="O", BJ46="O")), "Sim", "Não") ) ) -> N | BL46: P | BM46: =IF($Y46="N", "N", IF($B46="Não", "Sim", IF(OR( BL46=$Y46, AND($Y46="B", OR(BL46="B", BL46="P", BL46="O")), AND($Y46="P", OR(BL46="P", BL46="O")), AND($Y46="O", BL46="O")), "Sim", "Não") ) ) -> N | BN46: N | BO46: =IF($AJ46="N", "N", IF($B46="Não", "Sim", IF(OR( BN46=$AJ46, AND($AJ46="B", OR(BN46="B", BN46="P", BN46="O")), AND($AJ46="P", OR(BN46="P", BN46="O")), AND($AJ46="O", BN46="O")), "Sim", "Não") ) ) -> N | BP46: N | BQ46: =IF($T46="N", "N", IF($B46="Não", "Sim", IF(OR( BP46=$T46, AND($T46="B", OR(BP46="B", BP46="P", BP46="O")), AND($T46="P", OR(BP46="P", BP46="O")), AND($T46="O", BP46="O")), "Sim", "Não") ) ) -> N | BR46: N | BS46: =IF($I46="N", "N", IF($B46="Não", "Sim", IF(OR( BR46=$I46, AND($I46="B", OR(BR46="B", BR46="P", BR46="O")), AND($I46="P", OR(BR46="P", BR46="O")), AND($I46="O", BR46="O")), "Sim", "Não") ) ) -> N | BT46: N | BU46: =IF($G46="N", "N", IF($B46="Não", "Sim", IF(OR( BT46=$G46, AND($G46="B", OR(BT46="B", BT46="P", BT46="O")), AND($G46="P", OR(BT46="P", BT46="O")), AND($G46="O", BT46="O")), "Sim", "Não") ) ) -> N | BV46: N | BW46: =IF($G46="N", "N", IF($B46="Não", "Sim", IF(OR( BV46=$G46, AND($G46="B", OR(BV46="B", BV46="P", BV46="O")), AND($G46="P", OR(BV46="P", BV46="O")), AND($G46="O", BV46="O")), "Sim", "Não") ) ) -> N | BX46: N | BY46: =IF($P46="N", "N", IF($B46="Não", "Sim", IF(OR( BX46=$P46, AND($P46="B", OR(BX46="B", BX46="P", BX46="O")), AND($P46="P", OR(BX46="P", BX46="O")), AND($P46="O", BX46="O")), "Sim", "Não") ) ) -> N | BZ46: N | CA46: =IF($G46="N", "N", IF($B46="Não", "Sim", IF(OR( BZ46=$G46, AND($G46="B", OR(BZ46="B", BZ46="P", BZ46="O")), AND($G46="P", OR(BZ46="P", BZ46="O")), AND($G46="O", BZ46="O")), "Sim", "Não") ) ) -> N
B47: Não | C47: Testes | D47: Escritas de testes em Gherkin | E47: N | F47: N | G47: N | H47: N | I47: N | J47: N | K47: N | L47: N | N47: N | O47: N | P47: N | Q47: N | R47: N | S47: N | T47: N | U47: N | W47: B | X47: 0 | Y47: B | Z47: 0 | AA47: P | AB47: 0 | AC47: O | AD47: 0 | AF47: N | AG47: N | AH47: N | AI47: N | AJ47: N | AK47: N | AL47: N | AM47: N | AO47: I | AP47: I | AQ47: A | AR47: I | AT47: N | AU47: =IF($P47="N", "N", IF($B47="Não", "Sim", IF(OR( AT47=$P47, AND($P47="B", OR(AT47="B", AT47="P", AT47="O")), AND($P47="P", OR(AT47="P", AT47="O")), AND($P47="O", AT47="O")), "Sim", "Não") ) ) -> N | AV47: N | AW47: =IF($I47="N", "N", IF($B47="Não", "Sim", IF(OR( AV47=$I47, AND($I47="B", OR(AV47="B", AV47="P", AV47="O")), AND($I47="P", OR(AV47="P", AV47="O")), AND($I47="O", AV47="O")), "Sim", "Não") ) ) -> N | AX47: N | AY47: =IF($R47="N", "N", IF($B47="Não", "Sim", IF(OR( AX47=$R47, AND($R47="B", OR(AX47="B", AX47="P", AX47="O")), AND($R47="P", OR(AX47="P", AX47="O")), AND($R47="O", AX47="O")), "Sim", "Não") ) ) -> N | AZ47: N | BA47: =IF($I47="N", "N", IF($B47="Não", "Sim", IF(OR( AZ47=$I47, AND($I47="B", OR(AZ47="B", AZ47="P", AZ47="O")), AND($I47="P", OR(AZ47="P", AZ47="O")), AND($I47="O", AZ47="O")), "Sim", "Não") ) ) -> N | BB47: N | BC47: =IF($AJ47="N", "N", IF($B47="Não", "Sim", IF(OR( BB47=$AJ47, AND($AJ47="B", OR(BB47="B", BB47="P", BB47="O")), AND($AJ47="P", OR(BB47="P", BB47="O")), AND($AJ47="O", BB47="O")), "Sim", "Não") ) ) -> N | BD47: O | BE47: =IF($AC47="N", "N", IF($B47="Não", "Sim", IF(OR( BD47=$AC47, AND($AC47="B", OR(BD47="B", BD47="P", BD47="O")), AND($AC47="P", OR(BD47="P", BD47="O")), AND($AC47="O", BD47="O")), "Sim", "Não") ) ) -> Sim | BF47: D | BG47: =IF($Y47="N", "N", IF($B47="Não", "Sim", IF(OR( BF47=$Y47, AND($Y47="B", OR(BF47="B", BF47="P", BF47="O")), AND($Y47="P", OR(BF47="P", BF47="O")), AND($Y47="O", BF47="O")), "Sim", "Não") ) ) -> Sim | BH47: N | BI47: =IF($K47="N", "N", IF($B47="Não", "Sim", IF(OR( BH47=$K47, AND($K47="B", OR(BH47="B", BH47="P", BH47="O")), AND($K47="P", OR(BH47="P", BH47="O")), AND($K47="O", BH47="O")), "Sim", "Não") ) ) -> N | BJ47: D | BK47: =IF($Y47="N", "N", IF($B47="Não", "Sim", IF(OR( BJ47=$Y47, AND($Y47="B", OR(BJ47="B", BJ47="P", BJ47="O")), AND($Y47="P", OR(BJ47="P", BJ47="O")), AND($Y47="O", BJ47="O")), "Sim", "Não") ) ) -> Sim | BL47: D | BM47: =IF($Y47="N", "N", IF($B47="Não", "Sim", IF(OR( BL47=$Y47, AND($Y47="B", OR(BL47="B", BL47="P", BL47="O")), AND($Y47="P", OR(BL47="P", BL47="O")), AND($Y47="O", BL47="O")), "Sim", "Não") ) ) -> Sim | BN47: N | BO47: =IF($AJ47="N", "N", IF($B47="Não", "Sim", IF(OR( BN47=$AJ47, AND($AJ47="B", OR(BN47="B", BN47="P", BN47="O")), AND($AJ47="P", OR(BN47="P", BN47="O")), AND($AJ47="O", BN47="O")), "Sim", "Não") ) ) -> N | BP47: N | BQ47: =IF($T47="N", "N", IF($B47="Não", "Sim", IF(OR( BP47=$T47, AND($T47="B", OR(BP47="B", BP47="P", BP47="O")), AND($T47="P", OR(BP47="P", BP47="O")), AND($T47="O", BP47="O")), "Sim", "Não") ) ) -> N | BR47: N | BS47: =IF($I47="N", "N", IF($B47="Não", "Sim", IF(OR( BR47=$I47, AND($I47="B", OR(BR47="B", BR47="P", BR47="O")), AND($I47="P", OR(BR47="P", BR47="O")), AND($I47="O", BR47="O")), "Sim", "Não") ) ) -> N | BT47: N | BU47: =IF($G47="N", "N", IF($B47="Não", "Sim", IF(OR( BT47=$G47, AND($G47="B", OR(BT47="B", BT47="P", BT47="O")), AND($G47="P", OR(BT47="P", BT47="O")), AND($G47="O", BT47="O")), "Sim", "Não") ) ) -> N | BV47: N | BW47: =IF($G47="N", "N", IF($B47="Não", "Sim", IF(OR( BV47=$G47, AND($G47="B", OR(BV47="B", BV47="P", BV47="O")), AND($G47="P", OR(BV47="P", BV47="O")), AND($G47="O", BV47="O")), "Sim", "Não") ) ) -> N | BX47: N | BY47: =IF($P47="N", "N", IF($B47="Não", "Sim", IF(OR( BX47=$P47, AND($P47="B", OR(BX47="B", BX47="P", BX47="O")), AND($P47="P", OR(BX47="P", BX47="O")), AND($P47="O", BX47="O")), "Sim", "Não") ) ) -> N | BZ47: N | CA47: =IF($G47="N", "N", IF($B47="Não", "Sim", IF(OR( BZ47=$G47, AND($G47="B", OR(BZ47="B", BZ47="P", BZ47="O")), AND($G47="P", OR(BZ47="P", BZ47="O")), AND($G47="O", BZ47="O")), "Sim", "Não") ) ) -> N
B48: Não | C48: Testes | D48: JS - JavaScript ( Automações ) | E48: N | F48: N | G48: N | H48: N | I48: N | J48: N | K48: N | L48: N | N48: N | O48: N | P48: N | Q48: N | R48: N | S48: N | T48: N | U48: N | W48: B | X48: 0 | Y48: B | Z48: 0 | AA48: P | AB48: 0 | AC48: P | AD48: 0 | AF48: N | AG48: N | AH48: N | AI48: N | AJ48: N | AK48: N | AL48: N | AM48: N | AO48: I | AP48: I | AQ48: A | AR48: I | AT48: N | AU48: =IF($P48="N", "N", IF($B48="Não", "Sim", IF(OR( AT48=$P48, AND($P48="B", OR(AT48="B", AT48="P", AT48="O")), AND($P48="P", OR(AT48="P", AT48="O")), AND($P48="O", AT48="O")), "Sim", "Não") ) ) -> N | AV48: N | AW48: =IF($I48="N", "N", IF($B48="Não", "Sim", IF(OR( AV48=$I48, AND($I48="B", OR(AV48="B", AV48="P", AV48="O")), AND($I48="P", OR(AV48="P", AV48="O")), AND($I48="O", AV48="O")), "Sim", "Não") ) ) -> N | AX48: N | AY48: =IF($R48="N", "N", IF($B48="Não", "Sim", IF(OR( AX48=$R48, AND($R48="B", OR(AX48="B", AX48="P", AX48="O")), AND($R48="P", OR(AX48="P", AX48="O")), AND($R48="O", AX48="O")), "Sim", "Não") ) ) -> N | AZ48: N | BA48: =IF($I48="N", "N", IF($B48="Não", "Sim", IF(OR( AZ48=$I48, AND($I48="B", OR(AZ48="B", AZ48="P", AZ48="O")), AND($I48="P", OR(AZ48="P", AZ48="O")), AND($I48="O", AZ48="O")), "Sim", "Não") ) ) -> N | BB48: N | BC48: =IF($AJ48="N", "N", IF($B48="Não", "Sim", IF(OR( BB48=$AJ48, AND($AJ48="B", OR(BB48="B", BB48="P", BB48="O")), AND($AJ48="P", OR(BB48="P", BB48="O")), AND($AJ48="O", BB48="O")), "Sim", "Não") ) ) -> N | BD48: O | BE48: =IF($AC48="N", "N", IF($B48="Não", "Sim", IF(OR( BD48=$AC48, AND($AC48="B", OR(BD48="B", BD48="P", BD48="O")), AND($AC48="P", OR(BD48="P", BD48="O")), AND($AC48="O", BD48="O")), "Sim", "Não") ) ) -> Sim | BF48: B | BG48: =IF($Y48="N", "N", IF($B48="Não", "Sim", IF(OR( BF48=$Y48, AND($Y48="B", OR(BF48="B", BF48="P", BF48="O")), AND($Y48="P", OR(BF48="P", BF48="O")), AND($Y48="O", BF48="O")), "Sim", "Não") ) ) -> Sim | BH48: N | BI48: =IF($K48="N", "N", IF($B48="Não", "Sim", IF(OR( BH48=$K48, AND($K48="B", OR(BH48="B", BH48="P", BH48="O")), AND($K48="P", OR(BH48="P", BH48="O")), AND($K48="O", BH48="O")), "Sim", "Não") ) ) -> N | BJ48: B | BK48: =IF($Y48="N", "N", IF($B48="Não", "Sim", IF(OR( BJ48=$Y48, AND($Y48="B", OR(BJ48="B", BJ48="P", BJ48="O")), AND($Y48="P", OR(BJ48="P", BJ48="O")), AND($Y48="O", BJ48="O")), "Sim", "Não") ) ) -> Sim | BL48: P | BM48: =IF($Y48="N", "N", IF($B48="Não", "Sim", IF(OR( BL48=$Y48, AND($Y48="B", OR(BL48="B", BL48="P", BL48="O")), AND($Y48="P", OR(BL48="P", BL48="O")), AND($Y48="O", BL48="O")), "Sim", "Não") ) ) -> Sim | BN48: N | BO48: =IF($AJ48="N", "N", IF($B48="Não", "Sim", IF(OR( BN48=$AJ48, AND($AJ48="B", OR(BN48="B", BN48="P", BN48="O")), AND($AJ48="P", OR(BN48="P", BN48="O")), AND($AJ48="O", BN48="O")), "Sim", "Não") ) ) -> N | BP48: N | BQ48: =IF($T48="N", "N", IF($B48="Não", "Sim", IF(OR( BP48=$T48, AND($T48="B", OR(BP48="B", BP48="P", BP48="O")), AND($T48="P", OR(BP48="P", BP48="O")), AND($T48="O", BP48="O")), "Sim", "Não") ) ) -> N | BR48: N | BS48: =IF($I48="N", "N", IF($B48="Não", "Sim", IF(OR( BR48=$I48, AND($I48="B", OR(BR48="B", BR48="P", BR48="O")), AND($I48="P", OR(BR48="P", BR48="O")), AND($I48="O", BR48="O")), "Sim", "Não") ) ) -> N | BT48: N | BU48: =IF($G48="N", "N", IF($B48="Não", "Sim", IF(OR( BT48=$G48, AND($G48="B", OR(BT48="B", BT48="P", BT48="O")), AND($G48="P", OR(BT48="P", BT48="O")), AND($G48="O", BT48="O")), "Sim", "Não") ) ) -> N | BV48: N | BW48: =IF($G48="N", "N", IF($B48="Não", "Sim", IF(OR( BV48=$G48, AND($G48="B", OR(BV48="B", BV48="P", BV48="O")), AND($G48="P", OR(BV48="P", BV48="O")), AND($G48="O", BV48="O")), "Sim", "Não") ) ) -> N | BX48: N | BY48: =IF($P48="N", "N", IF($B48="Não", "Sim", IF(OR( BX48=$P48, AND($P48="B", OR(BX48="B", BX48="P", BX48="O")), AND($P48="P", OR(BX48="P", BX48="O")), AND($P48="O", BX48="O")), "Sim", "Não") ) ) -> N | BZ48: N | CA48: =IF($G48="N", "N", IF($B48="Não", "Sim", IF(OR( BZ48=$G48, AND($G48="B", OR(BZ48="B", BZ48="P", BZ48="O")), AND($G48="P", OR(BZ48="P", BZ48="O")), AND($G48="O", BZ48="O")), "Sim", "Não") ) ) -> N
B49: Não | C49: Testes | D49: Pipelines - Releases | E49: N | F49: N | G49: N | H49: N | I49: N | J49: N | K49: N | L49: N | N49: N | O49: N | P49: N | Q49: N | R49: N | S49: N | T49: N | U49: N | W49: B | X49: 0 | Y49: B | Z49: 0 | AA49: P | AB49: 0 | AC49: P | AD49: 0 | AF49: N | AG49: N | AH49: N | AI49: N | AJ49: N | AK49: N | AL49: N | AM49: N | AO49: I | AP49: I | AQ49: A | AR49: I | AT49: N | AU49: =IF($P49="N", "N", IF($B49="Não", "Sim", IF(OR( AT49=$P49, AND($P49="B", OR(AT49="B", AT49="P", AT49="O")), AND($P49="P", OR(AT49="P", AT49="O")), AND($P49="O", AT49="O")), "Sim", "Não") ) ) -> N | AV49: N | AW49: =IF($I49="N", "N", IF($B49="Não", "Sim", IF(OR( AV49=$I49, AND($I49="B", OR(AV49="B", AV49="P", AV49="O")), AND($I49="P", OR(AV49="P", AV49="O")), AND($I49="O", AV49="O")), "Sim", "Não") ) ) -> N | AX49: N | AY49: =IF($R49="N", "N", IF($B49="Não", "Sim", IF(OR( AX49=$R49, AND($R49="B", OR(AX49="B", AX49="P", AX49="O")), AND($R49="P", OR(AX49="P", AX49="O")), AND($R49="O", AX49="O")), "Sim", "Não") ) ) -> N | AZ49: N | BA49: =IF($I49="N", "N", IF($B49="Não", "Sim", IF(OR( AZ49=$I49, AND($I49="B", OR(AZ49="B", AZ49="P", AZ49="O")), AND($I49="P", OR(AZ49="P", AZ49="O")), AND($I49="O", AZ49="O")), "Sim", "Não") ) ) -> N | BB49: N | BC49: =IF($AJ49="N", "N", IF($B49="Não", "Sim", IF(OR( BB49=$AJ49, AND($AJ49="B", OR(BB49="B", BB49="P", BB49="O")), AND($AJ49="P", OR(BB49="P", BB49="O")), AND($AJ49="O", BB49="O")), "Sim", "Não") ) ) -> N | BD49: O | BE49: =IF($AC49="N", "N", IF($B49="Não", "Sim", IF(OR( BD49=$AC49, AND($AC49="B", OR(BD49="B", BD49="P", BD49="O")), AND($AC49="P", OR(BD49="P", BD49="O")), AND($AC49="O", BD49="O")), "Sim", "Não") ) ) -> Sim | BF49: B | BG49: =IF($Y49="N", "N", IF($B49="Não", "Sim", IF(OR( BF49=$Y49, AND($Y49="B", OR(BF49="B", BF49="P", BF49="O")), AND($Y49="P", OR(BF49="P", BF49="O")), AND($Y49="O", BF49="O")), "Sim", "Não") ) ) -> Sim | BH49: N | BI49: =IF($K49="N", "N", IF($B49="Não", "Sim", IF(OR( BH49=$K49, AND($K49="B", OR(BH49="B", BH49="P", BH49="O")), AND($K49="P", OR(BH49="P", BH49="O")), AND($K49="O", BH49="O")), "Sim", "Não") ) ) -> N | BJ49: B | BK49: =IF($Y49="N", "N", IF($B49="Não", "Sim", IF(OR( BJ49=$Y49, AND($Y49="B", OR(BJ49="B", BJ49="P", BJ49="O")), AND($Y49="P", OR(BJ49="P", BJ49="O")), AND($Y49="O", BJ49="O")), "Sim", "Não") ) ) -> Sim | BL49: B | BM49: =IF($Y49="N", "N", IF($B49="Não", "Sim", IF(OR( BL49=$Y49, AND($Y49="B", OR(BL49="B", BL49="P", BL49="O")), AND($Y49="P", OR(BL49="P", BL49="O")), AND($Y49="O", BL49="O")), "Sim", "Não") ) ) -> Sim | BN49: N | BO49: =IF($AJ49="N", "N", IF($B49="Não", "Sim", IF(OR( BN49=$AJ49, AND($AJ49="B", OR(BN49="B", BN49="P", BN49="O")), AND($AJ49="P", OR(BN49="P", BN49="O")), AND($AJ49="O", BN49="O")), "Sim", "Não") ) ) -> N | BP49: N | BQ49: =IF($T49="N", "N", IF($B49="Não", "Sim", IF(OR( BP49=$T49, AND($T49="B", OR(BP49="B", BP49="P", BP49="O")), AND($T49="P", OR(BP49="P", BP49="O")), AND($T49="O", BP49="O")), "Sim", "Não") ) ) -> N | BR49: N | BS49: =IF($I49="N", "N", IF($B49="Não", "Sim", IF(OR( BR49=$I49, AND($I49="B", OR(BR49="B", BR49="P", BR49="O")), AND($I49="P", OR(BR49="P", BR49="O")), AND($I49="O", BR49="O")), "Sim", "Não") ) ) -> N | BT49: N | BU49: =IF($G49="N", "N", IF($B49="Não", "Sim", IF(OR( BT49=$G49, AND($G49="B", OR(BT49="B", BT49="P", BT49="O")), AND($G49="P", OR(BT49="P", BT49="O")), AND($G49="O", BT49="O")), "Sim", "Não") ) ) -> N | BV49: N | BW49: =IF($G49="N", "N", IF($B49="Não", "Sim", IF(OR( BV49=$G49, AND($G49="B", OR(BV49="B", BV49="P", BV49="O")), AND($G49="P", OR(BV49="P", BV49="O")), AND($G49="O", BV49="O")), "Sim", "Não") ) ) -> N | BX49: N | BY49: =IF($P49="N", "N", IF($B49="Não", "Sim", IF(OR( BX49=$P49, AND($P49="B", OR(BX49="B", BX49="P", BX49="O")), AND($P49="P", OR(BX49="P", BX49="O")), AND($P49="O", BX49="O")), "Sim", "Não") ) ) -> N | BZ49: N | CA49: =IF($G49="N", "N", IF($B49="Não", "Sim", IF(OR( BZ49=$G49, AND($G49="B", OR(BZ49="B", BZ49="P", BZ49="O")), AND($G49="P", OR(BZ49="P", BZ49="O")), AND($G49="O", BZ49="O")), "Sim", "Não") ) ) -> N
B50: Não | C50: Testes | D50: Testes de API - FrontEnd | E50: N | F50: N | G50: N | H50: N | I50: N | J50: N | K50: N | L50: N | N50: N | O50: N | P50: N | Q50: N | R50: N | S50: N | T50: N | U50: N | W50: B | X50: 0 | Y50: B | Z50: 1 | AA50: P | AB50: 1 | AC50: O | AD50: 1 | AF50: N | AG50: N | AH50: N | AI50: N | AJ50: N | AK50: N | AL50: N | AM50: N | AO50: I | AP50: I | AQ50: A | AR50: I | AT50: N | AU50: =IF($P50="N", "N", IF($B50="Não", "Sim", IF(OR( AT50=$P50, AND($P50="B", OR(AT50="B", AT50="P", AT50="O")), AND($P50="P", OR(AT50="P", AT50="O")), AND($P50="O", AT50="O")), "Sim", "Não") ) ) -> N | AV50: N | AW50: =IF($I50="N", "N", IF($B50="Não", "Sim", IF(OR( AV50=$I50, AND($I50="B", OR(AV50="B", AV50="P", AV50="O")), AND($I50="P", OR(AV50="P", AV50="O")), AND($I50="O", AV50="O")), "Sim", "Não") ) ) -> N | AX50: N | AY50: =IF($R50="N", "N", IF($B50="Não", "Sim", IF(OR( AX50=$R50, AND($R50="B", OR(AX50="B", AX50="P", AX50="O")), AND($R50="P", OR(AX50="P", AX50="O")), AND($R50="O", AX50="O")), "Sim", "Não") ) ) -> N | AZ50: N | BA50: =IF($I50="N", "N", IF($B50="Não", "Sim", IF(OR( AZ50=$I50, AND($I50="B", OR(AZ50="B", AZ50="P", AZ50="O")), AND($I50="P", OR(AZ50="P", AZ50="O")), AND($I50="O", AZ50="O")), "Sim", "Não") ) ) -> N | BB50: N | BC50: =IF($AJ50="N", "N", IF($B50="Não", "Sim", IF(OR( BB50=$AJ50, AND($AJ50="B", OR(BB50="B", BB50="P", BB50="O")), AND($AJ50="P", OR(BB50="P", BB50="O")), AND($AJ50="O", BB50="O")), "Sim", "Não") ) ) -> N | BD50: O | BE50: =IF($AC50="N", "N", IF($B50="Não", "Sim", IF(OR( BD50=$AC50, AND($AC50="B", OR(BD50="B", BD50="P", BD50="O")), AND($AC50="P", OR(BD50="P", BD50="O")), AND($AC50="O", BD50="O")), "Sim", "Não") ) ) -> Sim | BF50: B | BG50: =IF($Y50="N", "N", IF($B50="Não", "Sim", IF(OR( BF50=$Y50, AND($Y50="B", OR(BF50="B", BF50="P", BF50="O")), AND($Y50="P", OR(BF50="P", BF50="O")), AND($Y50="O", BF50="O")), "Sim", "Não") ) ) -> Sim | BH50: N | BI50: =IF($K50="N", "N", IF($B50="Não", "Sim", IF(OR( BH50=$K50, AND($K50="B", OR(BH50="B", BH50="P", BH50="O")), AND($K50="P", OR(BH50="P", BH50="O")), AND($K50="O", BH50="O")), "Sim", "Não") ) ) -> N | BJ50: B | BK50: =IF($Y50="N", "N", IF($B50="Não", "Sim", IF(OR( BJ50=$Y50, AND($Y50="B", OR(BJ50="B", BJ50="P", BJ50="O")), AND($Y50="P", OR(BJ50="P", BJ50="O")), AND($Y50="O", BJ50="O")), "Sim", "Não") ) ) -> Sim | BL50: B | BM50: =IF($Y50="N", "N", IF($B50="Não", "Sim", IF(OR( BL50=$Y50, AND($Y50="B", OR(BL50="B", BL50="P", BL50="O")), AND($Y50="P", OR(BL50="P", BL50="O")), AND($Y50="O", BL50="O")), "Sim", "Não") ) ) -> Sim | BN50: N | BO50: =IF($AJ50="N", "N", IF($B50="Não", "Sim", IF(OR( BN50=$AJ50, AND($AJ50="B", OR(BN50="B", BN50="P", BN50="O")), AND($AJ50="P", OR(BN50="P", BN50="O")), AND($AJ50="O", BN50="O")), "Sim", "Não") ) ) -> N | BP50: N | BQ50: =IF($T50="N", "N", IF($B50="Não", "Sim", IF(OR( BP50=$T50, AND($T50="B", OR(BP50="B", BP50="P", BP50="O")), AND($T50="P", OR(BP50="P", BP50="O")), AND($T50="O", BP50="O")), "Sim", "Não") ) ) -> N | BR50: N | BS50: =IF($I50="N", "N", IF($B50="Não", "Sim", IF(OR( BR50=$I50, AND($I50="B", OR(BR50="B", BR50="P", BR50="O")), AND($I50="P", OR(BR50="P", BR50="O")), AND($I50="O", BR50="O")), "Sim", "Não") ) ) -> N | BT50: N | BU50: =IF($G50="N", "N", IF($B50="Não", "Sim", IF(OR( BT50=$G50, AND($G50="B", OR(BT50="B", BT50="P", BT50="O")), AND($G50="P", OR(BT50="P", BT50="O")), AND($G50="O", BT50="O")), "Sim", "Não") ) ) -> N | BV50: N | BW50: =IF($G50="N", "N", IF($B50="Não", "Sim", IF(OR( BV50=$G50, AND($G50="B", OR(BV50="B", BV50="P", BV50="O")), AND($G50="P", OR(BV50="P", BV50="O")), AND($G50="O", BV50="O")), "Sim", "Não") ) ) -> N | BX50: N | BY50: =IF($P50="N", "N", IF($B50="Não", "Sim", IF(OR( BX50=$P50, AND($P50="B", OR(BX50="B", BX50="P", BX50="O")), AND($P50="P", OR(BX50="P", BX50="O")), AND($P50="O", BX50="O")), "Sim", "Não") ) ) -> N | BZ50: N | CA50: =IF($G50="N", "N", IF($B50="Não", "Sim", IF(OR( BZ50=$G50, AND($G50="B", OR(BZ50="B", BZ50="P", BZ50="O")), AND($G50="P", OR(BZ50="P", BZ50="O")), AND($G50="O", BZ50="O")), "Sim", "Não") ) ) -> N
B51: Não | C51: Testes | D51: Test Cases - Estratégias e Planos de testes | E51: N | F51: N | G51: N | H51: N | I51: N | J51: N | K51: N | L51: N | N51: N | O51: N | P51: N | Q51: N | R51: N | S51: N | T51: N | U51: N | W51: B | X51: 0 | Y51: B | Z51: 1 | AA51: P | AB51: 1 | AC51: O | AD51: 1 | AF51: N | AG51: N | AH51: N | AI51: N | AJ51: N | AK51: N | AL51: N | AM51: N | AO51: I | AP51: I | AQ51: A | AR51: I | AT51: N | AU51: =IF($P51="N", "N", IF($B51="Não", "Sim", IF(OR( AT51=$P51, AND($P51="B", OR(AT51="B", AT51="P", AT51="O")), AND($P51="P", OR(AT51="P", AT51="O")), AND($P51="O", AT51="O")), "Sim", "Não") ) ) -> N | AV51: N | AW51: =IF($I51="N", "N", IF($B51="Não", "Sim", IF(OR( AV51=$I51, AND($I51="B", OR(AV51="B", AV51="P", AV51="O")), AND($I51="P", OR(AV51="P", AV51="O")), AND($I51="O", AV51="O")), "Sim", "Não") ) ) -> N | AX51: N | AY51: =IF($R51="N", "N", IF($B51="Não", "Sim", IF(OR( AX51=$R51, AND($R51="B", OR(AX51="B", AX51="P", AX51="O")), AND($R51="P", OR(AX51="P", AX51="O")), AND($R51="O", AX51="O")), "Sim", "Não") ) ) -> N | AZ51: N | BA51: =IF($I51="N", "N", IF($B51="Não", "Sim", IF(OR( AZ51=$I51, AND($I51="B", OR(AZ51="B", AZ51="P", AZ51="O")), AND($I51="P", OR(AZ51="P", AZ51="O")), AND($I51="O", AZ51="O")), "Sim", "Não") ) ) -> N | BB51: N | BC51: =IF($AJ51="N", "N", IF($B51="Não", "Sim", IF(OR( BB51=$AJ51, AND($AJ51="B", OR(BB51="B", BB51="P", BB51="O")), AND($AJ51="P", OR(BB51="P", BB51="O")), AND($AJ51="O", BB51="O")), "Sim", "Não") ) ) -> N | BD51: O | BE51: =IF($AC51="N", "N", IF($B51="Não", "Sim", IF(OR( BD51=$AC51, AND($AC51="B", OR(BD51="B", BD51="P", BD51="O")), AND($AC51="P", OR(BD51="P", BD51="O")), AND($AC51="O", BD51="O")), "Sim", "Não") ) ) -> Sim | BF51: B | BG51: =IF($Y51="N", "N", IF($B51="Não", "Sim", IF(OR( BF51=$Y51, AND($Y51="B", OR(BF51="B", BF51="P", BF51="O")), AND($Y51="P", OR(BF51="P", BF51="O")), AND($Y51="O", BF51="O")), "Sim", "Não") ) ) -> Sim | BH51: N | BI51: =IF($K51="N", "N", IF($B51="Não", "Sim", IF(OR( BH51=$K51, AND($K51="B", OR(BH51="B", BH51="P", BH51="O")), AND($K51="P", OR(BH51="P", BH51="O")), AND($K51="O", BH51="O")), "Sim", "Não") ) ) -> N | BJ51: B | BK51: =IF($Y51="N", "N", IF($B51="Não", "Sim", IF(OR( BJ51=$Y51, AND($Y51="B", OR(BJ51="B", BJ51="P", BJ51="O")), AND($Y51="P", OR(BJ51="P", BJ51="O")), AND($Y51="O", BJ51="O")), "Sim", "Não") ) ) -> Sim | BL51: B | BM51: =IF($Y51="N", "N", IF($B51="Não", "Sim", IF(OR( BL51=$Y51, AND($Y51="B", OR(BL51="B", BL51="P", BL51="O")), AND($Y51="P", OR(BL51="P", BL51="O")), AND($Y51="O", BL51="O")), "Sim", "Não") ) ) -> Sim | BN51: N | BO51: =IF($AJ51="N", "N", IF($B51="Não", "Sim", IF(OR( BN51=$AJ51, AND($AJ51="B", OR(BN51="B", BN51="P", BN51="O")), AND($AJ51="P", OR(BN51="P", BN51="O")), AND($AJ51="O", BN51="O")), "Sim", "Não") ) ) -> N | BP51: N | BQ51: =IF($T51="N", "N", IF($B51="Não", "Sim", IF(OR( BP51=$T51, AND($T51="B", OR(BP51="B", BP51="P", BP51="O")), AND($T51="P", OR(BP51="P", BP51="O")), AND($T51="O", BP51="O")), "Sim", "Não") ) ) -> N | BR51: N | BS51: =IF($I51="N", "N", IF($B51="Não", "Sim", IF(OR( BR51=$I51, AND($I51="B", OR(BR51="B", BR51="P", BR51="O")), AND($I51="P", OR(BR51="P", BR51="O")), AND($I51="O", BR51="O")), "Sim", "Não") ) ) -> N | BT51: N | BU51: =IF($G51="N", "N", IF($B51="Não", "Sim", IF(OR( BT51=$G51, AND($G51="B", OR(BT51="B", BT51="P", BT51="O")), AND($G51="P", OR(BT51="P", BT51="O")), AND($G51="O", BT51="O")), "Sim", "Não") ) ) -> N | BV51: N | BW51: =IF($G51="N", "N", IF($B51="Não", "Sim", IF(OR( BV51=$G51, AND($G51="B", OR(BV51="B", BV51="P", BV51="O")), AND($G51="P", OR(BV51="P", BV51="O")), AND($G51="O", BV51="O")), "Sim", "Não") ) ) -> N | BX51: N | BY51: =IF($P51="N", "N", IF($B51="Não", "Sim", IF(OR( BX51=$P51, AND($P51="B", OR(BX51="B", BX51="P", BX51="O")), AND($P51="P", OR(BX51="P", BX51="O")), AND($P51="O", BX51="O")), "Sim", "Não") ) ) -> N | BZ51: N | CA51: =IF($G51="N", "N", IF($B51="Não", "Sim", IF(OR( BZ51=$G51, AND($G51="B", OR(BZ51="B", BZ51="P", BZ51="O")), AND($G51="P", OR(BZ51="P", BZ51="O")), AND($G51="O", BZ51="O")), "Sim", "Não") ) ) -> N
B52: Não | C52: Testes | D52: KPI - Indicadores de Qualidade | E52: N | F52: N | G52: N | H52: N | I52: N | J52: N | K52: N | L52: N | N52: N | O52: N | P52: N | Q52: N | R52: N | S52: N | T52: N | U52: N | W52: B | X52: 0 | Y52: B | Z52: 0 | AA52: B | AB52: 0 | AC52: O | AD52: 0 | AF52: N | AG52: N | AH52: N | AI52: N | AJ52: N | AK52: N | AL52: N | AM52: N | AO52: I | AP52: I | AQ52: A | AR52: I | AT52: N | AU52: =IF($P52="N", "N", IF($B52="Não", "Sim", IF(OR( AT52=$P52, AND($P52="B", OR(AT52="B", AT52="P", AT52="O")), AND($P52="P", OR(AT52="P", AT52="O")), AND($P52="O", AT52="O")), "Sim", "Não") ) ) -> N | AV52: N | AW52: =IF($I52="N", "N", IF($B52="Não", "Sim", IF(OR( AV52=$I52, AND($I52="B", OR(AV52="B", AV52="P", AV52="O")), AND($I52="P", OR(AV52="P", AV52="O")), AND($I52="O", AV52="O")), "Sim", "Não") ) ) -> N | AX52: N | AY52: =IF($R52="N", "N", IF($B52="Não", "Sim", IF(OR( AX52=$R52, AND($R52="B", OR(AX52="B", AX52="P", AX52="O")), AND($R52="P", OR(AX52="P", AX52="O")), AND($R52="O", AX52="O")), "Sim", "Não") ) ) -> N | AZ52: N | BA52: =IF($I52="N", "N", IF($B52="Não", "Sim", IF(OR( AZ52=$I52, AND($I52="B", OR(AZ52="B", AZ52="P", AZ52="O")), AND($I52="P", OR(AZ52="P", AZ52="O")), AND($I52="O", AZ52="O")), "Sim", "Não") ) ) -> N | BB52: N | BC52: =IF($AJ52="N", "N", IF($B52="Não", "Sim", IF(OR( BB52=$AJ52, AND($AJ52="B", OR(BB52="B", BB52="P", BB52="O")), AND($AJ52="P", OR(BB52="P", BB52="O")), AND($AJ52="O", BB52="O")), "Sim", "Não") ) ) -> N | BD52: P | BE52: =IF($AC52="N", "N", IF($B52="Não", "Sim", IF(OR( BD52=$AC52, AND($AC52="B", OR(BD52="B", BD52="P", BD52="O")), AND($AC52="P", OR(BD52="P", BD52="O")), AND($AC52="O", BD52="O")), "Sim", "Não") ) ) -> Sim | BF52: D | BG52: =IF($Y52="N", "N", IF($B52="Não", "Sim", IF(OR( BF52=$Y52, AND($Y52="B", OR(BF52="B", BF52="P", BF52="O")), AND($Y52="P", OR(BF52="P", BF52="O")), AND($Y52="O", BF52="O")), "Sim", "Não") ) ) -> Sim | BH52: N | BI52: =IF($K52="N", "N", IF($B52="Não", "Sim", IF(OR( BH52=$K52, AND($K52="B", OR(BH52="B", BH52="P", BH52="O")), AND($K52="P", OR(BH52="P", BH52="O")), AND($K52="O", BH52="O")), "Sim", "Não") ) ) -> N | BJ52: D | BK52: =IF($Y52="N", "N", IF($B52="Não", "Sim", IF(OR( BJ52=$Y52, AND($Y52="B", OR(BJ52="B", BJ52="P", BJ52="O")), AND($Y52="P", OR(BJ52="P", BJ52="O")), AND($Y52="O", BJ52="O")), "Sim", "Não") ) ) -> Sim | BL52: D | BM52: =IF($Y52="N", "N", IF($B52="Não", "Sim", IF(OR( BL52=$Y52, AND($Y52="B", OR(BL52="B", BL52="P", BL52="O")), AND($Y52="P", OR(BL52="P", BL52="O")), AND($Y52="O", BL52="O")), "Sim", "Não") ) ) -> Sim | BN52: N | BO52: =IF($AJ52="N", "N", IF($B52="Não", "Sim", IF(OR( BN52=$AJ52, AND($AJ52="B", OR(BN52="B", BN52="P", BN52="O")), AND($AJ52="P", OR(BN52="P", BN52="O")), AND($AJ52="O", BN52="O")), "Sim", "Não") ) ) -> N | BP52: N | BQ52: =IF($T52="N", "N", IF($B52="Não", "Sim", IF(OR( BP52=$T52, AND($T52="B", OR(BP52="B", BP52="P", BP52="O")), AND($T52="P", OR(BP52="P", BP52="O")), AND($T52="O", BP52="O")), "Sim", "Não") ) ) -> N | BR52: N | BS52: =IF($I52="N", "N", IF($B52="Não", "Sim", IF(OR( BR52=$I52, AND($I52="B", OR(BR52="B", BR52="P", BR52="O")), AND($I52="P", OR(BR52="P", BR52="O")), AND($I52="O", BR52="O")), "Sim", "Não") ) ) -> N | BT52: N | BU52: =IF($G52="N", "N", IF($B52="Não", "Sim", IF(OR( BT52=$G52, AND($G52="B", OR(BT52="B", BT52="P", BT52="O")), AND($G52="P", OR(BT52="P", BT52="O")), AND($G52="O", BT52="O")), "Sim", "Não") ) ) -> N | BV52: N | BW52: =IF($G52="N", "N", IF($B52="Não", "Sim", IF(OR( BV52=$G52, AND($G52="B", OR(BV52="B", BV52="P", BV52="O")), AND($G52="P", OR(BV52="P", BV52="O")), AND($G52="O", BV52="O")), "Sim", "Não") ) ) -> N | BX52: N | BY52: =IF($P52="N", "N", IF($B52="Não", "Sim", IF(OR( BX52=$P52, AND($P52="B", OR(BX52="B", BX52="P", BX52="O")), AND($P52="P", OR(BX52="P", BX52="O")), AND($P52="O", BX52="O")), "Sim", "Não") ) ) -> N | BZ52: N | CA52: =IF($G52="N", "N", IF($B52="Não", "Sim", IF(OR( BZ52=$G52, AND($G52="B", OR(BZ52="B", BZ52="P", BZ52="O")), AND($G52="P", OR(BZ52="P", BZ52="O")), AND($G52="O", BZ52="O")), "Sim", "Não") ) ) -> N
